{
    "details": {
        "ಅಂಕಿತ": "ಅಪ್ರಮಾಣಕೂಡಲ ಸಂಗಮದೇವ", 
        "ಒಡಹುಟ್ಟಿದವರು": "--", 
        "ಕಾಯಕ": "ಶ್ರೇಷ್ಠ ಪಂಡಿತ, ಅನುಪಮ ಶಾಸ್ತ್ರಾನುಭಾವಿ", 
        "ಕಾಲ": "1500", 
        "ಕಾಲವಾದ ಸ್ಥಳ": "--", 
        "ಕೃತಿಯ ವೈಶಿಷ್ಟ್ಯ": "ಶುದ್ಧ ತಾತ್ತ್ವಿಕ ಶಾಸ್ತ್ರಕೃತಿ ವೀರಶೈವ ತತ್ತ್ವವಿವೇಚನೆಯೇ ಇದರ ಪರಮ ಗುರಿ. ತಾನು ಹೇಳುವ ಪ್ರತಿಯೊಂದು ವಿಷಯಕ್ಕೂ ಸಂಸ್ಕøತ ಪ್ರಮಾಣ ವಾಕ್ಯಗಳನ್ನು ಈತ ನೀಡಿರುವನು ಹೀಗಾಗಿ ವೇದ ಆಗಮ ಉಪನಿಷತ್ತು ಪ್ರಮಾಣ ಸಂಹಿತೆ ಶೃತಿ ಶ್ಮøತಿ ಸೂಕ್ತ ಮೊದಲಾದವುಗಳಿಂದ ಧಾರಾಳವಾಗಿ ತನ್ನ ವಿಚಾರ ಸಮರ್ಥನೆಗೆ ಉಕ್ತಿಗಳನ್ನು ಎತ್ತಿಕೊಟ್ಟಿರುವನು. ಅನುಭಾವ ಮತ್ತು ಬೆಡಗನ್ನು ಕುರಿತು ಅನೇಕ ವಚನಗಳಿವೆ.", 
        "ಗ್ರಾಮ": "--", 
        "ಜನ್ಮ ಸ್ಥಳ": "--", 
        "ಜಿಲ್ಲೆ": "--", 
        "ತಂದೆ ಹೆಸರು": "--", 
        "ತಾಯಿ ಹೆಸರು": "--", 
        "ತಾಲ್ಲೂಕು": "--", 
        "ಪತಿ: ಪತ್ನಿಯ ಹೆಸರು": "--", 
        "ಮಕ್ಕಳು: ಅವರ ಹೆಸರು": "--", 
        "ಲಭ್ಯ ವಚನಗಳ ಸಂಖ್ಯೆ": "920", 
        "ವಚನಕಾರರ ಹೆಸರು": "ಬಾಲಸಂಗಯ್ಯ ಅಪ್ರಮಾಣ ದೇವ", 
        "ವಚನಗಳಲ್ಲದೆ ಇತರ ಲಭ್ಯ ಕೃತಿಗಳು": "--", 
        "ಸಮಾಧಿ ಇರುವ ಸ್ಥಳ": "--"
    }, 
    "id": "255", 
    "name": "ಬಾಲಸಂಗಯ್ಯ ಅಪ್ರಮಾಣ ದೇವ", 
    "vachana": {
        "18344": "ಶ್ರೀಮನ್ನಿರಾಳ ನಿರಾಲಂಬ ನಿರಂಜನ ನಿರಾಮಯ ನಿರಾಮಯಾತೀತ", 
        "18345": "ಇನ್ನೂರ ಇಪ್ಪತ್ತು ನಾಲ್ಕು ಮಹಾಭುವನಂಗಳ ವಿಸ್ತೀರ್ಣವನು,", 
        "18346": "ಇನ್ನೂರ ಇಪ್ಪತ್ತನಾಲ್ಕು ಭುವನಂಗಳು, ಆ ಭುವನಾಧಿಪತಿಗಳ", 
        "18347": "ಅಂಥ ಬ್ರಹ್ಮಾಂಡವ ಎರಡುಸಾವಿರದ ಹದಿನೆಂಟು", 
        "18348": "ಅಂಥ ಬ್ರಹ್ಮಾಂಡವ ಮೂರುಸಾವಿರದ ಇಪ್ಪತ್ತೆಂಟು", 
        "18349": "ಅಂಥ ಬ್ರಹ್ಮಾಂಡವ ನಾಲ್ಕುಸಾವಿರದ ಮೂತ್ತೆಂಟುಕೋಟಿ", 
        "18350": "ಅಂಥ ಬ್ರಹ್ಮಾಂಡವ ಐದುಸಾವಿರದ ನಾಲ್ವತ್ತೆಂಟುಕೋಟಿ", 
        "18351": "ಅಂಥ ಬ್ರಹ್ಮಾಂಡವ ಆರುಸಾವಿರದೈವತ್ತೆಂಟು", 
        "18352": "ಅಂಥ ಬ್ರಹ್ಮಾಂಡವ ಏಳುಸಾವಿರದ ಅರವತ್ತೆಂಟು", 
        "18353": "ಅಂಥ ಬ್ರಹ್ಮಾಂಡವ ಎಂಟುಸಾವಿರದ ಎಪ್ಪತ್ತೆಂಟು", 
        "18354": "ಅಂಥ ಬ್ರಹ್ಮಾಂಡವ ಒಂಬತ್ತುಸಾವಿರದ ಎಂಬತ್ತೆಂಟು", 
        "18355": "ಅಂಥ ಬ್ರಹ್ಮಾಂಡವ ಹತ್ತು ಸಾವಿರದ ತೊಂಬತ್ತೆಂಟು", 
        "18356": "ಅಂಥ ಬ್ರಹ್ಮಾಂಡವ ಹನ್ನೊಂದುಸಾವಿರದ ನೂರಾಯೆಂಟು", 
        "18357": "ಅಂಥ ಬ್ರಹ್ಮಾಂಡವ ಹನ್ನೆರಡುಸಾವಿರದ ನೂರಾಹದಿನೆಂಟು", 
        "18358": "ಅಂಥ ಬ್ರಹ್ಮಾಂಡವ ಹದಿಮೂರುಸಾವಿರದ ನೂರಾಯಿಪ್ಪತ್ತೆಂಟು", 
        "18359": "ಅಂಥ ಬ್ರಹ್ಮಾಂಡವ ಹದಿನಾಲ್ಕುಸಾವಿರದ ನೂರಾಮೂವತ್ತೆಂಟು", 
        "18360": "ಅಂಥ ಬ್ರಹ್ಮಾಂಡವ ಹದಿನೈದುಸಾವಿರದ ನೂರಾನಾಲ್ವತ್ತೆಂಟು", 
        "18361": "ಅಂಥ ಬ್ರಹ್ಮಾಂಡವ ಹದಿನಾರುಸಾವಿರದ ನೂರಾಐವತ್ತೆಂಟು", 
        "18362": "ಅಂಥ ಬ್ರಹ್ಮಾಂಡವ ಹದಿನೇಳುಸಾವಿರದ ನೂರಾ ಅರವತ್ತೆಂಟು", 
        "18363": "ಅಂಥ ಬ್ರಹ್ಮಾಂಡವ ಹದಿನೆಂಟುಸಾವಿರದ ನೂರಾ ಎಪ್ಪತ್ತೆಂಟು", 
        "18364": "ಅಂಥ ಬ್ರಹ್ಮಾಂಡವ ಹತ್ತೊಂಬತ್ತು ಸಾವಿರದ ನೂರಾ ಎಂಬತ್ತೆಂಟು", 
        "18365": "ಅಂಥ ಬ್ರಹ್ಮಾಂಡವ ಇಪ್ಪತ್ತುಸಾವಿರದ ನೂರಾತೊಂಬತ್ತೆಂಟು", 
        "18366": "ಅಂಥ ಬ್ರಹ್ಮಾಂಡವ ಇಪ್ಪತ್ತೊಂದುಸಾವಿರದ  ಇನ್ನೂರಾ ಎಂಟು", 
        "18367": "ಅಂಥ ಬ್ರಹ್ಮಾಂಡವ ಇಪ್ಪತ್ತೆರಡು ಸಾವಿರದ ಇನ್ನೂರಾಹದಿನೆಂಟು", 
        "18368": "ಅಂಥ ಬ್ರಹ್ಮಾಂಡವ ಇಪ್ಪತ್ತುಮೂರುಸಾವಿರದ ಇನ್ನೂರಾ ಇಪ್ಪತ್ತೆಂಟು", 
        "18369": "ಅಂಥ ಬ್ರಹ್ಮಾಂಡವ ಇಪ್ಪತ್ತುನಾಲ್ಕುಸಾವಿರದ ಇನ್ನೂರ ಮೂವತ್ತೆಂಟು", 
        "18370": "ಅಂಥ ಬ್ರಹ್ಮಾಂಡವ ಇಪ್ಪತ್ತೈದುಸಾವಿರದ ಇನ್ನೂರನಾಲ್ವತ್ತೆಂಟು", 
        "18371": "ಅಂಥ ಬ್ರಹ್ಮಾಂಡವ ಇಪ್ಪತ್ತಾರುಸಾವಿರದ ಇನ್ನೂರ ಐವತ್ತೆಂಟು", 
        "18372": "ಅಂಥ ಬ್ರಹ್ಮಾಂಡವ ಇಪ್ಪತ್ತೇಳುಸಾವಿರದ ಇನ್ನೂರ ಅರವತ್ತೆಂಟು", 
        "18373": "ಅಂಥ ಬ್ರಹ್ಮಾಂಡವ ಇಪ್ಪತ್ತೆಂಟುಸಾವಿರದ ಇನ್ನೂರ ಎಪ್ಪತ್ತೆಂಟು", 
        "18374": "ಅಂಥ ಬ್ರಹ್ಮಾಂಡವ ಇಪ್ಪತ್ತೊಂಬತ್ತು ಸಾವಿರದ ಇನ್ನೂರ ಎಂಬತ್ತೆಂಟು", 
        "18375": "ಅಂಥ ಬ್ರಹ್ಮಾಂಡವ ಮೂವತ್ತುಸಾವಿರ ಇನ್ನೂರತೊಂಬತ್ತೆಂಟು", 
        "18376": "ಅಂಥ ಬ್ರಹ್ಮಾಂಡವ ಮೂವತ್ತೊಂದುಸಾವಿರದ ಮುನ್ನೂರಾ ಎಂಟು", 
        "18377": "ಅಂಥ ಬ್ರಹ್ಮಾಂಡವ ಮೂವತ್ತೆರಡು ಸಾವಿರದಮುನ್ನೂರಹದಿನೆಂಟು", 
        "18378": "ಅಂಥ ಬ್ರಹ್ಮಾಂಡವ ಮೂವತ್ತುಮೂರುಸಾವಿರದ ಮುನ್ನೂರಾಇಪ್ಪತ್ತೆಂಟು", 
        "18379": "ಅಂಥ ಬ್ರಹ್ಮಾಂಡವ ಮೂವತ್ತುನಾಲ್ಕುಸಾವಿರದ ಮುನ್ನೂರಾಮೂವತ್ತೆಂಟು", 
        "18380": "ಅಂಥ ಬ್ರಹ್ಮಾಂಡವ ಮೂವತ್ತೈದುಸಾವಿರದ ಮುನ್ನೂರಾನಾಲ್ವತ್ತೆಂಟು", 
        "18381": "ಅಂಥ ಬ್ರಹ್ಮಾಂಡವ ಮೂವತ್ತಾರುಸಾವಿರದ ಮುನ್ನೂರಾ ಐವತ್ತೆಂಟು", 
        "18382": "ಅಂಥ ಬ್ರಹ್ಮಾಂಡವ ಮೂವತ್ತೇಳುಸಾವಿರದ ಮುನ್ನೂರಾ ಅರವತ್ತೆಂಟು", 
        "18383": "ಅಂಥ ಬ್ರಹ್ಮಾಂಡವ ಮೂವತ್ತೆಂಟುಸಾವಿರದ ಮುನ್ನೂರಾ ಎಪ್ಪತ್ತೆಂಟು", 
        "18384": "ಅಂಥ ಬ್ರಹ್ಮಾಂಡವ ಮೂವತ್ತೊಂಬತ್ತುಸಾವಿರದ", 
        "18385": "ಅಂಥ ಬ್ರಹ್ಮಾಂಡವ ನಾಲ್ವತ್ತುಸಾವಿರದಮುನ್ನೂರಾತೊಂಬತ್ತೆಂಟು", 
        "18386": "ಅಂಥ ಬ್ರಹ್ಮಾಂಡವ ನಾಲ್ವತ್ತೊಂದುಸಾವಿರದನೂರಾಯೆಂಟು", 
        "18387": "ಅಂಥ ಬ್ರಹ್ಮಾಂಡವ ನಾಲ್ವತ್ತೆರಡುಸಾವಿರದ ನೂರಾಹದಿನೆಂಟು", 
        "18388": "ಅಂಥ ಬ್ರಹ್ಮಾಂಡವ ನಾಲ್ವತ್ತುಮೂರುಸಾವಿರದ ನಾನೂರಾ ಇಪ್ಪತ್ತೆಂಟು", 
        "18389": "ಅಂಥ ಬ್ರಹ್ಮಾಂಡವ ನಾಲ್ವತ್ತುನಾಲ್ಕುಸಾವಿರದ ನಾನೂರಾಮೂವತ್ತೆಂಟು", 
        "18390": "ಅಂಥ ಬ್ರಹ್ಮಾಂಡವ ನಾಲ್ವತ್ತೈದು ಸಾವಿರದಾ ನಾನೂರನಾಲ್ವತ್ತೆಂಟು", 
        "18391": "ಅಂಥ ಬ್ರಹ್ಮಾಂಡವ ನಾಲ್ವತ್ತಾರುಸಾವಿರದ ನಾನೂರಾ ಐವತ್ತೆಂಟು", 
        "18392": "ಅಂಥ ಬ್ರಹ್ಮಾಂಡವ ನಾಲ್ವತ್ತೇಳುಸಾವಿರದಾ ನಾನೂರಾ ಅರವತ್ತೆಂಟು", 
        "18393": "ಅಂಥ ಬ್ರಹ್ಮಾಂಡವ ನಾಲ್ವತ್ತೆಂಟುಸಾವಿರದಾ ನಾನೂರ ಎಪ್ಪತ್ತೆಂಟು", 
        "18394": "ಅಂಥ ಬ್ರಹ್ಮಾಂಡವ ನಾಲ್ವತ್ತೊಂಬತ್ತುಸಾವಿರದ ನಾನೂರಾ ಎಂಬತ್ತೆಂಟು", 
        "18395": "ಅಂಥ ಬ್ರಹ್ಮಾಂಡವ ಐವತ್ತುಸಾವಿರದ ನಾನೂರಾ ತೊಂಬತ್ತೆಂಟು", 
        "18396": "ಅಂಥ ಬ್ರಹ್ಮಾಂಡವ ಐವತ್ತೊಂದುಸಾವಿರದ ಐದುನೂರಾಯೆಂಟು", 
        "18397": "ಅಂಥ ಬ್ರಹ್ಮಾಂಡವ ಐವತ್ತೆರಡುಸಾವಿರದ ಐನೂರಾಹದಿನೆಂಟು", 
        "18398": "ಅಂಥ ಬ್ರಹ್ಮಾಂಡವ ಐವತ್ತುಮೂರುಸಾವಿರದ ಐನೂರ ಇಪ್ಪತ್ತೆಂಟು", 
        "18399": "ಅಂಥ ಬ್ರಹ್ಮಾಂಡವ ಐವತ್ತುನಾಲ್ಕು ಸಾವಿರದ ಐನೂರಾ ಮೂವತ್ತೆಂಟು", 
        "18400": "ಅಂಥ ಬ್ರಹ್ಮಾಂಡವ ಐವತ್ತೈದುಸಾವಿರದ ಐನೂರಾ ನಲವತ್ತೆಂಟು", 
        "18401": "ಅಂಥ ಬ್ರಹ್ಮಾಂಡವ ಐವತ್ತಾರುಸಾವಿರದ ಐನೂರಾ ಐವತ್ತೆಂಟು", 
        "18402": "ಅಂಥ ಬ್ರಹ್ಮಾಂಡವ ಐವತ್ತೇಳುಸಾವಿರದ ಐನೂರಾ ಅರವತ್ತೆಂಟು", 
        "18403": "ಅಂಥ ಬ್ರಹ್ಮಾಂಡವ ಐವತ್ತೆಂಟುಸಾವಿರದ ಐನೂರಾ ಎಪ್ಪತ್ತೆಂಟು", 
        "18404": "ಅಂಥ ಬ್ರಹ್ಮಾಂಡವ ಐವತ್ತೊಂಬತ್ತುಸಾವಿರದ ಐನೂರಾ ಎಂಬತ್ತೆಂಟು", 
        "18405": "ಅಂಥ ಬ್ರಹ್ಮಾಂಡವ ಅರುವತ್ತುಸಾವಿರದ ಐನೂರಾ ತೊಂಬತ್ತೆಂಟು", 
        "18406": "ಅಂಥ ಬ್ರಹ್ಮಾಂಡವ ಅರವತ್ತೊಂದುಸಾವಿರದ ಆರುನೂರಾ ಎಂಟು", 
        "18407": "ಅಂಥ ಬ್ರಹ್ಮಾಂಡವ ಅರುವತ್ತೆರಡು ಸಾವಿರದ ಆರುನೂರಾ ಹದಿನೆಂಟು", 
        "18408": "ಅಂಥ ಬ್ರಹ್ಮಾಂಡವ ಅರವತ್ತುಮೂರುಸಾವಿರದ  ಆರುನೂರಾ ಇಪ್ಪತ್ತೆಂಟು", 
        "18409": "ಅಂಥ ಬ್ರಹ್ಮಾಂಡವ ಅರವತ್ತಾ ್ನಲ್ಕು ಸಾವಿರದ ಆರುನೂರಾ ಮೂವತ್ತೆಂಟು", 
        "18410": "ಅಂಥ ಬ್ರಹ್ಮಾಂಡವ ಅರವತ್ತ್ತೈದು ಸಾವಿರದ ಆರುನೂರಾ ನಲವತ್ತೆಂಟು", 
        "18411": "ಅಂಥ ಬ್ರಹ್ಮಾಂಡವ ಅರವತ್ತಾರುಸಾವಿರದ  ಆರುನೂರಾ ಐವತ್ತೆಂಟು", 
        "18412": "ಅಂಥ ಬ್ರಹ್ಮಾಂಡವ ಅರವತ್ತೇಳು ಸಾವಿರದ  ಆರುನೂರಾ ಅರುವತ್ತೆಂಟು", 
        "18413": "ಅಂಥ ಬ್ರಹ್ಮಾಂಡವ ಅರವತ್ತೆಂಟು ಸಾವಿರದ ಆರುನೂರಾ ಎಪ್ಪತ್ತೆಂಟು", 
        "18414": "ಅಂಥ ಬ್ರಹ್ಮಾಂಡವ ಅರವತ್ತೊಂಬತ್ತು ಸಾವಿರದ", 
        "18415": "ಅಂಥ ಬ್ರಹ್ಮಾಂಡವ ಎಪ್ಪತ್ತುಸಾವಿರದ ಆರುನೂರಾ ತೊಂಬತ್ತೆಂಟು", 
        "18416": "ಅಂಥ ಬ್ರಹ್ಮಾಂಡವ ಎಪ್ಪತ್ತೊಂದುಸಾವಿರದ  ಏಳುನೂರಾ ಎಂಟು", 
        "18417": "ಅಂಥ ಬ್ರಹ್ಮಾಂಡವ ಎಪ್ಪತ್ತೆರಡು ಸಾವಿರದಾ ಏಳುನೂರಾ ಹದಿನೆಂಟು", 
        "18418": "ಅಂಥ ಬ್ರಹ್ಮಾಂಡವ ಎಪ್ಪತ್ತುಮೂರುಸಾವಿರದಾ ಏಳುನೂರಾ ಇಪ್ಪತ್ತೆಂಟು", 
        "18419": "ಅಂಥ ಬ್ರಹ್ಮಾಂಡವ ಎಪ್ಪತ್ತುನಾಲ್ಕು ಸಾವಿರದ ಏಳುನೂರಾ ಮೂವತ್ತೆಂಟು", 
        "18420": "ಅಂಥ ಬ್ರಹ್ಮಾಂಡವ ಎಪ್ಪತ್ತೈದುಸಾವಿರದ ಏಳುನೂರಾ ನಲವತ್ತೆಂಟು", 
        "18421": "ಅಂಥ ಬ್ರಹ್ಮಾಂಡವ ಎಪ್ಪತ್ತಾರುಸಾವಿರದಾ ಏಳುನೂರಾ ಐವತ್ತೆಂಟು", 
        "18422": "ಅಂಥ ಬ್ರಹ್ಮಾಂಡವ ಎಪ್ಪತ್ತೇಳು ಸಾವಿರದಾ ಏಳುನೂರಾ ಅರುವತ್ತೆಂಟು", 
        "18423": "ಅಂಥ ಬ್ರಹ್ಮಾಂಡವ ಎಪ್ಪತ್ತೆಂಟು ಸಾವಿರದಾ ಏಳುನೂರಾ ಎಪ್ಪತ್ತೆಂಟು", 
        "18424": "ಅಂಥ ಬ್ರಹ್ರಾಂಡವ ಎಪ್ಪತ್ತೊಂಬತ್ತು ಸಾವಿರದಾ", 
        "18425": "ಅಂಥ ಬ್ರಹ್ಮಾಂಡವ ಎಂಬತ್ತುಸಾವಿರದಾ ಏಳುನೂರಾ ತೊಂಬತ್ತೆಂಟು", 
        "18426": "ಅಂಥ ಬ್ರಹ್ಮಾಂಡವ ಎಂಬತ್ತೊಂದುಸಾವಿರದಾ ಎಂಟನೂರಾ ಎಂಟು", 
        "18427": "ಅಂಥ ಬ್ರಹ್ಮಾಂಡವ ಎಂಬತ್ತೆರಡುಸಾವಿರದಾ ಎಂಟುನೂರಾ ಹದಿನೆಂಟು", 
        "18428": "ಅಂಥ ಬ್ರಹ್ಮಾಂಡವ ಎಂಬತ್ಮೂರುಸಾವಿರದಾ ಎಂಟುನೂರಾ ಇಪ್ಪತ್ತೆಂಟು", 
        "18429": "ಅಂಥ ಬ್ರಹ್ಮಾಂಡವ ಎಂಬತ್ತುನಾಲ್ಕುಸಾವಿರದಾ ಎಂಟುನೂರಾಮೂವತ್ತೆಂಟು", 
        "18430": "ಅಂಥ ಬ್ರಹ್ಮಾಂಡವ ಎಂಬತ್ತೈದುಸಾವಿರದಾ ಎಂಟುನೂರಾ ನಲವತ್ತೆಂಟು", 
        "18431": "ಅಂಥ ಬ್ರಹ್ಮಾಂಡವ ಎಂಬತ್ತಾರುಸಾವಿರದ ಎಂಟುನೂರಾ ಐವತ್ತೆಂಟು", 
        "18432": "ಅಂಥ ಬ್ರಹ್ಮಾಂಡವ ಎಂಬತ್ತೇಳುಸಾವಿರದಾ ಎಂಟುನೂರಾ ಅರುವತ್ತೆಂಟು", 
        "18433": "ಅಂಥ ಬ್ರಹ್ಮಾಂಡವ ಎಂಬತ್ತೆಂಟುಸಾವಿರದ ಎಂಟುನೂರಾ ಎಪ್ಪತ್ತೆಂಟು", 
        "18434": "ಅಂಥ ಬ್ರಹ್ಮಾಂಡವ ಎಂಬತ್ತೊಂಬತ್ತು ಸಾವಿರದ", 
        "18435": "ಅಂಥ ಬ್ರಹ್ಮಾಂಡವ ತೊಂಬತ್ತುಸಾವಿರದ ಎಂಟನೂರಾ ತೊಂಬತ್ತೆಂಟು", 
        "18436": "ಅಂಥ ಬ್ರಹ್ಮಾಂಡವ ತೊಂಬತ್ತೊಂದುಸಾವಿರದ ಒಂಬತ್ತನೂರಾ ಎಂಟು", 
        "18437": "ಅಂಥ ಬ್ರಹ್ಮಾಂಡವ ತೊಂಬತ್ತೆರಡುಸಾವಿರದ ಒಂಬೈನೂರಾ ಹದಿನೆಂಟು", 
        "18438": "ಅಂಥ ಬ್ರಹ್ಮಾಂಡವ ತೊಂಬತ್ತು ಮೂರುಸಾವಿರದ", 
        "18439": "ಅಂಥ ಬ್ರಹ್ಮಾಂಡವ ತೊಂಬತ್ತಾರುಸಾವಿರದ ಒಂಬೈನೂರಾ ಮೂವತ್ತೆಂಟು", 
        "18440": "ಅಂಥ ಬ್ರಹ್ಮಾಂಡವ ತೊಂಬತ್ತೈದುಸಾವಿರದ ಒಂಬೈನೂರ ನಲವತ್ತೆಂಟು", 
        "18441": "ಅಂಥ ಬ್ರಹ್ಮಾಂಡವ ತೊಂಬತ್ತಾರುಸಾವಿರದ ಒಂಬೈನೂರಾ ಐವತ್ತೆಂಟು", 
        "18442": "ಅಂಥ ಬ್ರಹ್ಮಾಂಡವ ತೊಂಬತ್ತೇಳುಸಾವಿರದ ಒಂಬೈನೂರಾ ಅರವತ್ತೆಂಟು", 
        "18443": "ಅಂಥ ಬ್ರಹ್ಮಾಂಡವ ತೊಂಬತ್ತೆಂಟುಸಾವಿರದ ಒಂಬೈನೂರಾ ಎಪ್ಪತ್ತೆಂಟು", 
        "18444": "ಅಂಥ ಬ್ರಹ್ಮಾಂಡವ ತೊಂಬತ್ರೊಂಬತ್ತುಸಾವಿರದ ಒಂಬೈನೂರಾಎಂಬತ್ತೆಂಟು", 
        "18445": "ಅಂಥ ಬ್ರಹ್ಮಾಂಡವ ಲಕ್ಷದ ಮೇಲೆ ಒಂಬೈನೂರಾ ತೊಂಬತ್ತೆಂಟು", 
        "18446": "ಅಂಥ ಬ್ರಹ್ಮಾಂಡವ ಎರಡುಲಕ್ಷದ ಮೇಲೆ ಸಾವಿರದ ಹದಿನೆಂಟು", 
        "18447": "ಅಂಥ ಬ್ರಹ್ಮಾಂಡವ ಮೂರುಲಕ್ಷದ ಮೇಲೆ ಸಾವಿರ ಇಪ್ಪತ್ತೆಂಟು", 
        "18448": "ಅಂಥ ಬ್ರಹ್ಮಾಂಡವ ನಾಲ್ಕು ಲಕ್ಷದ ಮೇಲೆ ಸಾವಿರದ ಮೂವತ್ತೆಂಟು", 
        "18449": "ಅಂಥ ಬ್ರಹ್ಮಾಂಡವ ಐದುಲಕ್ಷದ ಮೇಲೆ ಸಾವಿರದ ನಲವತ್ತೆಂಟು", 
        "18450": "ಅಂಥ ಬ್ರಹ್ಮಾಂಡವ ಆರುಲಕ್ಷದ ಮೇಲೆ ಸಾವಿರದ ಐವತ್ತೆಂಟು", 
        "18451": "ಅಂಥ ಬ್ರಹ್ಮಾಂಡವ ಏಳು ಲಕ್ಷದ ಮೇಲೆ ಸಾವಿರದ ಅರವತ್ತೆಂಟು", 
        "18452": "ಅಂಥ ಬ್ರಹ್ಮಾಂಡವ ಎಂಟುಲಕ್ಷದ ಮೇಲೆ ಸಾವಿರದ ಎಪ್ಪತ್ತೆಂಟು", 
        "18453": "ಅಂಥ ಬ್ರಹ್ಮಾಂಡವ ಒಂಬತ್ತುಲಕ್ಷದ ಮೇಲೆ ಸಾವಿರದ ಎಂಬತ್ತೆಂಟು", 
        "18454": "ಅಂಥ ಬ್ರಹ್ಮಾಂಡವ ಹತ್ತುಲಕ್ಷದ ಮೇಲೆ ಸಾವಿರದ ತೊಂಬತ್ತೆಂಟು", 
        "18455": "ಅಂಥ ಬ್ರಹ್ಮಾಂಡವ ಹನ್ನೊಂದು ಲಕ್ಷದ ಮೇಲೆ ಸಾವಿರದ ನೂರಾ ಎಂಟು", 
        "18456": "ಅಂಥ ಬ್ರಹ್ಮಾಂಡವ ಹನ್ನೆರಡುಲಕ್ಷದ ಮೇಲೆ ಸಾವಿರದನೂರಾಹದಿನೆಂಟು", 
        "18457": "ಅಂಥ ಬ್ರಹ್ಮಾಂಡವ ಹದಿಮೂರುಲಕ್ಷದ ಮೇಲೆ ಸಾವಿರದ ನೂರಿಪ್ಪತ್ತೆಂಟು", 
        "18458": "ಅಂಥ ಬ್ರಹ್ಮಾಂಡವ ಹದಿನಾಲ್ಕುಲಕ್ಷದ ಮೇಲೆ ಸಾವಿರದನೂರಮೂವತ್ತೆಂಟು", 
        "18459": "ಅಂಥ ಬ್ರಹ್ಮಾಂಡವ ಹದಿನೈದುಲಕ್ಷದ ಮೇಲೆ ಸಾವಿರದನೂರಾನಲವತ್ತೆಂಟು", 
        "18460": "ಅಂಥ ಬ್ರಹ್ಮಾಂಡವ ಹದಿನಾರುಲಕ್ಷದ ಮೇಲೆ ಸಾವಿರದ ಐವತ್ತೆಂಟು", 
        "18461": "ಅಂಥ ಬ್ರಹ್ಮಾಂಡವ ಹದಿನೇಳು ಲಕ್ಷದ ಮೇಲೆ ಸಾವಿರದ ಅರವತ್ತೆಂಟು", 
        "18462": "ಅಂಥ ಬ್ರಹ್ಮಾಂಡವ ಹದಿನೆಂಟುಲಕ್ಷದ ಮೇಲೆ", 
        "18463": "ಅಂಥ ಬ್ರಹ್ಮಾಂಡವ ಹತ್ತೊಂಬತ್ತುಲಕ್ಷದ ಮೇಲೆ", 
        "18464": "ಅಂಥ ಬ್ರಹ್ಮಾಂಡವ ಇಪ್ಪತ್ತುಲಕ್ಷದ ಮೇಲೆ ಸಾವಿರದ ನೂರಾತೊಂಬತ್ತೆಂಟು", 
        "18465": "ಅಂಥ ಬ್ರಹ್ಮಾಂಡವ ಇಪ್ಪತ್ತೊಂದುಲಕ್ಷದ ಮೇಲೆ ಸಾವಿರದಿನ್ನೂರಾಯೆಂಟು", 
        "18466": "ಅಂಥ ಬ್ರಹ್ಮಾಂಡವ ಇಪ್ಪತ್ತೆರಡುಲಕ್ಷದ ಮೇಲೆ", 
        "18467": "ಅಂಥ ಬ್ರಹ್ಮಾಂಡವ ಇಪ್ಪತ್ಮೂರುಲಕ್ಷದ ಮೇಲೆ", 
        "18468": "ಅಂಥ ಬ್ರಹ್ಮಾಂಡವ ಇಪ್ಪತ್ನಾಲ್ಕುಲಕ್ಷದ ಮೇಲೆ", 
        "18469": "ಅಂಥ ಬ್ರಹ್ಮಾಂಡವ ಇಪ್ಪತ್ತೈದುಲಕ್ಷದ ಮೇಲೆ", 
        "18470": "ಅಂಥ ಬ್ರಹ್ಮಾಂಡವ ಇಪ್ಪತ್ತಾರುಲಕ್ಷದ ಮೇಲೆ", 
        "18471": "ಅಂಥ ಬ್ರಹ್ಮಾಂಡವ ಇಪ್ಪತ್ತೇಳುಲಕ್ಷದ ಮೇಲೆ", 
        "18472": "ಅಂಥ ಬ್ರಹ್ಮಾಂಡವ ಇಪ್ಪತ್ತೆಂಟುಲಕ್ಷದ ಮೇಲೆ", 
        "18473": "ಅಂಥ ಬ್ರಹ್ಮಾಂಡವ ಇಪ್ಪತ್ತೊಂದುಲಕ್ಷದ ಮೇಲೆ", 
        "18474": "ಅಂಥ ಬ್ರಹ್ಮಾಂಡವ ಮೂವತ್ತುಲಕ್ಷದ ಮೇಲೆ", 
        "18475": "ಅಂಥ ಬ್ರಹ್ಮಾಂಡವ ಮೂವತ್ತೊಂದುಲಕ್ಷದ ಮೇಲೆ", 
        "18476": "ಅಂಥ ಬ್ರಹ್ಮಾಂಡವ ಮೂವತ್ತೆರಡುಲಕ್ಷದ ಮೇಲೆ", 
        "18477": "ಅಂಥ ಬ್ರಹ್ಮಾಂಡವ ಮೂವತ್ತು  ಮೂರುಲಕ್ಷದ ಮೇಲೆ", 
        "18478": "ಅಂಥ ಬ್ರಹ್ಮಾಂಡವ ಮೂವತ್ತುನಾಲ್ಕುಲಕ್ಷದ ಮೇಲೆ", 
        "18479": "ಅಂಥ ಬ್ರಹ್ಮಾಂಡವ ಮೂವತ್ತೈದುಲಕ್ಷದ ಮೇಲೆ", 
        "18480": "ಅಂಥ ಬ್ರಹ್ಮಾಂಡವ ಮೂವತ್ತಾರುಲಕ್ಷದ ಮೇಲೆ", 
        "18481": "ಅಂಥ ಬ್ರಹ್ಮಾಂಡವ ಮೂವತ್ತೇಳುಲಕ್ಷದ ಮೇಲೆ", 
        "18482": "ಅಂಥ ಬ್ರಹ್ಮಾಂಡವ ಮೂವತ್ತೆಂಟುಲಕ್ಷದ ಮೇಲೆ", 
        "18483": "ಅಂಥ ಬ್ರಹ್ಮಾಂಡವ ಮೂವತ್ತೊಂಬತ್ತುಲಕ್ಷದ ಮೇಲೆ", 
        "18484": "ಅಂಥ ಬ್ರಹ್ಮಾಂಡವ ನಾಲ್ವತ್ತುಲಕ್ಷದ ಮೇಲೆ", 
        "18485": "ಅಂಥ ಬ್ರಹ್ಮಾಂಡವ ನಾಲ್ವತ್ತೊಂದುಲಕ್ಷದ ಮೇಲೆ", 
        "18486": "ಅಂಥ ಬ್ರಹ್ಮಾಂಡವ ನಾಲ್ವತ್ತೆರಡುಲಕ್ಷದ ಮೇಲೆ", 
        "18487": "ಅಂಥ ಬ್ರಹ್ಮಾಂಡವ ನಾಲ್ವತ್ಮೂರುಲಕ್ಷದ ಮೇಲೆ", 
        "18488": "ಅಂಥ ಬ್ರಹ್ಮಾಂಡವ ನಾಲವತ್ತುನಾಲ್ಕುಲಕ್ಷದ ಮೇಲೆ", 
        "18489": "ಅಂಥ ಬ್ರಹ್ಮಾಂಡವ ನಾಲವತ್ತೈದುಲಕ್ಷದ ಮೇಲೆ", 
        "18490": "ಅಂಥ ಬ್ರಹ್ಮಾಂಡವ ನಾಲವತ್ತಾರುಲಕ್ಷದ ಮೇಲೆ", 
        "18491": "ಅಂಥ ಬ್ರಹ್ಮಾಂಡವ ನಾಲವತ್ತೇಳು ಲಕ್ಷದ ಮೇಲೆ", 
        "18492": "ಅಂಥ ಬ್ರಹ್ಮಾಂಡವ ನಾಲವತ್ತೆಂಟುಲಕ್ಷದ ಮೇಲೆ", 
        "18493": "ಅಂಥ ಬ್ರಹ್ಮಾಂಡವ ನಾಲವತ್ತೊಂಬತ್ತುಲಕ್ಷದ ಮೇಲೆ", 
        "18494": "ಅಂಥ ಬ್ರಹ್ಮಾಂಡವ ಐವತ್ತುಲಕ್ಷದ ಮೇಲೆ", 
        "18495": "ಅಂಥ ಬ್ರಹ್ಮಾಂಡವ ಐವತ್ತೊಂದುಲಕ್ಷದ ಮೇಲೆ", 
        "18496": "ಅಂಥ ಬ್ರಹ್ಮಾಂಡವ ಐವತ್ತೆರಡುಲಕ್ಷದ ಮೇಲೆ", 
        "18497": "ಅಂಥ ಬ್ರಹ್ಮಾಂಡವ ಐವತ್ಮೂರುಲಕ್ಷದ ಮೇಲೆ", 
        "18498": "ಅಂಥ ಬ್ರಹ್ಮಾಂಡವ ಐವತ್ತುನಾಲ್ಕುಲಕ್ಷದ ಮೇಲೆ", 
        "18499": "ಅಂಥ ಬ್ರಹ್ಮಾಂಡವ ಐವತ್ತೈದುಲಕ್ಷದ ಮೇಲೆ", 
        "18500": "ಅಂಥ ಬ್ರಹ್ಮಾಂಡವ ಐವತ್ತಾರುಲಕ್ಷದ ಮೇಲೆ", 
        "18501": "ಅಂಥ ಬ್ರಹ್ಮಾಂಡವ ಐವತ್ತೇಳುಲಕ್ಷದ ಮೇಲೆ", 
        "18502": "ಅಂಥ ಬ್ರಹ್ಮಾಂಡವ ಐವತ್ತೆಂಟುಲಕ್ಷದ ಮೇಲೆ", 
        "18503": "ಅಂಥ ಬ್ರಹ್ಮಾಂಡವ ಐವತ್ತೊಂಬತ್ತು ಲಕ್ಷದ ಮೇಲೆ", 
        "18504": "ಅಂಥ ಬ್ರಹ್ಮಾಂಡವ ಅರುವತ್ತು  ಲಕ್ಷದ ಮೇಲೆ", 
        "18505": "ಅಂಥ ಬ್ರಹ್ಮಾಂಡವ ಅರುವತ್ತೊಂದು ಲಕ್ಷದ ಮೇಲೆ", 
        "18506": "ಅಂಥ ಬ್ರಹ್ಮಾಂಡವ ಅರುವತ್ತೆರಡು ಲಕ್ಷದ ಮೇಲೆ", 
        "18507": "ಅಂಥ ಬ್ರಹ್ಮಾಂಡವ ಅರುವತ್ಮೂರುಲಕ್ಷದ ಮೇಲೆ", 
        "18508": "ಅಂಥ ಬ್ರಹ್ಮಾಂಡವ ಅರುವತ್ನಾಲ್ಕುಲಕ್ಷದ ಮೇಲೆ", 
        "18509": "ಅಂಥ ಬ್ರಹ್ಮಾಂಡವ ಅರುವತ್ತೈದುಲಕ್ಷದ ಮೇಲೆ", 
        "18510": "ಅಂಥ ಬ್ರಹ್ಮಾಂಡವ ಅರುವತ್ತಾರುಲಕ್ಷದ ಮೇಲೆ", 
        "18511": "ಅಂಥ ಬ್ರಹ್ಮಾಂಡವ ಅರುವತ್ತೇಳು ಲಕ್ಷದ ಮೇಲೆ", 
        "18512": "ಅಂಥ ಬ್ರಹ್ಮಾಂಡವ ಅರುವತ್ತೆಂಟುಲಕ್ಷದ ಮೇಲೆ", 
        "18513": "ಅಂಥ ಬ್ರಹ್ಮಾಂಡವ ಅರುವತ್ತೊಂಬತ್ತು ಲಕ್ಷದ ಮೇಲೆ", 
        "18514": "ಅಂಥ ಬ್ರಹ್ಮಾಂಡವ ಎಪ್ಪತ್ತುಲಕ್ಷದ ಮೇಲೆ", 
        "18515": "ಅಂಥ ಬ್ರಹ್ಮಾಂಡವ ಎಪ್ಪತ್ತೊಂದು ಲಕ್ಷದ ಮೇಲೆ", 
        "18516": "ಅಂಥ ಬ್ರಹ್ಮಾಂಡವ ಎಪ್ಪತ್ತೆರಡುಲಕ್ಷದ ಮೇಲೆ", 
        "18517": "ಅಂಥ ಬ್ರಹ್ಮಾಂಡವ ಎಪ್ಪತ್ಮೂರುಲಕ್ಷದ ಮೇಲೆ", 
        "18518": "ಅಂಥ ಬ್ರಹ್ಮಾಂಡವ ಎಪ್ಪತ್ತುನಾಲ್ಕುಲಕ್ಷದ ಮೇಲೆ", 
        "18519": "ಅಂಥ ಬ್ರಹ್ಮಾಂಡವ ಎಪ್ಪತ್ತೈದುಲಕ್ಷದ ಮೇಲೆ", 
        "18520": "ಅಂಥ ಬ್ರಹ್ಮಾಂಡವ ಎಪ್ಪತ್ತಾರುಲಕ್ಷದ ಮೇಲೆ", 
        "18521": "ಅಂಥ ಬ್ರಹ್ಮಾಂಡವ ಎಪ್ಪತ್ತೇಳುಲಕ್ಷದ ಮೇಲೆ", 
        "18522": "ಅಂಥ ಬ್ರಹ್ಮಾಂಡವ ಎಪ್ಪತ್ತೆಂಟುಲಕ್ಷದ ಮೇಲೆ", 
        "18523": "ಅಂಥ ಬ್ರಹ್ಮಾಂಡವ ಎಪ್ಪತ್ತೊಂಬತ್ತುಲಕ್ಷದ ಮೇಲೆ", 
        "18524": "ಅಂಥ ಬ್ರಹ್ಮಾಂಡವ ಎಂಬತ್ತುಲಕ್ಷದ ಮೇಲೆ", 
        "18525": "ಅಂಥ ಬ್ರಹ್ಮಾಂಡವ ಎಂಬತ್ತೊಂದುಲಕ್ಷದ ಮೇಲೆ", 
        "18526": "ಅಂಥ ಬ್ರಹ್ಮಾಂಡವ ಎಂಬತ್ತೆರಡು ಲಕ್ಷದ ಮೇಲೆ", 
        "18527": "ಅಂಥ ಬ್ರಹ್ಮಾಂಡವ ಎಂಬತ್ತುಮೂರುಲಕ್ಷದ ಮೇಲೆ", 
        "18528": "ಅಂಥ ಬ್ರಹ್ಮಾಂಡವ ಎಂಬತ್ತುನಾಲ್ಕುಲಕ್ಷದ ಮೇಲೆ", 
        "18529": "ಅಂಥ ಬ್ರಹ್ಮಾಂಡವ ಎಂಬತ್ತೈದುಲಕ್ಷದ ಮೇಲೆ", 
        "18530": "ಅಂಥ ಬ್ರಹ್ಮಾಂಡವ ಎಂಬತ್ತಾರುಲಕ್ಷದ ಮೇಲೆ", 
        "18531": "ಅಂಥ ಬ್ರಹ್ಮಾಂಡವ ಎಂಬತ್ತೇಳು ಲಕ್ಷದ ಮೇಲೆ", 
        "18532": "ಅಂಥ ಬ್ರಹ್ಮಾಂಡವ ಎಂಬತ್ತೆಂಟು ಲಕ್ಷದ ಮೇಲೆ", 
        "18533": "ಅಂಥ ಬ್ರಹ್ಮಾಂಡವ ಎಂಬತ್ತೊಂಬತ್ತು ಲಕ್ಷದ ಮೇಲೆ", 
        "18534": "ಅಂಥ ಬ್ರಹ್ಮಾಂಡವ  ತೊಂಬತ್ತು  ಲಕ್ಷದ ಮೇಲೆ", 
        "18535": "ಅಂಥ ಬ್ರಹ್ಮಾಂಡವ ತೊಂಬತ್ತೊಂದು ಲಕ್ಷದ ಮೇಲೆ", 
        "18536": "ಅಂಥ ಬ್ರಹ್ಮಾಂಡವ ತೊಂಬತ್ತೆರಡು ಲಕ್ಷದ ಮೇಲೆ", 
        "18537": "ಅಂಥ ಬ್ರಹ್ಮಾಂಡವ ತೊಂಬತ್ತು ಮೂರು ಲಕ್ಷದ ಮೇಲೆ", 
        "18538": "ಅಂಥ ಬ್ರಹ್ಮಾಂಡವ ತೊಂಬತ್ನಾಲ್ಕು ಲಕ್ಷದ ಮೇಲೆ", 
        "18539": "ಅಂಥ ಬ್ರಹ್ಮಾಂಡವ ತೊಂಬತ್ತೈದು ಲಕ್ಷದ ಮೇಲೆ", 
        "18540": "ಅಂಥ ಬ್ರಹ್ಮಾಂಡವ ತೊಂಬತ್ತಾರು ಲಕ್ಷದ ಮೇಲೆ", 
        "18541": "ಅಂಥ ಬ್ರಹ್ಮಾಂಡವ ತೊಂಬತ್ತೇಳು ಲಕ್ಷದ ಮೇಲೆ", 
        "18542": "ಅಂಥ ಬ್ರಹ್ಮಾಂಡವ  ತೊಂಬತ್ತೇಳು ಲಕ್ಷದ ಮೇಲೆ", 
        "18543": "ಅಂಥ ಬ್ರಹ್ಮಾಂಡವ ತೊಂಬತ್ತೊಂಬತ್ತು ಲಕ್ಷದ ಮೇಲೆ", 
        "18544": "ಅಂಥ ಬ್ರಹ್ಮಾಂಡವ ಒಂದುಕೋಟಿಯ ಮೇಲೆ", 
        "18545": "ಅಂಥ ಬ್ರಹ್ಮಾಂಡವ ಎರಡುಕೋಟಿಯ ಮೇಲೆ", 
        "18546": "ಅಂಥ ಬ್ರಹ್ಮಾಂಡವ ಮೂರುಕೋಟಿಯ ಮೇಲೆ", 
        "18547": "ಅಂಥ ಬ್ರಹ್ಮಾಂಡವ ನಾಲ್ಕುಕೋಟಿಯ ಮೇಲೆ", 
        "18548": "ಅಂಥ ಬ್ರಹ್ಮಾಂಡವ ಐದುಕೋಟಿಯ ಮೇಲೆ", 
        "18549": "ಅಂಥ ಬ್ರಹ್ಮಾಂಡವ  ಆರುಕೋಟಿಯ ಮೇಲೆ", 
        "18550": "ಅಂಥ ಬ್ರಹ್ಮಾಂಡವ ಏಳುಕೋಟಿಯ ಮೇಲೆ", 
        "18551": "ಅಂಥ ಬ್ರಹ್ಮಾಂಡವ ಎಂಟುಕೋಟಿಯ ಮೇಲೆ", 
        "18552": "ಅಂಥ ಬ್ರಹ್ಮಾಂಡವ ಒಂಬತ್ತುಕೋಟಿಯ ಮೇಲೆ", 
        "18553": "ಅಂಥ ಬ್ರಹ್ಮಾಂಡವ ಹತ್ತುಕೋಟಿಯ ಮೇಲೆ", 
        "18554": "ಅಂಥ ಬ್ರಹ್ಮಾಂಡವ ಇಪ್ಪತ್ತುಕೋಟಿಯ ಮೇಲೆ", 
        "18555": "ಅಂಥ ಬ್ರಹ್ಮಾಂಡವ ಮೂವತ್ತುಕೋಟಿಯ ಮೇಲೆ", 
        "18556": "ಅಂಥ ಬ್ರಹ್ಮಾಂಡವ ನಾಲ್ವತ್ತು ಕೋಟಿಯ ಮೇಲೆ", 
        "18557": "ಅಂಥ ಬ್ರಹ್ಮಾಂಡವ ಐವತ್ತು ಕೋಟಿಯ ಮೇಲೆ", 
        "18558": "ಅಂಥ ಬ್ರಹ್ಮಾಂಡವ ಅರುವತ್ತುಕೋಟಿಯ ಮೇಲೆ", 
        "18559": "ಅಂಥ ಬ್ರಹ್ಮಾಂಡವ ಎಪ್ಪತ್ತುಕೋಟಿಯ ಮೇಲೆ", 
        "18560": "ಅಂಥ ಬ್ರಹ್ಮಾಂಡವ ಎಂಬತ್ತುಕೋಟಿಯ ಮೇಲೆ", 
        "18561": "ಅಂಥ ಬ್ರಹ್ಮಾಂಡವ ತೊಂಬತ್ತುಕೋಟಿಯ ಮೇಲೆ", 
        "18562": "ಅಂಥ ಬ್ರಹ್ಮಾಂಡವ ನೂರುಕೋಟಿಯ ಮೇಲೆ", 
        "18563": "ಅಂಥ ಬ್ರಹ್ಮಾಂಡವ ಇನ್ನೂರು ಕೋಟಿಯ ಮೇಲೆ", 
        "18564": "ಅಂಥ  ಬ್ರಹ್ಮಾಂಡವ ಮುನ್ನೂರುಕೋಟಿಯ ಮೇಲೆ", 
        "18565": "ಅಂಥ ಬ್ರಹ್ಮಾಂಡವ ನಾಲ್ಕುನೂರು ಕೋಟಿಯ ಮೇಲೆ", 
        "18566": "ಅಂಥ ಬ್ರಹ್ಮಾಂಡವ ಅನಂತಕೋಟಿ ಬ್ರಹ್ಮಾಂಡವನೊಳಕೊಂಡುದೊಂದು", 
        "18567": "ಅಂಥ ಬ್ರಹ್ಮಾಂಡವ ಅನಂತಕೋಟಿಯನೊಳಕೊಂಡ", 
        "18568": "ಇನ್ನು ಆದಿಮೂಲ ಅನಾದಿಮೂಲಗಳಿಗತ್ತತ್ತವಾದ", 
        "18569": "ಆ ಅಖಂಡ ಮಹಾಮೂಲಸ್ವಾಮಿಯ", 
        "18570": "ಆ ಅಖಂಡ ಮಹಾಮೂಲಸ್ವಾಮಿಯ ಸ್ಥಲದ", 
        "18571": "ಇನ್ನು ನಿರಂಜನಾತೀತಪ್ರಣವ ಮೊದಲಾಗಿ ಬ್ರಹ್ಮ ಕಡೆಯಾಗಿ", 
        "18572": "ಆ ಆದಿ ಪ್ರಣವದ ನೆನಹುಮಾತ್ರದಲ್ಲಿಯೇ", 
        "18573": "ಇದಕ್ಕೆ ಪ್ರಣವೋಪನಿಷತ್ತು :", 
        "18574": "ಇನ್ನು ಆ ಆದಿ ಉಕಾರ ಪ್ರಣವ, ಆದಿ ಮಕಾರ ಪ್ರಣವ,", 
        "18575": "ಇದಕ್ಕೆ ಮಹದೋಂಕಾರೋಪನಿಷತ್ತು :", 
        "18576": "ಇನ್ನು ಆ ಆದಿ ಮಕಾರಪ್ರಣವ, ಆದಿ ಅಕಾರಪ್ರಣವ,", 
        "18577": "ದಂಡಶ್ಚ ತಾರಕಾಕಾರೋ ಭವತಿ | ಓಂ ಸಾರ್ವತ್ಮಾ ದೇವತಾ |", 
        "18578": "ಇನ್ನು ಅಖಂಡಮಹಾಜ್ಯೋತಿಪ್ರಣವದ", 
        "18579": "ಇನ್ನು ಲಿಂಗೋತ್ಪತ್ಯವದೆಂತೆಂದಡೆ :", 
        "18580": "ಇನ್ನು ಲಿಂಗಗರ್ಭದಲ್ಲಿ ಅನೇಕ ಕೋಟಿ ತತ್ವಂಗಳು,", 
        "18581": "ಇನ್ನು ಅಖಂಡಪರಿಪೂರ್ಣ ಅಪ್ರಮಾಣ ಅಗೋಚರ ಅಪ್ರಮೇಯ", 
        "18582": "ಪಂಚಮುಖ ದಶಭುಜವನುಳ್ಳ ಸದಾಶಿವನ ನಿರ್ಭಾವಮುಖದಲ್ಲಿ", 
        "18583": "ಆ ಮಹಾಸದಾಶಿವತತ್ವದಲ್ಲಿ ಸದಾಶಿವನುತ್ಪತ್ಯವಾಗಿ", 
        "18584": "ಇನ್ನು ವಿಶ್ವಾಧಿಕ ಮಹಾರುದ್ರನುತ್ಪತ್ಯವೆಂತೆಂದಡೆ :", 
        "18585": "ಇನ್ನು ಬ್ರಹ್ಮಾಂಡಕಪಾಲದೊಳಗಣ ಸೃಷ್ಟಿಯ ವಿಸ್ತೀರ್ಣವದೆಂತೆಂದಡೆ :", 
        "18586": "ಆ ಮಹಾಸದಾಶಿವ ತತ್ವದ", 
        "18587": "ಆ ಪೃಥ್ವಿ ಅಪ್ಪು ತೇಜ ವಾಯುವಾಕಾಶವೆಂಬ", 
        "18588": "ಇನ್ನು ಪಿಂಡ ಉತ್ಪತ್ಯವದೆಂತೆಂದಡೆ :", 
        "18589": "ಇನ್ನು ಸ್ತ್ರೀಯರುಗಳಿಂದ ಜನನವಾದ ಶಿಶುಗಳ ಭೇದವಂ ಪೇಳ್ವೆ", 
        "18590": "ಇನ್ನು ಸ್ತ್ರೀ ಪುರುಷರುಗಳ ಕೂಟದ ಸ್ವರಭೇದವದೆಂತೆಂದಡೆ :", 
        "18591": "ಇನ್ನು ಕಾಲಭೇದಂಗಳದೆಂತೆಂದಡೆ :", 
        "18592": "ಇನ್ನು ವರ್ಣಭೇದವೆಂತೆಂದಡೆ :", 
        "18593": "ಇನ್ನು ಆಯುಷ್ಯಂಗಳ ಭೇದವೆಂತೆಂದಡೆ :", 
        "18594": "ಇನ್ನು ಆ ಶುಕ್ಲ ಸ್ತ್ರೀ ಪುರುಷರ ಸಂಯೋಗದಿಂದ", 
        "18595": "ಆ ಚೈತನ್ಯಬೀಜ ಶುಕ್ಲಶೋಣಿತ ಬಲಿತು ಜೀವನಾಗಿ", 
        "18596": "ಏಕರಾತ್ರಿಗೆ ಹಾಲಿಗೆ ಹೆಪ್ಪ ಕೊಟ್ಟ ಹಾಗೆ ಕದಡಿಕೊಂಡಿಹುದು.", 
        "18597": "ಪಂಚವಿಂಶತಿರಾತ್ರಿಗೆ ಪಂಚಾಂಕುರ ಸಂಪೂರ್ಣವಹುದು.", 
        "18598": "ತ್ರಿಮಾಸಕ್ಕೆ ಮಜ್ಜೆ ಅಸ್ಥಿ ಪುಟ್ಟುವುದು.", 
        "18599": "ಷಷ್ಠಿಮಾಸಕ್ಕೆ ಕಂಧರ ಉದರ ಪುಟ್ಟುವುದು.", 
        "18600": "ನವಮಾಸಕ್ಕೆ ಶ್ರೋತ್ರಾದಿಗಳೈದು, ಶಬ್ದಾದಿಗಳೈದು,", 
        "18601": "ಇನ್ನು ಪ್ರಸೂತಿಕಾಲದಲ್ಲಿ ವಾಯುವಶದಿಂದ", 
        "18602": "ಸುಕರ್ಮದಿಂದ ದೇವತಾಯೋನಿಯಲ್ಲಿ ಜನಿಸುವನು.", 
        "18603": "ಸ್ಥೂಲಕಾಯ ಶರೀರ ಶುಕ್ಲಶೋಣಿತದಿಂದ", 
        "18604": "ಸಪ್ತಧಾತುಗಳಿಂದ ದೇಹವಾಗಿ ಬೆಳೆದ ಪಿಂಡ", 
        "18605": "ಇನ್ನು ಸಪ್ತಕುಲಪರ್ವತಂಗಳ ಸ್ಥಾನವದೆಂತೆಂದಡೆ :", 
        "18606": "ಇನ್ನು ಸಪ್ತದ್ವೀಪಂಗಳ ಸ್ಥಾನವದೆಂತೆಂದಡೆ :", 
        "18607": "ಇನ್ನು ಸಪ್ತಸಮುದ್ರಂಗಳ ವಿವರವೆಂತೆಂದಡೆ :", 
        "18608": "ಇನ್ನು ಸಪ್ತಸಮುದ್ರಂಗಳ, ಸಪ್ತದ್ವೀಪಂಗಳ,", 
        "18609": "ಇನ್ನು ನಕ್ಷತ್ರ ನವಗ್ರಹಗಳ ಸ್ಥಾನವೆಂತೆಂದಡೆ :", 
        "18610": "ಇನ್ನು  ಭೂತನಾಯಕರ ಸ್ಥಾನವೆಂತೆಂದಡೆ :", 
        "18611": "ಇನ್ನು ಆ ಪಿಂಡಮಧ್ಯದಲ್ಲಿಹ ಷಡುಚಕ್ರಂಗಳೊಳು", 
        "18612": "ಇನ್ನು ಆ ಆತ್ಮನು ಪೃಥ್ವಿ ಅಪ್ಪು ತೇಜ", 
        "18613": "ಇಂತಪ್ಪ ನಾನಾ ಸುಖದುಃಖಂಗಳನುಂಡು,", 
        "18614": "ಇನ್ನು ನಾಡಿಧಾರಣವೆಂತೆಂದಡೆ :", 
        "18615": "ಅದೊಂದು ನಾಡಿ ಮೂಲಾಧಾರ ಮೊದಲಾಗಿ", 
        "18616": "ಕಾಲು ಕೈ ನಡುವೆಲ್ಲ ತಾವರೆಯ ತಂತಿನಂತೆ", 
        "18617": "ಭಾನುಕಿರಣಂಗಳು ಸರ್ವರ್ಲೋಕಂಗಳ ತುಂಬಿಕೊಂಡಿಹುದು.", 
        "18618": "ಅಗ್ನಿಮಂಡಲ, ಆದಿತ್ಯಮಂಡಲ, ಚಂದ್ರಮಂಡಲವೆಂಬ", 
        "18619": "ಎಲ್ಲಾ  ನಾಡಿಗಳಂ ಕೆಡೆಮೆಟ್ಟಿ", 
        "18620": "ನಾಡಿಗಳು ಚರಿಸುವ ಭೇದವನರಿದು", 
        "18621": "ತಿಲದೊಳಗಣ ತೈಲದಂತೆ, ಕ್ಷೀರದೊಳಗಣ ಘೃತದಂತೆ,", 
        "18622": "ಇನ್ನು ವಾಯುಧಾರಣೆ ಎಂತೆಂದಡೆ :", 
        "18623": "ಎಂಬತ್ತೆಂಟು ಕೋಟಿ ರೋಮದ್ವಾರಂಗಳಲ್ಲಿ ಚರಿಸುವ", 
        "18624": "ಪಿಂಗಳನಾಳವಮುಚ್ಚಿ ಇಡಾನಾಳದಲ್ಲಿ  ತೆಗೆದು,", 
        "18625": "ರೇಚಿಸಿ ರೇಚಿಸಿ ಪೂರಿಸಲು", 
        "18626": "ರೇಚಕ ಪೂರಕಮಂ ಬಿಟ್ಟು ಕುಂಭಕವಾಗಿ", 
        "18627": "ಆ ವಾಯುವಿಶಾಲವನರಿದು ನಿಲಿಸಿದಡೆ", 
        "18628": "ಸಕಲ ವೇದಾಗಮ ಶಾಸ್ತ್ರ ಪುರಾಣಂಗಳೆಲ್ಲ", 
        "18629": "ಹೋಹ ವಾಯುವಂ ಹೋಗಲೀಯದೆ ನಿಲಿಸಿ,", 
        "18630": "ಮುಂದೆ ಅನಂತಕೋಟಿ ಕಾಲ ತಪವ ಮಾಡಿದಾತಂಗಲ್ಲದೆ", 
        "18631": "ಇನ್ನು ಅಗ್ನಿಧಾರಣವೆಂತೆಂದಡೆ :", 
        "18632": "ಕಾಲಾಗ್ನಿಯನೆಬ್ಬಿಸಿ, ಕಮಲನಾಳದ ತುದಿಯನಡರಿ,", 
        "18633": "ಮಹಾವಾಯುವಂ ಪಿಡಿದು ಬಹುಮೂಲಜ್ವಾಲೆಯನೆಬ್ಬಿಸಿ,", 
        "18634": "ಪರದಲ್ಲಿ ಮನವ ಶಿಲ್ಕಿಸಿ", 
        "18635": "ಮೂಲಾಧಾರವನೊತ್ತಿ  ಮೂಲಾಗ್ನಿಯನೆಬ್ಬಿಸಿ,", 
        "18636": "ಇನ್ನು ಅಮೃತಧಾರಣವದೆಂತೆಂದಡೆ :", 
        "18637": "ತ್ರಿಕಲೆ ದ್ವಾದಶಕಲೆ ಷೋಡಶಕಲೆಗಳೆಂಬ", 
        "18638": "ಜ್ಞಾನಸ್ವರೂಪವಾಗಿ ಮಹಾಜ್ಯೋತಿರ್ಮಯಲಿಂಗವೆಂಬ", 
        "18639": "ಇನ್ನು ಆಧಾರ ಧಾರಣವೆಂತೆಂದಡೆ :", 
        "18640": "ಸ್ವಾಧಿಷ್ಠಾನಚಕ್ರದ ಷಡುದಳಪದ್ಮವ ಪೆÇಕ್ಕು ಸಾಧಿಸಿ,", 
        "18641": "ಮಣಿಪೂರಕಚಕ್ರದ ದಶದಳ ಪದ್ಮವ ಪೆÇಕ್ಕು ಸಾಧಿಸಿ,", 
        "18642": "ಆ ಅನಾಹತಚಕ್ರದ ದ್ವಾದಶದಳದ ಪದ್ಮವ ಪೆÇಕ್ಕು ಸಾಧಿಸಿ,", 
        "18643": "ಆ [ವಿಶುದ್ದಿಚಕ್ರದ] ಷೋಡಶದಳಪದ್ಮವ ಪೆÇಕ್ಕುನೋಡಿ ಸಾಧಿಸಿ,", 
        "18644": "ಆ  [ಆಜ್ಞಾಚಕ್ರದ]  ದ್ವಿದಳಪದ್ಮವ ಹೊಕ್ಕು ನೋಡಿ ಸಾಧಿಸಿ,", 
        "18645": "ಆ ಸಹಸ್ರದಳ ಪದ್ಮವ ಪೆÇಕ್ಕು ನೋಡಿ ಸಾಧಿಸಿ,", 
        "18646": "ಇನ್ನು ನಿರಾಧಾರಧಾರಣವೆಂತೆಂದಡೆ :", 
        "18647": "ಜೀವನೆಂಬ ಶಿವಾಲಯದೊಳು", 
        "18648": "ಎನ್ನ ದೇಹವೆಂಬ ಪ್ರಾಕಾರದೊಳು", 
        "18649": "ಬಿಂದುವೆ ಪೀಠ, ನಾದವೇ ಲಿಂಗ,", 
        "18650": "ಓಂಕಾರವೇ ಪೀಠ, ಅಕಾರವೇ ಕಂಠ,", 
        "18651": "ಓಂಕಾರದ ಪೀಠದ ಮೇಲೆ", 
        "18652": "ನಾಡಿಧಾರಣ ವಾಯುಧಾರಣ ಅಗ್ನಿಧಾರಣ", 
        "18653": "ಆ ಸದ್ಗುರುಸ್ವಾಮಿಯ ಕಂಡು", 
        "18654": "ಮತ್ತಂ, ಆ ಶಿಷ್ಯನು ಶ್ರೀ ಗುರುವೆ ಶರಣು,", 
        "18655": "ಮತ್ತಂ, ಆ ಶಿಷ್ಯನ ಪ್ರಳಾಪವೆಂತೆಂದಡೆ :", 
        "18656": "ಮತ್ತಂ, ಆ ಶಿಷ್ಯನ ಸ್ತೋತ್ರ:", 
        "18657": "ಇಂತೀ ನಾನಾ ಮುಖದಲ್ಲಿ ಸ್ತೋತ್ರವ ಮಾಡಿ", 
        "18658": "ಮತ್ತಂ, ಆ ಶಿಷ್ಯನು ತನ್ನ ಪೂರ್ವಾಪರಸಂಬಂಧವ", 
        "18659": "ನಾದ ಬಿಂದುವ ನುಂಗಿ ಉಗುಳದಂತಿದ್ದುದು.", 
        "18660": "ನಿರಂಜನಪ್ರಣವ ಉತ್ಪತ್ಯವಾಗದಂದು", 
        "18661": "ಪೃಥ್ವಿ ಅಪ್ಪು ತೇಜ ವಾಯು ಆಕಾಶವಿಲ್ಲದಂದು,", 
        "18662": "ಜ್ಞಾತೃ ಜ್ಞಾನಂಗಳಿಲ್ಲದಂದು, ಜ್ಞಾನತ್ರಯಂಗಳಿಲ್ಲದಂದು,", 
        "18663": "ಸಂಸಾರವೆಂಬ ಸಾಗರದೊಳು ಬಿದ್ದು ಮುಳುಗಿದೆನಯ್ಯ.", 
        "18664": "ಸಂಸಾರವೆಂಬ ಅರಣ್ಯದೊಳು ಬಿದ್ದೆನು.", 
        "18665": "ಸೂರ್ಯನ ಗ್ರಹಣದಂತೆ ಸರ್ವಗ್ರಹಣವಾಯಿತ್ತಯ್ಯಾ ಎನಗೆ.", 
        "18666": "ಶಬ್ದ  ಸ್ಪರ್ಶ ರೂಪು ರಸ ಗಂಧವೆಂಬ", 
        "18667": "ಇನ್ನು ಮಾಯಾವಿಡಂಬನಸ್ಥಲವದೆಂತೆಂದಡೆ :", 
        "18668": "ಮನು ಮುನಿ ಯತಿ ಸನ್ಯಾಸಿಗಳೆಲ್ಲರು", 
        "18669": "ಮನು ಮುನಿ ಯತಿ ಸನ್ಯಾಸಿಗಳ", 
        "18670": "ಅನಂತಕೋಟಿ ಬ್ರಹ್ಮರ", 
        "18671": "ಇನ್ನು ಗುರುಕರುಣಸ್ಥಲವದೆಂತೆಂದಡೆ :", 
        "18672": "ಗುರುಕರುಣದಿಂದ ವಿಭೂತಿಯ ಪಟ್ಟವಂ ಕಟ್ಟಿ", 
        "18673": "ಇನ್ನು ಲಿಂಗಧಾರಣಸ್ಥಲವದೆಂತೆಂದಡೆ :", 
        "18674": "ಕೃತಯುಗದಲ್ಲಿ ಅಖಂಡಾತ್ಮನೆಂಬ ಗಣೇಶ್ವರನಾಗಿದ್ದಂದು,", 
        "18675": "ಇನ್ನು ವಿಭೂತಿಸ್ಥಲವದೆಂತೆಂದಡೆ :", 
        "18676": "ಇನ್ನು ವಿಭೂತಿ ಭಸಿತ ಭಸ್ಮಕ್ಷಾರ ರಕ್ಷೆ ಎಂಬ", 
        "18677": "ಶ್ರುತಿವಿಧಿಸಿದ ಶ್ರೀವಿಭೂತಿಯ ಪರಂಜ್ಯೋತಿಯೆಂದರಿದು", 
        "18678": "ಇನ್ನು ರುದ್ರಾಕ್ಷಿಸ್ಥಲವೆಂತೆಂದಡೆ :", 
        "18679": "ಇನ್ನು ಲಿಂಗಧಾರಣ ಮಹಾತ್ಮೆಯ ಸ್ಥಲವೆಂತೆಂದಡೆ :", 
        "18680": "ಇನ್ನು ಪಂಚಾಕ್ಷರಿಯಸ್ಥಲವೆಂತೆಂದೊಡೆ :", 
        "18681": "ಇನ್ನು ಆ ಅಕಾರ ಉಕಾರ ಮಕಾರ ಇವು ಮೂರು ಬೀಜಾಕ್ಷರ.", 
        "18682": "ಐವತ್ತೆರಡು ಅಕ್ಷರಕ್ಕೆ ಈ ಪ್ರಣವವೇ", 
        "18683": "ಸಚ್ಚಿದಾನಂದಸ್ವರೂಪವಾಗಿಹ ಪರಬ್ರಹ್ಮನೆ", 
        "18684": "ಇಷ್ಟಲಿಂಗ ಪ್ರಾಣಲಿಂಗ ಭಾವಲಿಂಗಕ್ಕೆ", 
        "18685": "ಇನ್ನೊಂದು ಪ್ರಕಾರದ ಅಂಗತ್ರಯವೆಂತೆಂದಡೆ :", 
        "18686": "ಇನ್ನೊಂದು ಪ್ರಕಾರದ ಅಂಗಸ್ಥಲವೆಂತೆಂದಡೆ :", 
        "18687": "ಇನ್ನು ಅಂಗತ್ರಯಂಗಳಲ್ಲಿ  ಲಿಂಗತ್ರಯಸ್ವಾಯತವದೆಂತೆಂದಡೆ :", 
        "18688": "ಭಾವಲಿಂಗದಲ್ಲಿ  ಪ್ರಾಜ್ಞಾತ್ಮನೆಂಬ ಯೋಗಾಂಗವೈಕ್ಯವಾಯಿತ್ತು.", 
        "18689": "ಭಾವಲಿಂಗದಲ್ಲಿ  ಐಕ್ಯ-ಶರಣಸ್ಥಲವೆಂಬ ಯೋಗಾಂಗವೈಕ್ಯವಾಯಿತ್ತು.", 
        "18690": "ಇನ್ನು ಇಷ್ಟ-ಪ್ರಾಣ-ಭಾವಲಿಂಗದ ಪೂಜೆಯ ವಿವರವೆಂತೆಂದಡೆ :", 
        "18691": "ಉಪ್ಪು ಉದಕವ ಬೆರೆಸಿದಂತೆ", 
        "18692": "ಇನ್ನು ಇಷ್ಟಲಿಂಗ ಪ್ರಾಣಲಿಂಗ ಭಾವಲಿಂಗಾರ್ಪಿತದ ವಿವರವೆಂತೆಂದಡೆ :", 
        "18693": "ಇಷ್ಟಲಿಂಗಕ್ಕೆ ರೂಪಾಗಿ ಬಂದುದ ಕಾಯದ ಕೈಯಲ್ಲಿ ಕೊಡುವುದು.", 
        "18694": "ಇನ್ನು ಗುರುಲಿಂಗ ಶಿವಲಿಂಗ ಜಂಗಮಲಿಂಗದ ವಿವರವೆಂತೆಂದಡೆ :", 
        "18695": "ಇನ್ನು ಪ್ರಥಮ ಲಿಂಗದಲ್ಲಿ, ದ್ವಿತೀಯ ಲಿಂಗದಲ್ಲಿ,", 
        "18696": "ಹೀಂಗೆ ಅರಿದು ಅರ್ಚಿಸಿ ವಂದಿಸಿ ಆರಾಧನೆಯಂ ಮಾಡಿ", 
        "18697": "ಶ್ರೀಗುರುವಿನ ಉಪದೇಶ ಮಂತ್ರಮಾರ್ಗದಲ್ಲಿ", 
        "18698": "ಇನ್ನು ಗುರುಪೂಜಾವಿಧಿಯ ಕ್ರಮ ತಾನೇ ಅಷ್ಟಾಂಗಯೋಗ.", 
        "18699": "ಬ್ರಹ್ಮಚಾರಿಯಾಗಿಹ, ಅಪೇಕ್ಷೆಯಂ ಬಿಟ್ಟು ನಿರಾಪೇಕ್ಷನಾಗಿಹ,", 
        "18700": "ವಜ್ರಾಸನ, ಪದ್ಮಾಸನ, ಸ್ವಸ್ತಿಕಾಸನ, ಗೋಮುಖಾಸನ, ಕುಕ್ಕುಟಾಸನ,", 
        "18701": "ಸರ್ವೇಂದ್ರಿಯಂಗಳಿಗೆ ಒಡೆಯನಹಂತಾ ಮನಸ್ಸು,", 
        "18702": "ಮನವ ಸಕಲೇಂದ್ರಿಯಂಗಳ ಕೇರಿಗಳಲ್ಲಿ", 
        "18703": "ಶ್ರೀಗುರುಲಿಂಗಭಾವವಿಲ್ಲದ ನಿರ್ಭಾವಲಿಂಗವ ಭಾವಸ್ಥಲಕ್ಕೆ ತಂದು", 
        "18704": "ಆ ಧ್ಯಾನವನೆಚ್ಚಲರಿಯದೆ ಸುಷುಪ್ತಿಯ ಹಾಂಗೆ", 
        "18705": "ಇನ್ನು ಜಂಗಮಭಕ್ತಿಯ ವಿವರ ಅದೆಂತೆಂದಡೆ :", 
        "18706": "ಇನ್ನು ಪ್ರಥಮಲಿಂಗ ದ್ವಿತೀಯಲಿಂಗ ತೃತೀಯಲಿಂಗದಲ್ಲಿ", 
        "18707": "ಇನ್ನು  ಲಿಂಗೋದಕ, ಪಾದೋದಕ, ಪ್ರಸಾದೋದಕವೆಂತೆಂದಡೆ :", 
        "18708": "ಇನ್ನು ಷಟ್ಸ್ಥಲದ ಭೇದವೆಂತೆಂದಡೆ :", 
        "18709": "ಪರಸ್ತ್ರೀ ಪರಧನದಾಸೆಯ ಬಿಟ್ಟು ಶುದ್ಧವಾಗಿ", 
        "18710": "ಲಿಂಗಪ್ರಸಾದವ ಲಿಂಗನೆನಹಿನಿಂದ ಭೋಗಿಸುವುದು,", 
        "18711": "ಪ್ರಾಣವೆ ಲಿಂಗವಾಗಿ, ಲಿಂಗವೆ ಪ್ರಾಣವಾಗಿ,", 
        "18712": "ಲಿಂಗವೇ ಪತಿಯಾಗಿ, ತಾನು ಸತಿಯೆಂಬ ಭಾವದಲ್ಲಿ ಆಚರಿಸಿ,", 
        "18713": "ಕ್ಷುತ್ಪಿಪಾಸೆ ಶೋಕ ಮೋಹ ಜನನ ಮರಣ", 
        "18714": "ಹೀಗೆಂದು ಆ ಶಿಷ್ಯಂಗೆ ಬೋಧಿಸಿ, ಕೃತಾರ್ಥನ ಮಾಡಿದ", 
        "18715": "ಮತ್ತಂ,ಆ ಶಿಷ್ಯನು ಸದ್ಗುರುಸ್ವಾಮಿಗೆ ದೀರ್ಘದಂಡ ನಮಸ್ಕಾರವಂ ಮಾಡಿ", 
        "18716": "ಅ ಅಖಂಡಮಹಾಮೂಲಸ್ವಾಮಿಯ ಸ್ಥಲದ ವಚನವೆಂತೆಂದಡೆ :", 
        "18717": "ಆದಿಮೂಲ ಅನಾದಿಮೂಲಂಗಳಿಗತ್ತತ್ತವಾಗಿಹ", 
        "18718": "ಪರಾಪರವಿಲ್ಲದಂದು ಆ ಪರಾಪರಕ್ಕಪರವಾಗಿಹ", 
        "18719": "ಅನಂತಕೋಟಿ ಸೂರ್ಯ ಚಂದ್ರಾಗ್ನಿ ಪ್ರಕಾಶಮಯವಾಗಿಹ", 
        "18720": "ನಿರಾಳ ನಿರಂಜನವಿಲ್ಲದಂದು,", 
        "18721": "ಏನೂ ಏನೂ ಎನಲಿಲ್ಲದಂದು ಮಹಾಘನಕ್ಕೆ ಘನವಾದ", 
        "18722": "ಘನಕ್ಕೆ ಘನವಾದ ಮಹಾಘನದೋಂಕಾರವಿಲ್ಲದಂದು,", 
        "18723": "ಚಿನ್ನಾದ ಬಿದ್ಬಿಂದು ಚಿತ್ಕಳೆ ತಲೆದೋರದಂದು,", 
        "18724": "ನಿರಂಜನ ಪ್ರಣವದ ನೆನಹುಮಾತ್ರದಿಂದ", 
        "18725": "ಆದಿಮೂಲ ಅನಾದಿಮೂಲವಿಲ್ಲದಂದು,", 
        "18726": "ಬ್ರಹ್ಮ  ವಿಷ್ಣು  ರುದ್ರ ಈಶ್ವರ ಸದಾಶಿವರಿಲ್ಲದಂದು,", 
        "18727": "ಶಾಂತ್ಯತೀತೋತ್ತರಕಲೆ, ಶಾಂತ್ಯತೀತಕಲೆಗಳಿಲ್ಲದಂದು,", 
        "18728": "ಅವಾಚ್ಯಪ್ರಣವದ ನೆನಹು ಮಾತ್ರದಲ್ಲಿ", 
        "18729": "ಆ ಕಲಾಪ್ರಣವದ ಮೂವತ್ತೆಂಟು ಕಲೆಗಳ ಕಾಂತಿ ಅದೆಂತೆಂದಡೆ :", 
        "18730": "ಚಿತ್ಕಲಾಪ್ರಣವ ಉಪಮಿಸಬಾರದ ಉಪಮಾತೀತವು", 
        "18731": "ಸಚ್ಚಿದಾನಂದ ಪರಮಾನಂದವಿಲ್ಲದತ್ತತ್ತ ,", 
        "18732": "ಅವಾಚ್ಯಪ್ರಣವ ಅನಿರ್ವಾಚ್ಯಪ್ರಣವವಿಲ್ಲದಂದು,", 
        "18733": "ಇಂದ್ರಪದ ಬ್ರಹ್ಮಪದ ವಿಷ್ಣುಪದವಿಲ್ಲದಂದು,", 
        "18734": "ಏನು ಏನೂ ಎನಲಿಲ್ಲದ ಮಹಾಘನ ಚಿತ್ಕಲಾಪ್ರಣವದ", 
        "18735": "ಆದಿ ರುದ್ರ ಆದಿ ಈಶ್ವರ ಆದಿ ಸದಾಶಿವರಿಲ್ಲದ ಮುನ್ನ ಮುನ್ನ,", 
        "18736": "ಆದಿ ಅಕಾರದಲ್ಲಿ ತಾರಕಸ್ವರೂಪ ದಂಡಕಸ್ವರೂಪ", 
        "18737": "ಏನೂ ಏನೂ ಎನಲಿಲ್ಲದ ಅನಾದಿ ಪ್ರಣವದ", 
        "18738": "ಅನಂತಕೋಟಿ ಆದಿಬ್ರಹ್ಮರ ಶಿರವನರಿದು", 
        "18739": "ಏನೂ ಏನೂ ಎನಲಿಲ್ಲದ ಅನಾದಿ ಅಕಾರ, ಅನಾದಿ ಉಕಾರ,", 
        "18740": "ಸಪ್ತಕೋಟಿ ಮಹಾಮಂತ್ರ ವಿಶಾಲವಾಗದಂದು,", 
        "18741": "ಅಸಂಖ್ಯಾತ ಆದಿಬ್ರಹ್ಮರುತ್ಪತ್ಯವಾಗದಂದು,", 
        "18742": "ಆ ಆದಿ ಪ್ರಣವದ ನೆನಹುಮಾತ್ರದಲ್ಲಿ", 
        "18743": "ಆದಿ ಅಕಾರ ಪ್ರಣವಕ್ಕೆ ಆದಿ ನಾದಪ್ರಣವವೇ ಆಧಾರ.", 
        "18744": "ಇದಕ್ಕೆ ಪ್ರಣವೋಪನಿಷತ್ :", 
        "18745": "ಆ ಅಖಂಡಮಹಾಜ್ಯೋತಿಪ್ರಣವದ ತಾರಕಸ್ವರೂಪದ", 
        "18746": "ಇನ್ನು ಆ ಲಿಂಗಗರ್ಭದಲ್ಲಿ ಅನೇಕಕೋಟಿ ತತ್ವಂಗಳು,", 
        "18747": "ಇನ್ನು ಆ ಅಖಂಡ ಪರಿಪೂರ್ಣ ಅಪ್ರಮಾಣ ಅಗೋಚರ", 
        "18748": "ಪಂಚಮುಖ ದಶಭುಜವನುಳ್ಳ ಸದಾಶಿವನ ನಿರ್ಭಾವಮುಖದಲ್ಲಿ", 
        "18749": "ಅಖಂಡ ಜ್ಯೋತಿರ್ಮಯವಾಗಿಹ ಗೋಳಕಾಕಾರಪ್ರಣವದ", 
        "18750": "ಇನ್ನೊಂದು ಪ್ರಕಾರದ ಚಕ್ರೋತ್ಪತ್ಯವೆಂತೆಂದಡೆ :", 
        "18751": "ಗುದಸ್ಥಾನದಲ್ಲಿ  ಆಧಾರಚಕ್ರ ಉತ್ಪತ್ಯವಾಯಿತ್ತು.", 
        "18752": "ಪರಾಪರವಾಗಿಹ ಪರಬ್ರಹ್ಮದ ನೆನಹುಮಾತ್ರದಲ್ಲಿ", 
        "18753": "ಆ ಮಹಾಕ್ಷಿತಿದಳಪದ್ಮದಲ್ಲಿ ಕ್ಷಿತಿದಳಪದ್ಮಹುಟ್ಟಿ,", 
        "18754": "ಆ ಕ್ಷಿತಿದಳಪದ್ಮದಲ್ಲಿ -", 
        "18755": "ಆ ಕ್ಷೋಣಿದಳಪದ್ಮದಲ್ಲಿ -", 
        "18756": "ಆ ಪದ್ಮದಳಪದ್ಮದಲ್ಲಿ -", 
        "18757": "ಆ ಮಹಾಖರ್ವದಳಪದ್ಮದಲ್ಲಿ -", 
        "18758": "ಆ ಖರ್ವದಳಪದ್ಮದಲ್ಲಿ", 
        "18759": "ಆ ಅರ್ಬುದದಳಪದ್ಮದಲ್ಲಿ", 
        "18760": "ಆ ಕೋಟಿದಳಪದ್ಮದಲ್ಲಿ -", 
        "18761": "ಆ ಲಕ್ಷದಳಪದ್ಮದಲ್ಲಿ -", 
        "18762": "ಆ ತ್ರಿಸಹಸ್ರದಳಪದ್ಮದಲ್ಲಿ -", 
        "18763": "ಆ ಏಕದಳಪದ್ಮದಲ್ಲಿ -", 
        "18764": "ಆ ತ್ರಿದಳಪದ್ಮದಲ್ಲಿ -", 
        "18765": "ಆ ಸಹಸ್ರದಳಪದ್ಮದಲ್ಲಿ -", 
        "18766": "ಆ ಶತದಳಪದ್ಮದಲ್ಲಿ -", 
        "18767": "ಆ ತ್ರಿವಿಂಶಚತುರ್ದಳಪದ್ಮದಲ್ಲಿ -", 
        "18768": "ಆ ದ್ವಿದಳಪದ್ಮದಲ್ಲಿ -", 
        "18769": "ಆ ಷೋಡಶದಳಪದ್ಮದಲ್ಲಿ -", 
        "18770": "ಆ ದ್ವಾದಶದಳಪದ್ಮದಲ್ಲಿ -", 
        "18771": "ಆ ದಶದಳಪದ್ಮದಲ್ಲಿ -", 
        "18772": "ಆ ಷಡುದಳಪದ್ಮದಲ್ಲಿ-", 
        "18773": "ಪರಾಪರತತ್ವದಲ್ಲಿ -", 
        "18774": "ಅಖಂಡ ಮಹಾತತ್ವದಲ್ಲಿ -", 
        "18775": "ಅಚಲತತ್ವದಲ್ಲಿ -", 
        "18776": "ನಿರಂಜನತತ್ವದಲ್ಲಿ -", 
        "18777": "ನಿರಾಳತತ್ವದಲ್ಲಿ -", 
        "18778": "ನಿರಾಮಯತತ್ವದಲ್ಲಿ -", 
        "18779": "ಮಹಾತತ್ವದಲ್ಲಿ -", 
        "18780": "ಪರಶಿವತತ್ವದಲ್ಲಿ -", 
        "18781": "ನಿಷ್ಕಳತತ್ವದಲ್ಲಿ -", 
        "18782": "ನಿರ್ಗುಣತತ್ವದಲ್ಲಿ -", 
        "18783": "ಸರ್ವಾತ್ಮತತ್ವದಲ್ಲಿ -", 
        "18784": "ವಿಶ್ವಾತ್ಮತತ್ವದಲ್ಲಿ -", 
        "18785": "ಪರತತ್ವದಲ್ಲಿ -", 
        "18786": "ಸ್ವಯಾತ್ಮತತ್ವದಲ್ಲಿ-", 
        "18787": "ತತ್ವಾತ್ಮತತ್ವದಲ್ಲಿ-", 
        "18788": "ಇದಕ್ಕೆ ಈಶ್ವರ ಉವಾಚ :", 
        "18789": "ಇನ್ನು ಆ ಅಖಂಡಜ್ಯೋತಿರ್ಮಯವಾಗಿಹ", 
        "18790": "ಅಕಾರದಲ್ಲಿ  ಪೃಥ್ವಿಯಗ್ನಿ ಋಗ್ವೇದ ಭೂಲೋಕ", 
        "18791": "ಇನ್ನು ಆ ಪ್ರಣವದ ತತ್‍ಸ್ಥಾನವೆಂತೆಂದಡೆ :", 
        "18792": "ಇನ್ನು ಆ ಪ್ರಣವದ ತಾರಕಾಸ್ವರೂಪ", 
        "18793": "ಇನ್ನು ಅತಿ ಸೂಕ್ಷ್ಮಪಂಚಾಕ್ಷರದುತ್ಪತ್ಯವದೆಂತೆಂದಡೆ :", 
        "18794": "ಇನ್ನು ಅತಿಸೂಕ್ಷ್ಮಪಂಚಾಕ್ಷರದ ಕಾಂತಿ,", 
        "18795": "ಇನ್ನು ಐವತ್ತೆರಡಕ್ಷರದ ಉತ್ಪತ್ಯವದೆಂತೆಂದಡೆ :", 
        "18796": "ಇನ್ನು ಬೀಜಾಕ್ಷರಂಗಳ ನೆಲೆ ಅದೆಂತೆಂದಡೆ :", 
        "18797": "ಇನ್ನು ಆ ಪ್ರಣಮದ", 
        "18798": "ಈ ಐವತ್ತೆರಡಕ್ಷರವ ಅರಿವಿಂದರಿದಡೆ ಅನೇಕ ಆಗಮಂಗಳು,", 
        "18799": "ಆ ಅಖಂಡಜ್ಯೋತಿರ್ಮಯವಾಗಿಹ ಗೋಳಕಾಕಾರ ಪ್ರಣವದ", 
        "18800": "ಇನ್ನು ಷಡ್ವಿಧಮುಖಂಗಳ ನೆಲೆ ಅದೆಂತೆಂದಡೆ :", 
        "18801": "ಸದ್ಯೋಜಾತಮುಖದಲ್ಲಿ ಪೃಥ್ವಿ ಪುಟ್ಟಿತ್ತು ,", 
        "18802": "ಇನ್ನು ಷಡ್ವಿಧಭೂತಂಗಳ ನೆಲೆ ಅದೆಂತೆಂದಡೆ :", 
        "18803": "ಇನ್ನೊಂದು ಪ್ರಕಾರದ ಪಂಚಭೂತದ ಮನದ ನೆಲೆಯದೆಂತೆಂದಡೆ :", 
        "18804": "ಆ ಅಖಂಡ ಗೋಳಕಾಕಾರಪ್ರಣವದ", 
        "18805": "ಇನ್ನು ಷಡ್ವಿಧಲಿಂಗದ ನೆಲೆ ಅದೆಂತೆಂದಡೆ :", 
        "18806": "ಆಧಾರಚಕ್ರದಲ್ಲಿಹ ಆಚಾರಲಿಂಗವು", 
        "18807": "ಸ್ವಾಧಿಷ್ಠಾನಚಕ್ರದಲ್ಲಿಹ ಗುರುಲಿಂಗಸ್ಥಲವನು", 
        "18808": "ಮಣಿಪೂರಕಚಕ್ರದಲ್ಲಿಹ ಶಿವಲಿಂಗವು", 
        "18809": "ಅನಾಹತಚಕ್ರದಲ್ಲಿಯ ಜಂಗಮಲಿಂಗವು", 
        "18810": "ವಿಶುದ್ಧಿಚಕ್ರದಲ್ಲಿಹ ಪ್ರಸಾದಲಿಂಗವು", 
        "18811": "ಆಜ್ಞಾಚಕ್ರದಲ್ಲಿಯ ಮಹಾಲಿಂಗವು", 
        "18812": "ಆ ಅಖಂಡ ಜ್ಯೋತಿರ್ಮಯವಾಗಿಹ ಗೋಳಕಾಕಾರಪ್ರಣವದ", 
        "18813": "ಆಚಾರಲಿಂಗದಲ್ಲಿ ನಿವೃತ್ತಿಕಲೆ ಇಹುದು.", 
        "18814": "ಇನ್ನೊಂದು ಪ್ರಕಾರದ ಕಲಾನ್ಯಾಸವದೆಂತೆಂದೊಡೆ :", 
        "18815": "ಶಾಂತ್ಯತೀತೋತ್ತರಕಲೆಯಲ್ಲಿ ಮಹಾಸಾದಾಖ್ಯ ಉತ್ಪತ್ಯವಾಯಿತ್ತು .", 
        "18816": "ಸಾದಾಖ್ಯ ಉತ್ಪತ್ಯ ಇನ್ನೊಂದು ಪ್ರಕಾರವದೆಂತೆಂದಡೆ :", 
        "18817": "ಇನ್ನು ಷಡ್ವಿಧಸಾದಾಖ್ಯದ ನೆಲೆ ಅದೆಂತೆಂದಡೆ :", 
        "18818": "ಆ ಅಖಂಡ ಜ್ಯೋತಿರ್ಮಯವಾಗಿಹ ಗೋಳಕಾಕಾರಪ್ರಣವದ", 
        "18819": "ಇನ್ನು ಷಡ್ವಿಧಹಸ್ತಂಗಳ ನೆಲೆ ಅದೆಂತೆಂದಡೆ :", 
        "18820": "ಏನು ಏನೂ ಎನಲಿಲ್ಲದ ಮಹಾಘನ ನಿರಂಜನ ವಸ್ತುವಿನ", 
        "18821": "ಇನ್ನು ನವಶಕ್ತಿಗಳ ನೆಲೆ ಅದೆಂತೆಂದಡೆ :", 
        "18822": "ಆ ಅಖಂಡ ಜ್ಯೋತಿರ್ಮಯವಾಗಿಹ ಗೋಳಕಾಕಾರ ಪ್ರಣವದ", 
        "18823": "ಇನ್ನು ನವಷಡ್ವಿಧ ಅಧಿದೇವತೆಗಳ ನೆಲೆ ಅದೆಂತೆಂದಡೆ :", 
        "18824": "ನಿಶ್ಶಬ್ದವೆಂಬ ಪರಬ್ರಹ್ಮದ ನೆನಹುಮಾತ್ರದಲ್ಲಿ-", 
        "18825": "ಇನ್ನು ಅಷ್ಟನಾದದ ನೆಲೆ ಅದೆಂತೆಂದಡೆ :", 
        "18826": "ಆ ಅಖಂಡ ಜ್ಯೋತಿರ್ಮಯವಾಗಿಹ ಗೋಳಕಾಕಾರಪ್ರಣವದ", 
        "18827": "ಇನ್ನು ಷಡ್ವಿಧಭಕ್ತಿಯ ನೆಲೆ ಅದೆಂತೆಂದಡೆ :", 
        "18828": "ಆ ಅಖಂಡ ಜ್ಯೋತಿರ್ಮಯವಾಗಿಹ ಗೋಳಕಾಕಾರಪ್ರಣವದ", 
        "18829": "ಇನ್ನು ಷಡ್ವಿಧ ಪರಿಣಾಮದ ನೆಲೆ ಅದೆಂತೆಂದಡೆ :", 
        "18830": "ಆ ಅಖಂಡ ಜ್ಯೋತಿರ್ಮಯವಾಗಿಹ ಗೋಳಕಾಕಾರ ಪ್ರಣವದ", 
        "18831": "ಆ ಅಖಂಡ ಜ್ಯೋತಿರ್ಮಯವಾಗಿಹ ಗೋಳಕಾಕಾರಪ್ರಣವದ", 
        "18832": "ಇನ್ನು ಋಗ್ವೇದ ಯಜುರ್ವೇದ ಅಥರ್ವಣವೇದ", 
        "18833": "ಲಿಂಗವೆಂಬುದು ನಾದಬಿಂದುಕಲಾತೀತ.", 
        "18834": "ಆಧಾರಚಕ್ರದಲ್ಲಿ ಅನಾದಿಯೆಂಬ ಸಂಜ್ಞೆ,", 
        "18835": "ಗುದಸ್ಥಾನದಲ್ಲಿ ಆಧಾರಚಕ್ರ, ಪೃಥ್ವಿ ಎಂಬ ಮಹಾಭೂತ.", 
        "18836": "ಅಲ್ಲಿಂದ ಮೇಲೆ ಲಿಂಗಸ್ಥಾನದಲ್ಲಿ ಸ್ವಾಧಿಷ್ಠಾನಚಕ್ರ,", 
        "18837": "ಅಲ್ಲಿಂದ ಮೇಲೆ ನಾಭಿಸ್ಥಾನದಲ್ಲಿ ಮಣಿಪೂರಕಚಕ್ರ,", 
        "18838": "ಅಲ್ಲಿಂದ ಮೇಲೆ ಹೃದಯಸ್ಥಾನದಲ್ಲಿ", 
        "18839": "ಅಲ್ಲಿಂದ ಮೇಲೆ ಕಂಠಸ್ಥಾನದಲ್ಲಿ ವಿಶುದ್ಧಿಚಕ್ರ,", 
        "18840": "ಅಲ್ಲಿಂದ ಮೇಲೆ ಭ್ರೂಮಧ್ಯದಲ್ಲಿ ಆಜ್ಞಾಚಕ್ರ,", 
        "18841": "ಇನ್ನು ಇಷ್ಟ ಪ್ರಾಣ ಭಾವಲಿಂಗದ ಭೇದವೆಂತೆಂದಡೆ :", 
        "18842": "ಆ ಆದಿ ಉಕಾರ, ಆ ಆದಿ ಮಕಾರ, ಆ ಆದಿ ಅಕಾರಕ್ಕೆ", 
        "18843": "ಆ ಇಷ್ಟ ಪ್ರಾಣ ಭಾವಲಿಂಗವೆಂಬ ಆದಿಪ್ರಣವತ್ರಿತಯದಲ್ಲಿ", 
        "18844": "ಇನ್ನು ಪ್ರಣವದ ಲಕ್ಷಣವದೆಂತೆಂದಡೆ :", 
        "18845": "ಅಖಂಡಜ್ಯೋತಿರ್ಮಯವಾಗಿಹ ಪರಮೋಂಕಾರ ಪ್ರಣವದ", 
        "18846": "ಆ ಅಖಂಡ ಜ್ಯೋತಿರ್ಮಯವಾಗಿಹ  ಪರಮೋಂಕಾರಪ್ರಣವದ", 
        "18847": "ಅಖಂಡ ಜ್ಯೋತಿರ್ಮಯವಾಗಿಹ ಪರಮೋಂಕಾರ ಪ್ರಣವದ", 
        "18848": "ಪೃಥ್ವಿಯೆಂಬ ಮಹಾಭೂತವೇ ಅಂಗವಾಗಿ ಭಕ್ತನಿಹನು.", 
        "18849": "ಅಖಂಡಜ್ಯೋತಿರ್ಮಯವಾಗಿ ಪರಮೋಂಕಾರಪ್ರಣವದ", 
        "18850": "ಇನ್ನೊಂದು ಪ್ರಕಾರದ ಹಸ್ತ ಉತ್ಪತ್ಯವದೆಂತೆಂದಡೆ :", 
        "18851": "ಪೃಥ್ವಿಭೂತದಲ್ಲಿ ಸುಚಿತ್ತಹಸ್ತವಿಹುದು,", 
        "18852": "ಆ ಅಖಂಡಜ್ಯೋತಿರ್ಮಯವಾಗಿಹ ಪರಮೋಂಕಾರಪ್ರಣವದ", 
        "18853": "ಇನ್ನೊಂದು ಪ್ರಕಾರದ ಲಿಂಗೋತ್ಪತ್ಯವದೆಂತೆಂದಡೆ :", 
        "18854": "ಪೃಥ್ವಿಯೆಂಬ ಮಹಾಭೂತದಲ್ಲಿ ಆಚಾರಲಿಂಗವಿಹುದು.", 
        "18855": "ಇನ್ನೊಂದು ಪ್ರಕಾರದ ಷಡ್ಲಿಂಗನ್ಯಾಸಸ್ಥಲವೆಂತೆಂದಡೆ :", 
        "18856": "ಪೃಥ್ವಿಯೇ ಅಂಗವಾದ ಭಕ್ತನ ಸುಚಿತ್ತಹಸ್ತದಲ್ಲಿಹ", 
        "18857": "ಅಪ್ಪುವೆ ಅಂಗವಾದ ಮಹೇಶ್ವರನ ಸುಬುದ್ಧಿಹಸ್ತದಲ್ಲಿಹ", 
        "18858": "ಅನಲಾಂಗವಾದ ಪ್ರಸಾದಿಯ ನಿರಹಂಕಾರಹಸ್ತದಲ್ಲಿಹ", 
        "18859": "ವಾಯುವೇ ಅಂಗವಾದ ಪ್ರಾಣಲಿಂಗಿಯ", 
        "18860": "ವ್ಯೋಮವೇ ಅಂಗವಾದ ಶರಣನ ಸುಜ್ಞಾನಹಸ್ತದಲ್ಲಿಹ", 
        "18861": "ಆತ್ಮನೆ ಅಂಗವಾದ ಐಕ್ಯನ ಭಾವಹಸ್ತದಲ್ಲಿ", 
        "18862": "ಆ ಅಖಂಡ ಜ್ಯೋತಿರ್ಮಯವಾಗಿಹ ಪರಮೋಂಕಾರ ಪ್ರಣಮದ", 
        "18863": "ಘ್ರಾಣ ಪೃಥ್ವಿಯಾಶ್ರಯವಾಗಿಹುದು.", 
        "18864": "ಅಖಂಡ ಜ್ಯೋತಿರ್ಮಯವಾಗಿಹ ಪರಮೋಂಕಾರ ಪ್ರಣವದ", 
        "18865": "ಪೃಥ್ವಿಯಲ್ಲಿ ಗಂಧವಿಹುದು, ಅಪ್ಪುವಿನಲ್ಲಿ ರಸವಿಹುದು,", 
        "18866": "ಭೂಮಿಯೆ ಅಂಗವಾದ ಭಕ್ತನು ಸುಚಿತ್ತವೆಂಬ ಹಸ್ತದಲ್ಲಿ", 
        "18867": "ಅಪ್ಪುವೆ ಅಂಗವಾದ ಮಹೇಶ್ವರನು ಸುಬುದ್ದಿಯೆಂಬ ಹಸ್ತದಲ್ಲಿ", 
        "18868": "ಅಗ್ನಿಯೆ ಅಂಗವಾದ ಪ್ರಸಾದಿ ನಿರಹಂಕಾರವೆಂಬ ಹಸ್ತದಲ್ಲಿ", 
        "18869": "ವಾಯುವೆ ಅಂಗವಾದ ಪ್ರಾಣಲಿಂಗಿ ಸುಮನವೆಂಬ ಹಸ್ತದಲ್ಲಿ", 
        "18870": "ಆಕಾಶವೇ ಅಂಗವಾದ ಶರಣ ಸುಜ್ಞಾನವೆಂಬ ಹಸ್ತದಲ್ಲಿ", 
        "18871": "ಆತ್ಮನೆ ಅಂಗವಾದ ಐಕ್ಯ ಭಾವವೆಂಬ ಹಸ್ತದಲ್ಲಿ", 
        "18872": "ಭಕ್ತನಾಚಾರಲಿಂಗದಲ್ಲಿ ಭೋಜ್ಯ ಸಮರ್ಪಣವು.", 
        "18873": "ಇನ್ನು ಕರಣಾರ್ಪಣಸ್ಥಲಂಗಳೆಂತೆಂದಡೆ :", 
        "18874": "ಭಕ್ತನಲ್ಲಿಯ ಪ್ರಸಾದಿಗೆ ಪೃಥ್ವಿಯಲ್ಲಿಯ ಅಗ್ನಿಯೇ ಅಂಗ.", 
        "18875": "ಭಕ್ತನಲ್ಲಿಯ ಪ್ರಾಣಲಿಂಗಿಗೆ ಪೃಥ್ವಿಯಲ್ಲಿಯ ವಾಯುವೇ ಅಂಗ.", 
        "18876": "ಭಕ್ತನಲ್ಲಿಯ ಶರಣಂಗೆ ಪೃಥ್ವಿಯಲ್ಲಿಯ ಆಕಾಶವೇ ಅಂಗ.", 
        "18877": "ಭಕ್ತನಲ್ಲಿಯ ಐಕ್ಯಂಗೆ ಪೃಥ್ವಿಯಲ್ಲಿಯ ಆತ್ಮನೆ ಅಂಗ,", 
        "18878": "ಇನ್ನು ಮಹೇಶ್ವರನಲ್ಲಿಯ ಷಡ್ವಿಧ ಷಡುಸ್ಥಲಲಿಂಗ", 
        "18879": "ಆ ಮಾಹೇಶ್ವರನಲ್ಲಿಯ ಭಕ್ತಂಗೆ ಅಪ್ಪುವಿನಲ್ಲಿಯ ಪೃಥ್ವಿಯೇ ಅಂಗ.", 
        "18880": "ಆ ಮಾಹೇಶ್ವರನಲ್ಲಿಯ ಪ್ರಸಾದಿಗೆ ಅಪ್ಪುವಿನಲ್ಲಿಯ ಅಗ್ನಿಯೇ ಅಂಗ.", 
        "18881": "ಆ ಮಹಾಹೇಶ್ವರನಲ್ಲಿಯ ಪ್ರಾಣಲಿಂಗಿಗೆ", 
        "18882": "ಆ ಮಾಹೇಶ್ವರನಲ್ಲಿಯ ಶರಣಂಗೆ ಅಪ್ಪುವಿನಲ್ಲಿಯ ಆಕಾಶವೇ ಅಂಗ.", 
        "18883": "ಆ ಮಾಹೇಶ್ವರನಲ್ಲಿಯ ಐಕ್ಯಂಗೆ ಅಪ್ಪುವಿನಲ್ಲಿಯ ಆತ್ಮನೇ ಅಂಗ.", 
        "18884": "ಇನ್ನು ಪ್ರಸಾದಿಯ ಷಡ್ವಿಧ ಷಡುಸ್ಥಲಲಿಂಗ", 
        "18885": "ಇನ್ನು ಆ ಪ್ರಸಾದಿಯಲ್ಲಿಯ ಭಕ್ತಂಗೆ ಅಗ್ನಿಯಲ್ಲಿಯ ಪೃಥ್ವಿಯೆ ಅಂಗ.", 
        "18886": "ಆ ಪ್ರಸಾದಿಯಲ್ಲಿಯ ಮಾಹೇಶ್ವರಂಗೆ ಅಗ್ನಿಯಲ್ಲಿಯ ಅಪ್ಪುವೆ ಅಂಗ.", 
        "18887": "ಆ ಪ್ರಸಾದಿಯಲ್ಲಿಯ ಪ್ರಾಣಲಿಂಗಿಗೆ ಅಗ್ನಿಯಲ್ಲಿಯ ವಾಯುವೇ ಅಂಗ.", 
        "18888": "ಆ ಪ್ರಸಾದಿಯಲ್ಲಿಯ ಶರಣಂಗೆ ಅಗ್ನಿಯಲ್ಲಿಯ ಆಕಾಶವೇ ಅಂಗ.", 
        "18889": "ಆ ಪ್ರಸಾದಿಯಲ್ಲಿಯ ಐಕ್ಯಂಗೆ ಅಗ್ನಿಯಲ್ಲಿಯ ಆತ್ಮವೇ ಅಂಗ.", 
        "18890": "ಇನ್ನು ಪ್ರಾಣಲಿಂಗಿಯಲ್ಲಿಯ ಷಡ್ವಿಧ ಷಡುಸ್ಥಲಲಿಂಗ", 
        "18891": "ಇನ್ನು ಪ್ರಾಣಲಿಂಗಿಯಲ್ಲಿಯ ಭಕ್ತಂಗೆ", 
        "18892": "ಆ ಪ್ರಾಣಲಿಂಗಿಯಲ್ಲಿಯ ಮಾಹೇಶ್ವರಂಗೆ", 
        "18893": "ಆ ಪ್ರಾಣಲಿಂಗಿಯಲ್ಲಿಯ ಪ್ರಸಾದಿಗೆ", 
        "18894": "ಆ ಪ್ರಾಣಲಿಂಗಿಯಲ್ಲಿಯ ಶರಣಂಗೆ", 
        "18895": "ಆ ಪ್ರಾಣಲಿಂಗಿಯಲ್ಲಿಯ ಐಕ್ಯಂಗೆ ವಾಯುವಿನಲ್ಲಿಯ ಆತ್ಮನೇ ಅಂಗ.", 
        "18896": "ಇನ್ನು ಶರಣನಲ್ಲಿಯ ಷಡ್ವಿಧ ಷಡುಸ್ಥಲಲಿಂಗ", 
        "18897": "ಇನ್ನು ಶರಣನಲ್ಲಿಯ ಭಕ್ತಂಗೆ ಆಕಾಶದಲ್ಲಿಯ ಪೃಥ್ವಿಯೇ ಅಂಗ.", 
        "18898": "ಆ ಶರಣನಲ್ಲಿಯ ಮಾಹೇಶ್ವರಂಗೆ ಆಕಾಶದಲ್ಲಿಯ ಅಪ್ಪುವೇ ಅಂಗ.", 
        "18899": "ಆ ಶರಣನಲ್ಲಿಯ ಪ್ರಸಾದಿಗೆ ಆಕಾಶದಲ್ಲಿಯ ಅಗ್ನಿಯೇ ಅಂಗ.", 
        "18900": "ಆ ಶರಣನಲ್ಲಿಯ ಪ್ರಾಣಲಿಂಗಿಗೆ ಆಕಾಶದಲ್ಲಿಯ ವಾಯುವೇ ಅಂಗ.", 
        "18901": "ಆ ಶರಣನಲ್ಲಿಯ ಐಕ್ಯಂಗೆ ಆಕಾಶದಲ್ಲಿಯ ಆತ್ಮನೇ ಅಂಗ.", 
        "18902": "ಇನ್ನು ಆ ಐಕ್ಯನಲ್ಲಿಯ ಷಡ್ವಿಧ ಷಡುಸ್ಥಲಲಿಂಗ", 
        "18903": "ಇನ್ನು ಆ ಐಕ್ಯನಲ್ಲಿಯ ಭಕ್ತಂಗೆ ಆತ್ಮನಲ್ಲಿಯ ಪೃಥ್ವಿಯೇ ಅಂಗ.", 
        "18904": "ಆ ಐಕ್ಯನಲ್ಲಿಯ ಮಾಹೇಶ್ವರಂಗೆ ಆತ್ಮನಲ್ಲಿಯ ಅಪ್ಪುವೇ ಅಂಗ.", 
        "18905": "ಆ ಐಕ್ಯನಲ್ಲಿಯ ಪ್ರಸಾದಿಗೆ ಆತ್ಮನಲ್ಲಿಯ ಅಗ್ನಿಯೇ ಅಂಗ.", 
        "18906": "ಆ ಐಕ್ಯನಲ್ಲಿಯ ಪ್ರಾಣಲಿಂಗಿಗೆ ಆತ್ಮನಲ್ಲಿಯ ವಾಯುವೇ ಅಂಗ.", 
        "18907": "ಆ ಐಕ್ಯನಲ್ಲಿಯ ಶರಣಂಗೆ ಆತ್ಮನಲ್ಲಿಯ ಆಕಾಶವೇ ಅಂಗ.", 
        "18908": "ಆ ಐಕ್ಯನಲ್ಲಿಯ ಐಕ್ಯಂಗೆ ಆತ್ಮನಲ್ಲಿಯ ಪರಮಾತ್ಮನೆ ಅಂಗ.", 
        "18909": "ಈ ಮೂವತ್ತಾರು ಷಡುಸ್ಥಲಬ್ರಹ್ಮವನರಿದು", 
        "18910": "ನಾಮರೂಪಕ್ರಿಯಾತ್ಮಕವಾಗಿಹ ಪರವಸ್ತುಲಿಂಗ ತಾನೆ", 
        "18911": "ಸ್ಥೂಲತನುವಿನಲ್ಲಿ ಇಷ್ಟಲಿಂಗ ಸ್ವಾಯತವಾಗಿಹುದು.", 
        "18912": "ಇನ್ನು ಹೃದಯಂಗದಲ್ಲಿ ಮಹಾಲಿಂಗ ಸ್ವಾಯತವಾಗಿಹುದು.", 
        "18913": "ಜ್ಞಾನೇಂದ್ರಿಯವೆಂಬ ಅಂಗಂಗಳಲ್ಲಿ ಲಿಂಗಸ್ವಾಯತವಾಗಿಹುದು.", 
        "18914": "ಶ್ರೋತ್ರ ತ್ವಕ್ಕು ಚಕ್ಷು ಜಿಹ್ವೆ ಘ್ರಾಣಂಗಳೆಂಬವೈದು", 
        "18915": "ಆ ಹೃದಯಾಕಾಶದಲ್ಲಿ ಮಹಾಲಿಂಗ ಸ್ವಾಯತವಾಗಿಹುದು.", 
        "18916": "ರುಧಿರದಲ್ಲಿ ಆಚಾರಲಿಂಗವಿಹುದು.", 
        "18917": "ನಕಾರವೇ ರುಧಿರಮಯವಾಗಿಹುದು.", 
        "18918": "ನಕಾರವೇ ಆಚಾರಲಿಂಗ, ಮಕಾರವೇ ಗುರುಲಿಂಗ,", 
        "18919": "ಅನಾದಿ ಸದಾಶಿವತತ್ವ, ಅನಾದಿ ಈಶ್ವರತತ್ವ,", 
        "18920": "ತಾನೆ ಭಕ್ತ ತಾನೆ ಮಾಹೇಶ್ವರನು", 
        "18921": "ತಾನೆ  ಇಷ್ಟಲಿಂಗ ತಾನೆ ಪ್ರಾಣಲಿಂಗ ತಾನೆ ಭಾವಲಿಂಗ ನೋಡಾ.", 
        "18922": "ತಾನೆ ಭಕ್ತ ಮಹೇಶ್ವರ ಪ್ರಸಾದಿ ಪ್ರಾಣಲಿಂಗಿ ಶರಣ ಐಕ್ಯನೆಂಬ", 
        "18923": "ತನ್ನಲ್ಲಿ ಅನಂತಕೋಟಿ ಬ್ರಹ್ಮರುತ್ಪತ್ಯ ಸ್ಥಿತಿ ಲಯ ನೋಡಾ.", 
        "18924": "ತಾನೆ ಗುರುತತ್ವ, ತಾನೆ ಶಿವತತ್ವ, ತಾನೆ ಪರತತ್ವ", 
        "18925": "ಆದಿ ಅನಾದಿಯಿಲ್ಲದಂದು ತಾನೆ ಪ್ರಣವಸ್ವರೂಪನು.", 
        "18926": "ಬ್ರಹ್ಮಲೋಕ ತಾನಿರ್ದಲ್ಲಿ,", 
        "18927": "ಅಂಗಾಲಕಣ್ಣವರು ಮೈಯಲ್ಲಾ ಕಣ್ಣವರು ತಾನಿರ್ದಲ್ಲಿ,", 
        "18928": "ಬ್ರಹ್ಮವಿಷ್ಣ್ವಾದಿಗಳು ತಾನಿರ್ದಲ್ಲಿ, ರುದ್ರ ಈಶ್ವರರು ತಾನಿರ್ದಲ್ಲಿ,", 
        "18929": "ಪೈಥ್ವಿ  ಅಪ್ಪು ತೇಜ ವಾಯುವಾಕಾಶ ಚಂದ್ರ ಸೂರ್ಯ ಆತ್ಮರೆಂಬೀ", 
        "18930": "ಅತಳಲೋಕ ಸುತಳಲೋಕ ತಾನಿರ್ದಲ್ಲಿ,", 
        "18931": "ಋಗ್ವೇದ ಯಜುರ್ವೇದ ತಾನಿರ್ದಲ್ಲಿ,", 
        "18932": "ಸಪ್ತಕೋಟಿ ಮಹಾಮಂತ್ರಂಗಳು ತಾನಿರ್ದಲ್ಲಿ,", 
        "18933": "ಮತ್ರ್ಯಲೋಕದ ಮಹಾಗಣಂಗಳೆಲ್ಲ  ತಾನಿರ್ದಲ್ಲಿ,", 
        "18934": "ಏಕೋ ರುದ್ರಮಹೇಶ್ವರಾ ಎಂಬ ಮಹೇಶ್ವರತತ್ವ ತಾನಿರ್ದಲ್ಲಿ,", 
        "18935": "ಅನಂತಕೋಟಿ ಇಂದ್ರಾದಿಗಳೆಲ್ಲ ಇಂದ್ರಸಂಸಾರಕ್ಕೊಳಗಾಗಿ", 
        "18936": "ಶ್ರೋತ್ರ, ತ್ವಕ್ಕು, ನೇತ್ರ, ಜಿಹ್ವೆ, ಘ್ರಾಣವೆಂಬ", 
        "18937": "ನಿವೈತ್ತಿ ಕಲೆ ಪ್ರತಿಷ್ಠಾಕಲೆ ತಾನಿರ್ದಲ್ಲಿ,", 
        "18938": "ಇಡಾ ಪಿಂಗಳ ಸುಷುಮ್ನ ಗಾಂಧಾರಿ ಹಸ್ತಿ  ಜಿಂಹ್ವೆ", 
        "18939": "ಇಡೆಯಲ್ಲಿ  ಸುಳಿವ ವಾಯುವ ಸ್ವೀಕರಿಸಿ ನಿಜವನರಿಯದೆ", 
        "18940": "ಕಲ್ಲದೇವರು ದೇವರಲ್ಲ, ಮಣ್ಣದೇವರು ದೇವರಲ್ಲ ,", 
        "18941": "ಬ್ರಹ್ಮ ದೇವರಲ್ಲ, ವಿಷ್ಣು ದೇವರಲ್ಲ, ರುದ್ರ ದೇವರಲ್ಲ,", 
        "18942": "ಗಂಗಾಧರ ಗೌರೀಶ ದೇವರಲ್ಲ, ಶಂಕರ ಶಶಿಧರ ದೇವರಲ್ಲ,", 
        "18943": "ನಾಸಿಕದ ತುದಿಯಲ್ಲಿ ಆಡುವ ಪ್ರಾಣಾವಾಯು", 
        "18944": "ಪೃಥ್ವಿ ಅಪ್ಪು ತೇಜ ವಾಯು ಆಕಾಶವೆಂಬ", 
        "18945": "ಪಿಂಗಳನಾಳದಲ್ಲಿ ಆಡುವ ಸೂರ್ಯನ ದೇವರೆಂಬರು ;", 
        "18946": "ಆಧಾರ ಸ್ವಾಧಿಷ್ಠಾನ ಮಣಿಪೂರಕ ಅನಾಹತ", 
        "18947": "ಬ್ರಹ್ಮಚಕ್ರದ ಸಹಸ್ರದಳಪದ್ಮದೊಳು ದೇವರಿಹುದು,", 
        "18948": "ಹೃದಯಕಮಲಮಧ್ಯದಲ್ಲಿ ಲಕ್ಷವಿಟ್ಟು", 
        "18949": "ಭೂಚರಿಯಮುದ್ರೆಯ ದೇವರೆಂಬರು,", 
        "18950": "ತಾನೆ ಚಿನ್ನಾದ, ತಾನೆ ಚಿದ್ಬಿಂದು, ತಾನೆ ಚಿತ್ಕಲೆ", 
        "18951": "ತಾನೆ ಚಿತ್ಪ್ರಕಾಶ ತಾನೆ ಚಿದಾಕಾಶ ತಾನೆ ಬಿಂದ್ವಾಕಾಶ ನೋಡಾ.", 
        "18952": "ಆದಿ ಮಕಾರಪ್ರಣವ, ಆದಿ ಅಕಾರಪ್ರಣವ, ಆದಿ ಉಕಾರಪ್ರಣವ", 
        "18953": "ಆ ಮಕಾರಪ್ರಣವಕ್ಕೆ ಆದಿ ಕಲಾಪ್ರಣವವೇ ಆಧಾರ.", 
        "18954": "ಇದಕ್ಕೆ ಓಂಕಾರೋಪನಿಷತ್ :", 
        "18955": "ಇನ್ನು ಆ ಅಖಂಡಮಹಾಜ್ಯೋತಿಪ್ರಣವದ", 
        "18956": "ಇನ್ನು ಷಟ್ಸ್ಥಲಬ್ರಹ್ಮವಾಗಿಹ", 
        "18957": "ಆ ಅಖಂಡಮಹಾಜ್ಯೋತಿಪ್ರಣವದ ಜ್ಯೋತಿಸ್ವರೂಪವಾಗಿಹ", 
        "18958": "ಆ ಅಖಂಡಮಹಾಜ್ಯೋತಿಪ್ರಣವದ ದರ್ಪಣಾಕಾರವಾಗಿಹ", 
        "18959": "ಆ ಅಖಂಡಮಹಾಜ್ಯೋತಿಪ್ರಣವದ ಅರ್ಧಚಂದ್ರಕಸ್ವರೂಪವಾಗಿಹ", 
        "18960": "ಆ ಅಖಂಡಮಹಾಜ್ಯೋತಿಪ್ರಣವದ ಕುಂಡಲಾಕಾರವಾಗಿಹ", 
        "18961": "ಆ ಅಖಂಡಮಹಾಜ್ಯೋತಿಪ್ರಣವದ ದಂಡಕಸ್ವರೂಪವಾಗಿಹ", 
        "18962": "ಆ ಅಖಂಡಮಹಾಜ್ಯೋತಿಪ್ರಣವದ ತಾರಕಸ್ವರೂಪವಾಗಿಹ", 
        "18963": "ನಿಃಶಬ್ದವೆಂಬ ಪರಬ್ರಹ್ಮದ ಚಿಂತಾಶಕ್ತಿಯ", 
        "18964": "ಚಿಚ್ಛಕ್ತಿ  ಪರಾಶಕ್ತಿ  ಆದಿಶಕ್ತಿ  ಇಚ್ಛಾಶಕ್ತಿ  ಜ್ಞಾನಶಕ್ತಿ  ಕ್ರಿಯಾಶಕ್ತಿ", 
        "18965": "ಇನ್ನು ಷಡಂಗ ಉತ್ಪತ್ಯವದೆಂತೆಂದಡೆ :", 
        "18966": "ಪೃಥ್ವಿ ಅಪ್ಪು ತೇಜ ವಾಯು ಆಕಾಶ ಕ್ಷೇತ್ರಜ್ಞನು", 
        "18967": "ಗಂಧ ರಸ ರೂಪ ಸ್ಪರ್ಶ ಶಬ್ದ  ಕರ್ತನು", 
        "18968": "ಚಿತ್ತ  ಬುದ್ಧಿ  ಅಹಂಕಾರ ಮನ ಜ್ಞಾನ ಭಾವ", 
        "18969": "ಘ್ರಾಣ ಜಿಹ್ವೆ ನೇತ್ರ ತ್ವಕ್ಕು ಶ್ರೋತ್ರ ಚೇತನ", 
        "18970": "ಪಾಯು ಗುಹ್ಯ ಪಾದ ಪಾಣಿ ವಾಕ್ ಅಂತರ", 
        "18971": "ಜಗತ್ ಸೃಷ್ಟಾ ್ಯರ್ಥಕಾರಣವಾಗಿ", 
        "18972": "ಶಿವತತ್ವದ ಪೃಥ್ವಿಯೆಂದು, ಶಿವತತ್ವದ ಅಪ್ಪುವೆಂದು,", 
        "18973": "ಆ ಶಿವತತ್ವದ ಪೃಥ್ವಿಯ ಮೇಲೆ ನಿರಾಳ ಆಧಾರಚಕ್ರ.", 
        "18974": "ಶಿವತತ್ತ್ವದ ಅಪ್ಪುವಿನ ಮೇಲೆ ನಿರಾಳ ಸ್ವಾಧಿಷ್ಠಾನಚಕ್ರ,", 
        "18975": "ಶಿವತತ್ವದ ತೇಜದ ಮೇಲೆ ನಿರಾಳ ಮಣಿಪೂರ ಚಕ್ರ.", 
        "18976": "ಶಿವತತ್ವದ ವಾಯುವಿನ ಮೇಲೆ ನಿರಾಳ ಅನಾಹತಚಕ್ರ.", 
        "18977": "ಶಿವತತ್ತ್ವದ ಆಕಾಶದ ಮೇಲೆ ನಿರಾಳ ವಿಶುದ್ಧಿಚಕ್ರ.", 
        "18978": "ಶಿವತತ್ತ್ವದ ಹೃದಯದ ಮೇಲೆ ನಿರಾಳ ಆಜ್ಞಾಚಕ್ರ.", 
        "18979": "ನಿರಾಳ ಷಡುಚಕ್ರಂಗಳ ಮೇಲೆ ನಾಲ್ಕು ಚಕ್ರಂಗಳುಂಟು.", 
        "18980": "ಇನ್ನು ನಿರಾಳ ಷಡುಚಕ್ರಂಗಳ ಮೇಲಣ", 
        "18981": "ನಿರಾಮಯ ಭಕ್ತ, ನಿರಾಮಯ ಮಹೇಶ್ವರ,", 
        "18982": "ಇನ್ನು ನಿರಾಮಯ ಭಕ್ತಂಗೆ ನಿರಾಮಯವೇ ಅಂಗ.", 
        "18983": "ನಿರಾಮಯ ಮಹೇಶ್ವರಂಗೆ  ನಿರಾಮಯವೆ  ಅಂಗ,", 
        "18984": "ನಿರಾಮಯ ಪ್ರಸಾದಿಗೆ ನಿರಾಮಯವೆ ಅಂಗ,", 
        "18985": "ನಿರಾಮಯ ಪ್ರಾಣಲಿಂಗಿಗೆ ನಿರಾಮಯವೆ ಅಂಗ,", 
        "18986": "ನಿರಾಮಯ ಶರಣಂಗೆ ನಿರಾಮಯವೆ ಅಂಗ,", 
        "18987": "ನಿರಾಮಯ ಐಕ್ಯಂಗೆ ನಿರಾಮಯವೆ ಅಂಗ,", 
        "18988": "ಪರತತ್ತ್ವದ ಪೃಥ್ವಿಯೆಂದು, ಪರತತ್ತ್ವದ ಅಪ್ಪುವೆಂದು,", 
        "18989": "ಆ ಪರತತ್ತ್ವದ ಪೃಥ್ವಿಯ ಮೇಲೆ ನಿರಂಜನ ಆಧಾರಚಕ್ರ.", 
        "18990": "ಪರತತ್ತ್ವದ ಅಪ್ಪುವಿನ ಮೇಲೆ ನಿರಂಜನ ಸ್ವಾಧಿಷ್ಠಾನಚಕ್ರ.", 
        "18991": "ಪರತತ್ತ್ವದ ತೇಜದ ಮೇಲೆ ನಿರಂಜನ ಮಣಿಪೂರಕಚಕ್ರ.", 
        "18992": "ಪರತತ್ತ್ವದ ವಾಯುವಿನ ಮೇಲೆ ನಿರಂಜನ ಅನಾಹತಚಕ್ರ.", 
        "18993": "ಪರತತ್ತ್ವದ ಹೃದಯದ ಮೇಲೆ ನಿರಂಜನ ಆಜ್ಞಾಚಕ್ರ.", 
        "18994": "ಇನ್ನು ನಿರಂಜನ ಷಡುಚಕ್ರಂಗಳ ಮೇಲೆ ನಾಲ್ಕು ಚಕ್ರಂಗಳುಂಟು.", 
        "18995": "ಇನ್ನು ನಿರಂಜನಷಡುಚಕ್ರಂಗಳ ಮೇಲಣ ನಾಲ್ಕು ಚಕ್ರಂಗಳ", 
        "18996": "ನಿರಂಜನಾತೀತ ಭಕ್ತ, ನಿರಂಜನಾತೀತ ಮಹೇಶ್ವರ,", 
        "18997": "ಇನ್ನು ನಿರಂಜನಾತೀತ ಷಟ್‍ಸ್ಥಲ ಬ್ರಹ್ಮದ", 
        "18998": "ಜಾಗ್ರದಲ್ಲಿಯ ಸ್ವಪ್ನವಾವುದು ?", 
        "18999": "ಜಾಗ್ರದಲ್ಲಿಯ ಜಾಗ್ರವಾವುದು ?", 
        "19000": "ಮುಂದೆ ಹೇಳಿದ ಪ್ರೇರಕಾವಸ್ಥೆಯಲ್ಲಿ  ಹೇಳಿದ", 
        "19001": "ಇನ್ನು ಕೆಳಗಾದವಸ್ಥೆಯ ದರ್ಶನವದೆಂತೆಂದಡೆ :", 
        "19002": "ಸ್ವಪ್ನವಾವುದು ?", 
        "19003": "ಸುಷುಪ್ತಿ  ಯಾವುದು ?", 
        "19004": "ತೂರ್ಯವಾವುದು ?", 
        "19005": "ತೂರ್ಯಾತೀತವಾವುದು ?", 
        "19006": "ಇನ್ನು ಮೇಲಾದವಸ್ಥೆಯ ದರ್ಶನವದೆಂತೆಂದಡೆ :", 
        "19007": "ನಾದ ಬಿಂದುಗಳಿಗಿಂಬಾಗಿ ನಿಂದು", 
        "19008": "ನಾದ ಬಿಂದು ಸಾದಾಖ್ಯ ಇಂಬಾಗಿ ನಿಂದು ಪುರುಷನನು,", 
        "19009": "ನಾದ ಬಿಂದು ಸಾದಾಖ್ಯ ಈಶ್ವರ ಇಂಬಾಗಿ ನಿಂದು,", 
        "19010": "ಶಿವತತ್ವವೈದು ಇಂಬಾಗಿ ನಿಂದು", 
        "19011": "ಇನ್ನು ಕೇವಲಾವಸ್ಥೆಯ ದರ್ಶನವದೆಂತೆಂದಡೆ :", 
        "19012": "ಇನ್ನು ಶುದ್ಧಾವಸ್ಥೆಯ ದರ್ಶನವೆಂತೆಂದಡೆ :", 
        "19013": "ಇನ್ನು ನಿರ್ಮಲಾವಸ್ಥೆಯ ದರ್ಶನವ ಮಾಡುವಾಗ", 
        "19014": "ನಿರಂಜನಜಾಗ್ರದಲ್ಲಿನಿಂದಡೆ ಭಕ್ತನೆಂಬೆ.", 
        "19015": "ನಕಾರದೊಳಗೆ ಐವತ್ತೊಂದಕ್ಷರವನರಿಯದೆ", 
        "19016": "ಪರಸ್ತ್ರೀ ಪರಾರ್ಥ ಪರಾನ್ನಕ್ಕೆ ಸುಳಿವ ಅಣ್ಣಗಳು ನೀವು ಕೇಳಿರೆ.", 
        "19017": "ಪರಧನ ಪರಸ್ತ್ರೀ ಪರಾನ್ನದಾಸೆಯ ಬಿಡದೆ,", 
        "19018": "ಆರು ಬೀಜವ ಮೀರಿ ತೋರಿತ್ತು  ನೋಡಾ ಒಂದು ಬೀಜ,", 
        "19019": "ಬಣ್ಣವಿಲ್ಲದ ಪಕ್ಷಿ ಬಯಲ ತತ್ತಿಯನಿಕ್ಕಿತ್ತು ನೋಡಾ.", 
        "19020": "ಅಂಧಕಾರವಾಗಿಹ ಕತ್ತಲೆಯೊಳು ಮಹಾಮೇರುವಿಹುದು ನೋಡಾ.", 
        "19021": "ಅಂದು ಮೊದಲಾಗಿ ಇಂದು ಕಡೆಯಾಗಿ", 
        "19022": "ರೂಪಿಲ್ಲದ ಪುಸ್ತಕದ ಬರಹವ", 
        "19023": "ಓಂಕಾರವೆಂಬ ಬಾವಿಯೊಳಗೆ ಒಂದು ಮರ ಹುಟ್ಟಿತ್ತು ನೋಡಾ.", 
        "19024": "ತತ್ವಮೂರರಾದಿಯನರಿದು,", 
        "19025": "ತ್ರಿಪುರಂಗಳ ಸಂಹಾರವ ಮಾಡಿ,", 
        "19026": "ಸಕಲಾಗಮ ಶಿಖಾಮಣಿಯನು,", 
        "19027": "ಅವಾಚ್ಯತತ್ತ್ವ ತಲೆದೋರದಂದು,", 
        "19028": "ನಿರಂಜನಪ್ರಣವ  ಅವಾಚ್ಯಪ್ರಣವ  ಉತ್ಪತ್ಯವಾಗದತ್ತತ್ತ ,", 
        "19029": "ಸಕಲತತ್ವವಿಲ್ಲದಂದು, ನಿಷ್ಕಲತತ್ವವಿಲ್ಲದಂದು,", 
        "19030": "ಏನು ಏನೂ ಎನಲಿಲ್ಲದಂದು ಮಹಾಘನ ನಿರಂಜನಾತೀತವಾಗಿಹ ವಸ್ತು", 
        "19031": "ನಿರಾಳಜಾಗ್ರ ನಿರಾಳಸ್ವಪ್ನವಿಲ್ಲದತ್ತತ್ತ ,", 
        "19032": "ನಿರ್ಮಲಜಾಗ್ರ ನಿರ್ಮಲಸ್ವಪ್ನವಿಲ್ಲದಂದು,", 
        "19033": "ಶಿವಜಾಗ್ರ ಶಿವಸ್ವಪ್ನವಿಲ್ಲದಂದು,", 
        "19034": "ಜ್ಞಾನಜಾಗ್ರ ಜ್ಞಾನಸ್ವಪ್ನವಿಲ್ಲದ ಮುನ್ನ,", 
        "19035": "ಶಿವತತ್ವವಿಲ್ಲದಂದು, ಸದಾಶಿವತತ್ವವಿಲ್ಲದಂದು,", 
        "19036": "ನಿರಂಜನಪ್ರಣವದ ನೆನಹುಮಾತ್ರದಿಂದ", 
        "19037": "ಇನ್ನು ಸಹಸ್ರಾಕ್ಷರ ತ್ರಯಾಕ್ಷರ ಏಕಾಕ್ಷರ ನಿವೃತ್ತಿ ಅದೆಂತೆಂದಡೆ :", 
        "19038": "ಇನ್ನು ಅಂತರಾತ್ಮ ಪರಮಾತ್ಮನ ನಿವೃತ್ತಿ ಅದೆಂತೆಂದಡೆ :", 
        "19039": "ಏನು ಏನೂ ಎನಲಿಲ್ಲದ ಮಹಾಘನ", 
        "19040": "ಪೃಥ್ವಿ, ಅಪ್ಪು, ತೇಜ, ವಾಯು, ಆಕಾಶ, ಆತ್ಮನು ಈ ಪ್ರಕಾರವು", 
        "19041": "ಇನ್ನು ಷಡ್ವಿಧಲಿಂಗ ಅದೆಂತೆಂದಡೆ :", 
        "19042": "ವೇದಾಂತತತ್ವವೆಂಬ ಅಷ್ಟವಿಂಶತಿತತ್ವವನೊಳಕೊಂಡು", 
        "19043": "ಇಂದ್ರ ಇಂದ್ರರೆಂಬುವರನೇಕ ಕೋಟಿ", 
        "19044": "ನಿರಂಜನ ಪ್ರಣವದುತ್ಪತ್ಯ :", 
        "19045": "ಇನ್ನು ಷಡಧ್ವದುತ್ಪತ್ಯವದೆಂತೆಂದಡೆ :", 
        "19046": "ಈ ಷಡ್ವಿಧದಿಂದವೆ ಅನೇಕ ವೇದಂಗಳೆಸಗಿತ್ತು.", 
        "19047": "ದಾಸಿಯ ಸಂಗವುಳ್ಳನ್ನಬರ ಗುರುವಿಲ್ಲವೆಂಬ", 
        "19048": "ಹೆಣ್ಣೆಂಬ ಭೂತವ ಸೋಂಕಿ ಹೆಣನಾಗಿಹ ಗುರುಗಳು", 
        "19049": "ಪಸರ ಪಸರ ತಪ್ಪದಿಹ ಗಾಜುಗಳೆಲ್ಲ ರತ್ನವಾಗಬಹುದೆ ಅಯ್ಯಾ ?", 
        "19050": "ಹೊನ್ನು ಹೆಣ್ಣು ಮಣ್ಣು ಹಿಡಿವನ್ನಕ್ಕ ಗುರುವಲ್ಲ.", 
        "19051": "ಪಂಚಾಕ್ಷರಿ ಪಂಚವಕ್ತ್ರಂಗಳ ನೆಲೆಯನರಿಯರು", 
        "19052": "ತಾನೆ ಶಿವಪ್ರಣವ, ತಾನೆ ಶಕ್ತಿಪ್ರಣವ,", 
        "19146": "ಪರತತ್ತ್ವದ ಆಕಾಶದ ಮೇಲೆ ನಿರಂಜನ ವಿಶುದ್ಧಿಚಕ್ರ.", 
        "19148": "ನಿರಂಜನಾತೀತ ಮಹೇಶ್ವರಂಗೆ ನಿರಂಜನಾತೀತವೇ ಅಂಗ,", 
        "19150": "ನಿರಂಜನಾತೀತಪ್ರಸಾದಿಗೆ ನಿರಂಜನಾತೀತವೇ ಅಂಗ,", 
        "19151": "ನಿರಂಜನಾತೀತಪ್ರಾಣಲಿಂಗಿಗೆ ನಿರಂಜನಾತೀತವೇ ಅಂಗ,", 
        "19152": "ನಿರಂಜನಾತೀತಶರಣಂಗೆ ನಿರಂಜನಾತೀತವೆ ಅಂಗ", 
        "19154": "ನಿರಂಜನಾತೀತಐಕ್ಯಂಗೆ ನಿರಂಜನಾತೀತವೇ ಅಂಗ", 
        "19156": "ನಿರಂಜನಾತೀತಷಟ್‍ಸ್ಥಲಬ್ರಹ್ಮ ಅಂಗವಾಗಿ", 
        "19157": "ಪ್ರೇರಕಾವಸ್ಥೆ  ಒಂದು, ಮಧ್ಯಾವಸ್ಥೆ  ಐದು", 
        "19159": "ಇನ್ನು  ಪ್ರೇರಕಾವಸ್ಥೆಯ ದರ್ಶನವದೆಂತೆಂದಡೆ", 
        "19160": "ಇನ್ನು ಮಧ್ಯಾವಸ್ಥೆಯ ದರ್ಶನವದೆಂತೆಂದಡೆ", 
        "19161": "ಜಾಗ್ರದಲ್ಲಿಯ ಸುಷುಪ್ತಿ ಯಾವುದು ?", 
        "19165": "ಇನ್ನು ಮುಂದೆ ಹೇಳಿದ ನಿರ್ಮಲಾವಸ್ಥೆಯ ದರ್ಶನವದೆಂತೆಂದಡೆ :", 
        "19166": "ಆ ಪರಮಭೋಗಿಯಲ್ಲಿಯೆ ಸಂತೋಷವಳಿದು", 
        "19167": "ಅವಸ್ಥೆಗಳಿಪ್ಪತ್ತುನಾಲ್ಕನು", 
        "19168": "ಅವನು ಅವಳು ಅದು ನಾನೆಂಬ ಜ್ಯೋತಿ ಅಡಗಿತ್ತಾಗಿ ಕರ್ಮ ನಷ್ಟ.", 
        "19169": "ಅದಂಥಾದಿಂಥಾದೆಂದು ನೋಡುವ ರೂಪ ನಿರೂಪವ ಬಿಟ್ಟು", 
        "19170": "ಇನ್ನು ಜ್ಞಾನಾವಸ್ಥೆಯ ದರ್ಶನವದೆಂತೆಂದಡೆ :", 
        "19171": "ಇನ್ನು ಶಿವಾವಸ್ಥೆಯ ದರ್ಶನವದೆಂತೆಂದಡೆ :", 
        "19172": "ಇನ್ನು ನಿರಾಳವಸ್ಥೆಯ ದರ್ಶನವದೆಂತೆಂದಡೆ :", 
        "19173": "ಇನ್ನು ನಿರಂಜನಾವಸ್ಥೆಯ ದರ್ಶನವದೆಂತೆಂದಡೆ :", 
        "19174": "ಶ್ರೋತ್ರದ್ವಾರಂಗಳೆರಡು ದ್ವಯದಳ", 
        "19175": "ನಿರಾಮಯದೊಳು ನಿರಾಕಾರವಾಗಿ ಹುಟ್ಟಿತ್ತು  ನೋಡಾ ಒಂದು ಪದ್ಮ.", 
        "19176": "ಅಕಾರವೆಂಬ ಅಷ್ಟದಳಕಮಲದ ಮಧ್ಯದಲ್ಲಿಯೂ", 
        "19177": "ನಿರಾಮಯದೊಳು ಹುಟ್ಟಿತು ನೋಡಾ ಒಂದು ಪದ್ಮ.", 
        "19178": "ನಿರಾಳದಷ್ಟದಳದ ಕಮಲದೊಳು", 
        "19179": "ಅಖಂಡಜ್ಯೋತಿರ್ಮಯವಾಗಿಹ ಗೋಳಕಾಕಾರ ಪ್ರಣವದ", 
        "19180": "ಮತ್ತಂ, ಆ ಪ್ರಣವದ ದರ್ಪಣಾಕಾರದಲ್ಲಿ", 
        "19181": "ಈಶಾನಮುಖದಲ್ಲಿ  ಈಶಾನಮಂತ್ರ ಉತ್ಪತ್ಯವಾಯಿತ್ತು.", 
        "19182": "ಇನ್ನು ತೊಂಬತ್ತುನಾಲ್ಕು ವ್ಯೋಮವ್ಯಾಪಿ ಪದಂಗಳುತ್ಪತ್ಯವದೆಂತೆಂದಡೆ :", 
        "19183": "ಇನ್ನು ಐವತ್ತೆರಡು ಅಕ್ಷರವದೆಂತೆಂದಡೆ :", 
        "19184": "ಪ್ರಣವದ ಜ್ಯೋತಿಸ್ವರೂಪದಲ್ಲಿಹ ಚಿದಾತ್ಮ ಪರಮಾತ್ಮನಲ್ಲಿ", 
        "19185": "ಇನ್ನು ಇನ್ನೂರ ಇಪ್ಪತ್ತುನಾಲ್ಕು ಭುವನಂಗಳ ಉತ್ಪತ್ಯವೆಂತೆಂದಡೆ :", 
        "19186": "ಇನ್ನು ಇನ್ನೂರ ಇಪ್ಪತ್ತುನಾಲ್ಕು ಭುವನಂಗಳ ವಿವರವದೆಂತೆಂದಡೆ :", 
        "19187": "ಇನ್ನು ಮೂವತ್ತಾರು ತತ್ತ್ವಂಗಳುತ್ಪತ್ಯವದೆಂತೆಂದಡೆ :", 
        "19188": "ಇನ್ನು  ಸಕಲತತ್ವದಲ್ಲಿ ಇಪ್ಪತ್ತುನಾಲ್ಕುತತ್ವ ಉತ್ಪತ್ಯವದೆಂತೆಂದಡೆ :", 
        "19189": "ಇನ್ನು  ಷಟ್‍ಕಲೆಗಳುತ್ಪತ್ಯವದೆಂತೆಂದಡೆ :", 
        "19190": "ಇನ್ನು ಷಡಧ್ವನ್ಯಾಸವದೆಂತೆಂದಡೆ :", 
        "19191": "ಅಲ್ಲಿಂದ ಮೇಲೆ ಸ್ವಾಧಿಷ್ಠಾನಚಕ್ರದ", 
        "19192": "ಅಲ್ಲಿಂದ ಮೇಲೆ ಮಣಿಪೂರಕ ಚಕ್ರದ", 
        "19193": "ಅಲ್ಲಿಂದ ಮೇಲೆ ಅನಾಹತಚಕ್ರದ", 
        "19194": "ಅಲ್ಲಿಂದ ಮೇಲೆ ವಿಶುದ್ಧಿಚಕ್ರದ", 
        "19195": "ಅಲ್ಲಿಂದ ಮೇಲೆ ಆಜ್ಞಾಚಕ್ರದ ಚತುರ್ದಳಪದ್ಮದ", 
        "19196": "ಈ ಮಂತ್ರಾಧ್ವ ಪದಾಧ್ವವ ತನ್ನಲ್ಲಿ ತಿಳಿದು", 
        "19197": "ಅಖಂಡ ಜ್ಯೋತಿರ್ಮಯವಾಗಿಹ ಗೋಳಕಾಕಾರಪ್ರಣವದ", 
        "19198": "ಈಶಾನಮುಖದಲ್ಲಿ  ಈಶಾನಮಂತ್ರವಡಗಿತ್ತು.", 
        "19199": "ಆ ಅಖಂಡ ಜ್ಯೋತಿರ್ಮಯವಾಗಿಹ ಗೋಳಕಾಕಾರ ಪ್ರಣವದ", 
        "19200": "ವ್ಯೋಮವ್ಯಾಪಿ ಮೊದಲಾಗಿ ಓಂಕಾರವೆಂಬ ಪದ ಕಡೆಯಾಗಿ", 
        "19201": "ವ ಶ ಷ ಸ ಎಂಬ ಚತುವರ್ಣಾಕ್ಷರವು", 
        "19202": "ಕ ಖ ಗ ಘ ಙ ಚ ಛ ಜ ಝ ಞ ಟ ಠ", 
        "19203": "ಇನ್ನು ಪಂಚಾಕ್ಷರಂಗಳ ನಿವೃತ್ತಿಯೆಂತೆಂದಡೆ :", 
        "19204": "ಅನಾಶ್ರಿತವೆಂಬ ಭುವನ ಮೊದಲಾಗಿ", 
        "19205": "ಇನ್ನು ಮೂವತ್ತಾರು ತತ್ವಂಗಳ ನಿವೃತ್ತಿ ಎಂತೆಂದಡೆ :", 
        "19206": "ಗುಣತ್ರಯ ಮನ ಬುದ್ಧಿ ಚಿತ್ತ ಅಹಂಕಾರ", 
        "19207": "ಆಕಾಶ ಚೈತನ್ಯ ಭಾವ ಕರ್ತ ಕ್ಷೇತ್ರಜ್ಞ ಶಿವನು- ಈ ಆರು ತತ್ತ್ವಂಗಳು", 
        "19208": "ವಾಕ್ ಶ್ರೋತ್ರ ಜ್ಞಾನ ಶಬ್ದ ಮಹಾಕಾಶ ಸದಾಶಿವನು", 
        "19209": "ಪಾಣಿ ತ್ವಕ್ಕು ಮನ ಸ್ಪರ್ಶ ವಾಯು ಈಶ್ವರನು", 
        "19210": "ಪಾದ ನೇತ್ರ ಅಹಂಕಾರ ರೂಪ ಅಗ್ನಿ ರುದ್ರನು", 
        "19211": "ಗುಹ್ಯ ಚಿಹ್ವೆ ಬುದ್ಧಿ ರಸ ಅಪ್ಪು ವಿಷ್ಣು", 
        "19212": "ಗುದ ಘ್ರಾಣ ಚಿತ್ತ ಗಂಧ ಪೃಥ್ವಿ ಬ್ರಹ್ಮ", 
        "19213": "ಇನ್ನು ಷಡಂಗನಿವೈತ್ತಿ ಅದೆಂತೆಂದಡೆ :", 
        "19214": "ಪೃಥ್ವಿ ಅಪ್ಪು ತೇಜ ವಾಯು ಆಕಾಶ ಕ್ಷೇತ್ರಜ್ಞ", 
        "19215": "ಗಂಧ ರಸ ರೂಪ ಸ್ಪರ್ಶ ಶಬ್ದ ಕರ್ತನು", 
        "19216": "ಚಿತ್ತ ಬುದ್ಧಿ ಅಹಂಕಾರ ಮನ ಜ್ಞಾನ ಭಾವ", 
        "19217": "ಘ್ರಾಣ ಜಿಹ್ವೆ ನೇತ್ರ ತ್ವಕ್ಕು ಶ್ರೋತ್ರ ಚೇತನ", 
        "19218": "ಪಾಯು ಗುಹ್ಯ ಪಾದ ಪಾಣಿ ವಾಕ್ ಅಂತರ್", 
        "19219": "ಇನ್ನು ಷಡುಶಕ್ತಿಗಳ ನಿವೃತ್ತಿ  ಅದೆಂತೆಂದಡೆ :", 
        "19220": "ಅನಂತಕೋಟಿ ತತ್ವಂಗಳನೊಳಕೊಂಡು", 
        "19221": "ಪರಬ್ರಹ್ಮಸ್ವರೂಪವಾಗಿಹ ಪರಮಪ್ರಣವದ ತಾರಕಸ್ವರೂಪದಲ್ಲಿ", 
        "19222": "ಇನ್ನು ಭಕ್ತ ಮಾಹೇಶ್ವರ ಪ್ರಸಾದಿ ಪ್ರಾಣಲಿಂಗಿ", 
        "19223": "ಇನ್ನು ಷಡ್ವಿಧಹಸ್ತನಿವೃತ್ತಿ ಅದೆಂತೆಂದಡೆ :", 
        "19224": "ಇನ್ನು ಷಡ್ವಿಧಲಿಂಗನಿವೃತ್ತಿ ಅದೆಂತೆಂದಡೆ :", 
        "19225": "ಇನ್ನು ಷಡ್ವಿಧಮುಖಂಗಳ ನಿವೃತ್ತಿ ಅದೆಂತೆಂದಡೆ :", 
        "19226": "ಇನ್ನು ಷಡ್ವಿಧಪರಿಣಾಮದ ನಿವೃತ್ತಿ ಅದೆಂತೆಂದಡೆ :", 
        "19227": "ಪೃಥ್ವಿ ಅಪ್ಪು ತೇಜ ವಾಯು ಆಕಾಶ ಆತ್ಮನೆಂಬ", 
        "19228": "ಸ್ವಾಧಿಷ್ಠಾನಚಕ್ರದ ಸಹಸ್ರಾಂಶದಲ್ಲಿ ಆಧಾರಚಕ್ರವಡಗಿತ್ತು .", 
        "19229": "ಇನ್ನು ದ್ವಿದಶಕಮಲಂಗಳ ನಿವೃತ್ತಿ ಅದೆಂತೆಂದಡೆ :", 
        "19230": "ಇನ್ನು ವಿಂಶತಿಕಮಲದಳಾಕ್ಷರಂಗಳ ನಿವೃತ್ತಿ ಅದೆಂತೆಂದಡೆ :", 
        "19231": "ಇನ್ನು ಪಂಚಾಕ್ಷರದ ನಿವೃತ್ತಿ ಅದೆಂತೆಂದಡೆ :", 
        "19232": "ಇನ್ನು ಅಖಂಡಜ್ಯೋತಿರ್ಮಯವಾಗಿಹ ಗೋಳಕಾಕಾರಪ್ರಣವದ", 
        "19233": "ಇನ್ನು ಷಡ್ವಿಧಭೂತಂಗಳ ನಿವೃತ್ತಿ  ಅದೆಂತೆಂದಡೆ :", 
        "19234": "ಇನ್ನು ಷಡ್ವಿಧಮುಖಂಗಳ ನಿವೃತ್ತಿ ಅದೆಂತೆಂದಡೆ :", 
        "19235": "ಇನ್ನು ಷಡ್ವಿಧಲಿಂಗದ ನಿವೃತ್ತಿ ಅದೆಂತೆಂದಡೆ :", 
        "19236": "ಇನ್ನು ಷಡ್ವಿಧಸಾದಾಖ್ಯಂಗಳ ನಿವೃತ್ತಿ ಅದೆಂತೆಂದಡೆ :", 
        "19237": "ಇನ್ನು ಷಡ್ವಿಧಕಲೆಗಳ ನಿವೃತ್ತಿ ಅದೆಂತೆಂದಡೆ :", 
        "19238": "ಇನ್ನು ಷಡ್ವಿಧಹಸ್ತಂಗಳ ನಿವೃತ್ತಿ ಅದೆಂತೆಂದಡೆ :", 
        "19239": "ಇನ್ನು ನವಶಕ್ತಿಗಳ ನಿವೃತ್ತಿ ಅದೆಂತೆಂದಡೆ :", 
        "19240": "ಇನ್ನು  ವಿಂಶತಿಚಕ್ರಂಗಳ ಅಧಿದೇವತೆಗಳ ನಿವೃತ್ತಿ ಅದೆಂತೆಂದಡೆ:", 
        "19241": "ಇನ್ನು ಅಷ್ಟನಾದನಿವೃತ್ತಿಯೆಂತೆಂದಡೆ :", 
        "19242": "ಇನ್ನು ಷಡ್ವಿಧಭಕ್ತಿಯ ನಿವೃತ್ತಿ ಅದೆಂತೆಂದಡೆ :", 
        "19243": "ಇನ್ನು ಷಡ್ವಿಧದ್ರವ್ಯಂಗಳ ನಿವೃತ್ತಿ ಅದೆಂತೆಂದಡೆ :", 
        "19244": "ಇನ್ನು ಋಗ್ವೇದ ಯಜುರ್ವೇದ ಸಾಮವೇದ", 
        "19245": "ದ್ವಿದಶಚಕ್ರ ಮೊದಲಾಗಿ ಚತುರ್ವೇದ ಅಜಪೆ ಗಾಯತ್ರಿ ಕಡೆಯಾಗಿ", 
        "19246": "ಇನ್ನು ಭಕ್ತನ ತಾಮಸನಿರಸನವದೆಂತೆಂದಡೆ :", 
        "19247": "ಭಕಾರವೇ ಜ್ಞಾನಸ್ವರೂಪ", 
        "19248": "ಭಕ್ತನೆಂಬೆರಡಕ್ಷರವೇ ತಾನೆಂದು ತಿಳಿದು", 
        "19249": "ಇನ್ನು ಗುರುತಾಮಸ ನಿರಸನವದೆಂತೆಂದಡೆ :", 
        "19250": "ಗುಕಾರವೇ ನಿರ್ಗುಣಾತ್ಮನು, ರುಕಾರವೇ ಪರಮಾತ್ಮನು.", 
        "19251": "ಹೊನ್ನು ಹೆಣ್ಣು ಮಣ್ಣೆಂಬ ತ್ರಿವಿಧವಿಡಿದಾತ ಗುರುವಲ್ಲ.", 
        "19252": "ಇನ್ನು ಲಿಂಗದ ತಾಮಸನಿರಸನವದೆಂತೆಂದಡೆ :", 
        "19253": "ಇನ್ನು ಜಂಗಮದ ತಾಮಸನಿರಸನವದೆಂತೆಂದಡೆ :", 
        "19254": "ಹೊನ್ನು ಹೆಣ್ಣು ಮಣ್ಣೆಂಬ ತ್ರಿವಿಧ ಉಳ್ಳವರ ಮನೆಯ ಬಾಗಿಲಕಾಯ್ದು,", 
        "19255": "ಜಟೆಯಾಗಲಿ, ಮುಡಿಯಾಗಲಿ, ಶಿಖಿಯಾಗಲಿ,", 
        "19256": "ಗುರುಲಿಂಗಜಂಗಮವೆಂದು ಸುಳಿವ ಅಣ್ಣಗಳು ನೀವು ಕೇಳಿರೆ :", 
        "19257": "ಹೊನ್ನು ಬಿಡದೆ ಹಿರಿಯರೆಂಬರು ;", 
        "19258": "ಹೊನ್ನ ಬಿಟ್ಟಡೆ ಹಿರಿಯರೆಂಬೆನೆ ?", 
        "19259": "ಹೊನ್ನ ಬಿಟ್ಟರೇನು ? ಹೆಣ್ಣಿನಾಸೆಯ ಬಿಡದನ್ನಕ್ಕ.", 
        "19260": "ಅಕಾರ ಉಕಾರ ಮಕಾರ", 
        "19261": "ಅಕಾರ ಉಕಾರ ಮಕಾರವನರಿಯದೆ,", 
        "19262": "ಉಕಾರದೊಳಗೆ ಉಕಾರವನರಿಯರು", 
        "19263": "ಮಕಾರದೊಳಗೆ ಮಕಾರವನರಿಯರು", 
        "19264": "ಮಂತ್ರ ಹನ್ನೊಂದನರಿಯರು ಆಚಾರ್ಯರೆಂಬರು.", 
        "19265": "ಆಣವ ಮಾಯಾ ಕಾರ್ಮಿಕವೆಂಬ ಮಲತ್ರಯಂಗಳಲ್ಲಿ", 
        "19266": "ಆ ಸದ್ಗುರುಸ್ವಾಮಿ ಸದ್ಯೋಜಾತವಾಮದೇವಮುಖದಲ್ಲಿ", 
        "19267": "ಅಕಾರ ಉಕಾರ ಮಕಾರವನರಿದು", 
        "19268": "ಉಕಾರದೊಳಗೆ ಉಕಾರವನರಿದು", 
        "19269": "ಮಕಾರದೊಳಗೆ ಮಕಾರವನರಿದು", 
        "19270": "ಮಂತ್ರ ಹನ್ನೊಂದು, ಪದ ತೊಂಬತ್ತುನಾಲ್ಕನರಿದು", 
        "19271": "ಅಕಾರ ಉಕಾರ ಮಕಾರ ನಾದ ಬಿಂದು ಕಳೆಗಳ ತಿಳಿದು,", 
        "19272": "ಆಣವ ಮಾಯಾ ಕಾರ್ಮಿಕವೆಂಬ ಮಲತ್ರಯಂಗಳ ಹೊದ್ದದೆ", 
        "19273": "ಎನ್ನ ಮನ ಬುದ್ಧಿ ಚಿತ್ತ  ಅಹಂಕಾರ ಜ್ಞಾನವೆಂಬ ಭೂಮಿಯ ಮೇಲೆ", 
        "19274": "ನಾಮರೂಪುಕ್ರಿಯಾತೀತವಾಗಿ", 
        "19275": "ಈ ವಚನಾನುಭಾವದಲುಳ್ಳರ್ಥವು", 
        "19276": "ಇನ್ನು ಮುಂದೆ ಅನುಭಾವದ ವಚನ ಅದೆಂತೆಂದಡೆ :", 
        "19277": "ಅರಿದಾತ ದುಃಖಕ್ಕೊಳಗಾಗದೆ", 
        "19278": "ತನ್ನನರಿಯದೆ ತಾನೆ ಕೆಟ್ಟೆನೆಂದವು ಶ್ರುತಿಗಳು.", 
        "19279": "ಮೂರವಸ್ಥೆಯ ನೆಲೆಯೆಂದು ಕಾಬವ", 
        "19280": "ಕಾಯ ಜೀವದ ಹೊಲಿಗೆ ಬಿಚ್ಚಲರಿಯದಿದ್ದೆನು ಅನೇಕ ಕಾಲವು.", 
        "19281": "ತಾನೆಂಬ ಅರಿವ ಬಿಟ್ಟು ಮತ್ತೆಲ್ಲವನತಿಗಳದು", 
        "19282": "ಊನವಾಗಿಹ ದೇಹವ ಕೂಡಿಕೊಂಡು ಹೋಗಿ", 
        "19283": "ಜೀವ ಕರಣ ದೇಹ ಇತ್ಯಾದಿಗಳು", 
        "19284": "ಜಾಗ್ರ ಸ್ವಪ್ನ ಸುಷುಪ್ತಿ ತೂರ್ಯ ತೂರ್ಯಾತೀತ", 
        "19285": "ತೂರ್ಯವಡಗಿ ಹೇಳಬಾರದ ಹಾಳವರಿದುದ", 
        "19286": "ವಾಗಾದಿಗಳೈದು, ವಚನಾದಿಗಳೈದು, ಶ್ರೋತ್ರಾದಿಗಳೈದು,", 
        "19287": "ಆ ವ್ಯೋಮಾತೀತವೆಂಬ ಮಹಾಘನದಲ್ಲಿ", 
        "19288": "ಶ್ಲೋಕದೊಳಗಣ ಅರ್ಥದಂತಿದ್ದುದು,", 
        "19289": "ತಿಲದೊಳಗಣ ತೈಲದಂತಿದ್ದುದು,", 
        "19290": "ತನ್ನನುಭೂತಿಯಲ್ಲಿ ತಾ ಕಂಡ ಶರಣನ ನಿಲವು", 
        "19291": "ಕರ್ಮಭಾವವು ಕೆಟ್ಟಡೊಂದು ನಿರ್ವಾಣವೆಂದು", 
        "19292": "ಅಕಾರವೆಂಬೆನೆ  ಉಕಾರವಾಗಿಹುದು,", 
        "19293": "ಬಿಂದುವಾಗಿದ್ದು ಅಲ್ಲದೆ", 
        "19294": "ವೇದಾಗಮ ಪುರಾಣಂಗಳನೋದಿ", 
        "19295": "ಗುರುಕರುಣವಿಲ್ಲದೆ", 
        "19296": "ಅನೇಕ ವೇದಾಗಮಶಾಸ್ತ್ರಪುರಾಣವನೋದಿ ಕೇಳಿದಡೇನು ?", 
        "19297": "ದೇಹವಳಿದು ಜೀವವಳಿದು ಮನವಳಿದು ಅರಿವಳಿದು,", 
        "19298": "ನಿರಾಮಯಾತೀತದಲ್ಲಿ ಪುಟ್ಟಿದ ಶರಣನು", 
        "19299": "ಹೆಣ್ಣೆಂಬೆನೆ ಹೆಣ್ಣಲ್ಲ, ಗಂಡೆಂಬೆನೆ ಗಂಡಲ್ಲ,", 
        "19300": "ನಿರಾಮಯಾತೀತದಲ್ಲಿ ಹುಟ್ಟಿದ ನೋಡಾ ಶರಣನು.", 
        "19301": "ರೂಪಿಲ್ಲದವನರಿದನೆಂದು ನಿರೂಪಲ್ಲದ ಮಾಮರದ ತುದಿಗೆ", 
        "19302": "ಆತ್ಮತತ್ವ ಇಪ್ಪತ್ತೈದು , ವಿದ್ಯಾತತ್ವ ಹತ್ತು, ಶಿವತತ್ತ್ವವೊಂದು.", 
        "19303": "ಷಟ್ಸ್ಥಲಬ್ರಹ್ಮ ಷಟ್ಸ್ಥಲಬ್ರಹ್ಮವೆಂಬರು.", 
        "19304": "ಭ್ರಮರನು ಚತುರ್ದಳಪದ್ಮದ ಮೇಲೆ ಆಡಿತ್ತು ನೋಡಾ.", 
        "19305": "ಕುರುಹು ಕೆಟ್ಟು ಬೀಜದಲ್ಲಿ ಮೂರು ನಿರಾಳವೃಕ್ಷ ಹುಟ್ಟಿತ್ತು.", 
        "19306": "ಕುಂಡಲೀಶಕ್ತಿಯ ಬಾಯಲ್ಲಿ ಮೂರು ಮಾತ್ರೆ ಹುಟ್ಟಿತ್ತು ನೋಡಾ.", 
        "19307": "ನಿರಾಮಯದೊಳು ನಿರಾಳಮಯವಾಗಿ ಹುಟ್ಟಿತ್ತು ನೋಡಾ", 
        "19308": "ನಿರಾಮಯದೊಳು ಹುಟ್ಟಿತ್ತು ನೋಡಾ ಒಂದು ಪದ್ಮ.", 
        "19309": "ನಿರಾಳ ಅಷ್ಟದಳಕಮಲದೊಳು", 
        "19310": "ಊಧ್ರ್ವಮುಖ ಅಧೋಮುಖ ಸಮಾದಿಷ್ಟಿಯೆಂದು", 
        "19311": "ನಿರಾಮಯವೆಂಬ ಬಾವಿಗೆ", 
        "19312": "ರೂಪಿಲ್ಲದೆ ಇಹುದು ನೋಡಾ ಜೀವಾತ್ಮನು.", 
        "19313": "ದೇಹ ಪ್ರಾಣ ಇಂದ್ರಿಯ ಕರಣಂಗಳ ಕೂಡಿ", 
        "19314": "ಕಣ್ಣಿಲ್ಲದಂಧಕ ಕಾಲಿಲ್ಲದ ಪಶುವ ಮೇಸುವ ನೋಡಾ.", 
        "19315": "ಕೋಣನ ಬಸುರಲ್ಲಿ ಒಂದು ಕಪಿ ಹುಟ್ಟಿ ಕುಣಿವುದ ಕಂಡೆನು.", 
        "19316": "ಆಣವ ಮಾಯಾ ಕಾರ್ಮಿಕವೆಂಬ ಮೂರು ಕಲ್ಲನಿರಿಸಿ,", 
        "19317": "ನಾದವೆಂಬ ಕೆರೆಯೊಳಗೆ ಬಿಂದುವೆಂಬ ಅಮೃತವ ತುಂಬಿ,", 
        "19318": "ಕಾಲಿಲ್ಲದ ಗುರುವಿಂಗೆ ತಲೆಯಿಲ್ಲದ ಶಿಷ್ಯನು.", 
        "19319": "ಆವುದೊಂದು ರೂಪನು ಕಂಗಳು ಕಾಣವು.", 
        "19320": "ಶಿವನು ಐದಕ್ಷರವೆಂಬ ಅಣ್ಣಗಳು ನೀವು ಕೇಳಿರೆ,", 
        "19321": "ಶಿವನು ಐದಕ್ಷರವು ಆಗಬಲ್ಲ, ಐದು ವರ್ಣವು ಆಗಬಲ್ಲ,", 
        "19322": "ತ್ರಿಪುರಂಗಳ ಕೆಡೆಮೆಟ್ಟಿ, ತೂರ್ಯ ತೂರ್ಯಾತೀತವ ದಾಂಟಿ,", 
        "19323": "ಮಹಾವಾಯುವ ಹಿಡಿದು ಮೂಲಜ್ವಾಲೆಯನೆಬ್ಬಿಸಿ,", 
        "19324": "ಎಡಬಲನ ತಡೆದು, ಮೇರುಗಿರಿಶಿಖರ ಪಶ್ಚಿಮದ್ವಾರದಲ್ಲಿ ನಿಲಿಸಿದಡೆ,", 
        "19325": "ಜಂಬುಕ ಹದಿನಾಲ್ಕು  ವಿಷಯವನುಂಡು ಸತ್ತವು ನೋಡಾ,", 
        "19326": "ಪದ್ಮವೊಂದು ಮೊಗ್ಗೆ ಮೂರುಂಟು ನೋಡಾ :", 
        "19327": "ಏಳುಸುತ್ತಿನ ಕೋಟೆಗೆ ಒಂಬತ್ತು ಬಾಗಿಲು,", 
        "19328": "ಒಂದಾದೆನೆಂಬ ಅಣ್ಣಗಳು ನೀವು ಕೇಳಿರೆ,", 
        "19329": "ಒಂದೆಂಬೆನೆ ಎರಡಾಗಿ ತೋರುತ್ತಿದೆ,", 
        "19330": "ಬೀಜವಿಲ್ಲದೆ ಅಂಕುರವಿಲ್ಲ, ಬೀಜವಿಲ್ಲದೆ ಅಂಕುರವ ಕಾಣಬಾರದು.", 
        "19331": "ಅದೆ ಇದೆಂಬ ಅಣ್ಣಗಳು ನೀವು ಕೇಳಿರೆ,", 
        "19332": "ಉರಿಯ ಬೀಜದ ಬಾಯಲ್ಲಿ ಎರಡು ಪಕ್ಷಿ ಹುಟ್ಟಿತ್ತು ನೋಡಾ,", 
        "19333": "ಪರಬ್ರಹ್ಮಸ್ವರೂಪವಾಗಿಹ ಪ್ರಣವದ ಬಾವಿಯೊಳಗೆ", 
        "19334": "ಅನಂತಕೋಟಿ ಸೂರ್ಯ ಚಂದ್ರಾಗ್ನಿಪ್ರಕಾಶವಾಗಿಹ", 
        "19335": "ಸಮತೆ ಸಮಾಧಾನವೆಂಬ ಭೂಮಿಯ ಮೇಲೆ", 
        "19336": "ಸೊಂಬರಿಹರು ಶುದ್ಧಬಯಲಲ್ಲಿ ನೋಡಾ,", 
        "19337": "ಸೊಂಬರಿಹರು ನಿರಾಳಮಯದಲ್ಲಿ", 
        "19338": "ಏನು ಏನೂ ಎನಲಿಲ್ಲದ ಹಾಳು ಬೆಟ್ಟದ ಮೇಲೊಂದು", 
        "19339": "ಎಂಟೆರಡೆಂಟೆರಡೆಂಬರು,", 
        "19340": "ಬೀಜವ ವೃಕ್ಷ ನುಂಗಿ ತೋರಿದ ಘನವನೇನೆಂಬೆ ನೋಡಾ !", 
        "19341": "ನಾದವ ಬಿಂದು ನುಂಗಿ, ಬಿಂದುವ ನಾದ ನುಂಗಿ", 
        "19342": "ಸರ್ಪನ ಬಾಯಲ್ಲಿ ಚಂದ್ರಸೂರ್ಯರುತ್ಪತ್ಯವಾಗಿ", 
        "19343": "ಹುಸಿವರ್ಣನಾಗಿ ಪಂಚಭೂತವಲ್ಲ,", 
        "19344": "ಸರ್ಪನ ಹೆಸರ ಹೇಳಿದಡೆ ವಿಷ ಹತ್ತಿತು ನೋಡಾ,", 
        "19345": "ಅನಾದಿ ಗಣೇಶ್ವರನ ನೆನಹುಮಾತ್ರದಲ್ಲಿ", 
        "19346": "ಕಣ್ಣಿಲ್ಲದೆ ನೋಡಿ ಕಾಮಿಸುವ ಶರಣ.", 
        "19347": "ಶರಣನ ಸ್ವಾನುಭಾವವೆ ಕಣ್ಣಿಲ್ಲದ ನೋಟ,", 
        "19348": "ಶರಣನು ಸ್ವಾನುಭಾವದಲ್ಲಿ ಕಂಡನು ನಿರಾಮಯಾತೀತವ,", 
        "19349": "ಶರಣ ಸತ್ತು, ಸುತ್ತಿದ್ದ ಪ್ರಪಂಚ ಕೆಟ್ಟವು ನೋಡಾ.", 
        "19350": "ಮೂರುಲೋಕವ ನುಂಗಿತ್ತು ನೋಡಾ ಒಂದು ಕಪ್ಪೆ,", 
        "19351": "ಅಯ್ಯಾ, ಎನ್ನ ಮನವ ಮಹಾಮಾಯೆ ಮುಚ್ಚಿಕೊಂಡ ಕಾರಣ", 
        "19352": "ಗಣೇಶ್ವರಿಯೆಂಬ ಮಹಾಶಕ್ತಿಗೆ ಆರುಮುಖವುಂಟು ನೋಡಾ.", 
        "19353": "ಮೇರುಗಿರಿಶಿಖರ ಪಶ್ಚಿಮದ್ವಾರದಲ್ಲಿ ಎರಡು ಗೂಬೆ ಹುಟ್ಟಿತ್ತು.", 
        "19354": "ಮೇರುಗಿರಿಶಿಖರ ಪಶ್ಚಿಮದ್ವಾರದಮಧ್ಯದಲ್ಲಿ", 
        "19355": "ನಾದ ಬಿಂದು ಕಲಾತೀತವಾಗಿಹ ಜ್ಯೋತಿರ್ಮಯವಾಗಿಹ ಲಿಂಗವ", 
        "19356": "ಉತ್ತರ ದಕ್ಷಿಣ ಪೂರ್ವ ಪಶ್ಚಿಮವೆಂಬ ನಾಲ್ಕು ದೇಶವ ತಿರುಗಿದಡೆ,", 
        "19357": "ಉತ್ತರ ದಕ್ಷಿಣ ಪೂರ್ವ ಪಶ್ಚಿಮವೆಂಬ", 
        "19358": "ಚಿತ್ಸ್ವರೂಪವಾಗಿ ತನ್ನೊಳಗೆ ತೀರ್ಥ ಚಿತ್ಪ್ರಕಾಶವಾಗಿಹುದು ನೋಡಾ.", 
        "19359": "ಆ ತೀರ್ಥ ಸೂರ್ಯಪ್ರಭೆಗೂ ಬತ್ತಲೀಯದು,", 
        "19360": "ತಾನೊಂದು ಕಾಲದಲ್ಲಿ ನಿರಾಮಯವಾಗಿರ್ದನು ನೋಡಾ.", 
        "19361": "ತಾನೊಂದು ಕಾಲದಲ್ಲಿ ನಾದ ಬಿಂದು ಕಲೆಯಾದನು.", 
        "19362": "ತಾನೊಂದು ಕಾಲದಲ್ಲಿ ಬಿಂದುವಿನೊಳಗೆ ಬಿಂದುವಾದನು.", 
        "19363": "ತಾನೊಂದು ಕಾಲದಲ್ಲಿ ಕಲೆಯೊಳಗೆ ಕಲೆಯಾದನು.", 
        "19364": "ಅಯ್ಯಾ, ಆತ್ಮಯೋಗಿಗಳು ದೇಹವಾಸನೆ ಕೆಡದೆ"
    }
}