{
    "details": {
        "ಅಂಕಿತ": "ಹುಲಿಗೆರೆಯ ವರದ ಸೋಮನಾಥ", 
        "ಒಡಹುಟ್ಟಿದವರು": "--", 
        "ಕಾಯಕ": "ಪವಿತ್ರೋದಕವನ್ನು ತರುವ ಕಾಯಕ", 
        "ಕಾಲ": "1160", 
        "ಕಾಲವಾದ ಸ್ಥಳ": "--", 
        "ಕೃತಿಯ ವೈಶಿಷ್ಟ್ಯ": "ಈ ವಚನಕಾರ ನೇಮವನ್ನು ಹಿಡಿದವನಿಗೆ ಛಲ ಬೇಕೆನ್ನುವನು. ಇಷ್ಟಲಿಂಗ ಕಳೆದು ಹೋದಾಗ ಜೀವ ಬಿಡಬೇಕೆನ್ನುವ ನಿಷ್ಠೆ, ಮರಳಿ ಗುರುವಿನಿಂದ ಲಿಂಗ ದೀಕ್ಷೆ ಪಡೆಯಬಾರದೆನ್ನುವ ಸಂಪ್ರದಾಯಿಕ ಶ್ರದ್ಧೆಯುಳ್ಳವನು. ಏಕದೇವೋಪಾಸನೆಯನ್ನು ಪ್ರತಿಪಾದಿಸಿರುವನು.", 
        "ಗ್ರಾಮ": "--", 
        "ಜನ್ಮ ಸ್ಥಳ": "ಪುಲಿಗೆರೆ", 
        "ಜಿಲ್ಲೆ": "ಬೆಳಗಾವಿ", 
        "ತಂದೆ ಹೆಸರು": "--", 
        "ತಾಯಿ ಹೆಸರು": "--", 
        "ತಾಲ್ಲೂಕು": "--", 
        "ಪತಿ: ಪತ್ನಿಯ ಹೆಸರು": "--", 
        "ಮಕ್ಕಳು: ಅವರ ಹೆಸರು": "--", 
        "ಲಭ್ಯ ವಚನಗಳ ಸಂಖ್ಯೆ": "4", 
        "ವಚನಕಾರರ ಹೆಸರು": "ಅಗ್ಘವಣಿ ಹೊನ್ನಯ್ಯ", 
        "ವಚನಗಳಲ್ಲದೆ ಇತರ ಲಭ್ಯ ಕೃತಿಗಳು": "--", 
        "ಸಮಾಧಿ ಇರುವ ಸ್ಥಳ": "--"
    }, 
    "id": "23", 
    "name": "ಅಗ್ಘವಣಿ ಹೊನ್ನಯ್ಯ", 
    "vachana": {
        "8252": "ಆದಂತೆ ಆಗಲಿ, ಮಾದಂತೆ ಮಾಣಲಿ ಎನಲಾಗದು,", 
        "8253": "ಚರ ಚರ ವಿರಕ್ತರಾಗಿ,", 
        "8254": "ವಿಶ್ವವೆಲ್ಲ ಪಶುವು, ಶಿವನೊಬ್ಬನೆ ಪತಿ, ಬೇರೊಬ್ಬ ಪತಿಯಿಲ್ಲ.", 
        "8255": "ಹೊರಗೆಂಟು ತನು, ಒಳಗೆ ನಿರಂಜನ ಜ್ಯೋತಿ,"
    }
}