{
    "details": {
        "ಅಂಕಿತ": "ಅಂಬಿಗರ ಚೌಡಯ್ಯ", 
        "ಒಡಹುಟ್ಟಿದವರು": "--", 
        "ಕಾಯಕ": "ದೋಣಿ ನಡೆಸುವುದು", 
        "ಕಾಲ": "1160", 
        "ಕಾಲವಾದ ಸ್ಥಳ": "--", 
        "ಕೃತಿಯ ವೈಶಿಷ್ಟ್ಯ": "ತನ್ನ ಹೆಸರನ್ನೇ ವಚನಕ್ಕೆ ಅಂಕಿತವಾಗಿ ಬಳಸಿರುವನು. ನಿರ್ಭೀತ, ನಿಷ್ಠುರ, ನಿರ್ದಾಕ್ಷಿಣ್ಯ ಕಟೂಕ್ತಿ - ಇವನ ಮನೋಭಾವ. ಶ್ರೇಷ್ಠ ಅನುಭಾವಿ. ತನ್ನ ವೃತ್ತಿಯನ್ನೇ ಸಾಂಕೇತಿಕವಾಗಿ ಅನುಭಾವದ ಮೂಲಕ ವ್ಯಂಜಿಸಿರುವನು. ಅನ್ಯಾಯ, ಜಾತೀಯತೆ, ಅಧಾರ್ಮಿಕ ಆಚರಣೆಗಳನ್ನು ಕಟುವಾಗಿ ಟೀಕಿಸಿರುವನು.", 
        "ಗ್ರಾಮ": "--", 
        "ಜನ್ಮ ಸ್ಥಳ": "ಶಿವಪುರ (ಧಾರವಾಡ ಜಿಲ್ಲೆ) (ಚೌಡದಾನಪುರ)", 
        "ಜಿಲ್ಲೆ": "ಧಾರವಾಡ", 
        "ತಂದೆ ಹೆಸರು": "--", 
        "ತಾಯಿ ಹೆಸರು": "--", 
        "ತಾಲ್ಲೂಕು": "--", 
        "ಪತಿ: ಪತ್ನಿಯ ಹೆಸರು": "--", 
        "ಮಕ್ಕಳು: ಅವರ ಹೆಸರು": "--", 
        "ಲಭ್ಯ ವಚನಗಳ ಸಂಖ್ಯೆ": "279", 
        "ವಚನಕಾರರ ಹೆಸರು": "ಅಂಬಿಗರ ಚೌಡಯ್ಯ", 
        "ವಚನಗಳಲ್ಲದೆ ಇತರ ಲಭ್ಯ ಕೃತಿಗಳು": "--", 
        "ಸಮಾಧಿ ಇರುವ ಸ್ಥಳ": "--"
    }, 
    "id": "21", 
    "name": "ಅಂಬಿಗರ ಚೌಡಯ್ಯ", 
    "vachana": {
        "20706": "ಈಶಲಾಂಛನವ ತೊಟ್ಟು ಮನ್ಮಥವೇಷಲಾಂಛನವ ತೊಡಲೇತಕ್ಕೆ ?", 
        "20707": "ಈಶ್ವರನ ಕಾಬುದೊಂದಾಸೆಯುಳ್ಳೊಡೆ ಪರದೇಶಕ್ಕೆ ಹೋಗಿ ಬಳಲದಿರು,", 
        "20708": "ಕಳ್ಳ, ಹಾದರಿಗ, ಸೂಳೆಗಾರ, ತಳವಾರನಲ್ಲಿ ಮಿಥ್ಯವಿಲ್ಲದಿರಬೇಕು.", 
        "20709": "ಕಾಮವ ಕಳೆದು, ಕ್ರೋಧವ ದಾಂಟಿ,", 
        "20710": "ಕಾಯ ಜೀವವೆಂಬ ಹೆಚ್ಚು ಕುಂದನರಿಯದೆ", 
        "20711": "ಕಾಯದ ಶೃಂಗಾರ ಕಾಮಿನಿಯರ ಕೂಟಕ್ಕೊಳಗು,", 
        "20712": "ಕಾಯದಿಂದ ಕಂಡೆಹೆನೆಂದಡೆ ಬ್ರಹ್ಮನ ಹಂಗು,", 
        "20713": "ಕಾಲ ವೇಳೆಯನರಿತು ಕೂಗಿದ ಕೋಳಿಯ ಕಂಡು", 
        "20714": "ಕಾಶಿಯಾತ್ರೆಗೆ ಹೋದೆನೆಂಬ", 
        "20715": "ಕಾಷ್ಠದಲ್ಲಿ ನಿಂದಗ್ನಿಮಥನ", 
        "20716": "ಕಾಸಿನ ಕಲ್ಲ ಕೈಯಲ್ಲಿ ಕೊಟ್ಟು ಹೇಸದೆ ಕೊಂದ", 
        "20717": "ಕಾಳೆಗದಲ್ಲಿ ಹೋಗದಿರಯ್ಯ,", 
        "20718": "ಕುಡಿವ ನೀರೆನ್ನಬಹುದೆ, ಹುಡುಕುನೀರಲದ್ದುವಾಗ ?", 
        "20719": "ಕುರಿಕೋಳಿ ಕಿರುಮೀನ ತಿಂಬವರ", 
        "20720": "ಕುರುಹೆಂಬೆನೆ ಕಲ್ಲಿನಲ್ಲಿ ಹತ್ತಿದ ಹಾವಸೆ,", 
        "20721": "ಕುಲವಾದ ಛಲವಾದ ವಾಗ್ವಾದಂಗಳಲ್ಲಿ ಹೋರುವನ್ನಬರ ಅರುಹಿರಿಯಪ್ಪರೆ ?", 
        "20722": "ಕುಲ ಹಲವಾದಡೇನು ? ಉತ್ಪತ್ಯ ಸ್ಥಿತಿ ಲಯ ಒಂದೆ ಭೇದ.", 
        "20723": "ಕುಲಹೀನ ಶಿಷ್ಯಂಗೆ ಅನುಗ್ರಹವ ಮಾಡಿ,", 
        "20724": "ಕೂಡಿದ ಧನವೆಲ್ಲವನು ಗುರುಲಿಂಗಜಂಗಮಕ್ಕೆ", 
        "20725": "ಕೂರ್ಮನ ಭಾವ ನಿಂದಲ್ಲಿ, ಮೋಹವಾಗಿಪ್ಪುದು.", 
        "20726": "ಕೇಳಿದೇನೆಲೆ ಮಾನವ,", 
        "20727": "ಕೇಳಿರಯ್ಯಾ ಮಾನವರೆ,", 
        "20728": "ಕೇಳು ನೀನೆಲೊ ಮಾನವಾ,", 
        "20729": "ಕೈ ಮುಟ್ಟುವಲ್ಲಿ, ಕಿವಿ ಕೇಳುವಲ್ಲಿ, ಬಾಯಿ ಕೊಂಬಲ್ಲಿ,", 
        "20730": "ಕ್ರೀ ಜ್ಞಾನವೆಂಬ ಉಭಯವ ತಾವರಿಯದೆ,", 
        "20731": "ಕ್ರೀಯನರಿದವಂಗೆ ಗುರುವಿಲ್ಲ, ಆಚಾರವನರಿದವಂಗೆ ಲಿಂಗವಿಲ್ಲ,", 
        "20732": "ಕ್ಷೀರದಿಂದಾದ ತುಪ್ಪ ಕ್ಷೀರವಪ್ಪುದೇ ?", 
        "20733": "ಗಂಡನೆಂಜಲಿಗೆ ಹೇಸುವಳು ಮಿಂಡನ ತಂಬುಲವ ತಿಂಬುವ ತೆರನಂತೆ,", 
        "20734": "ಗಂಧವ ವಾಯು ಕೊಂಬಾಗ ಅದ ತಂದು ಕೂಡಿದವರಾರು ?", 
        "20735": "ಗಾಳಿಯ ಹಡೆದಲ್ಲಿ ತೂರಿಕೊಳ್ಳಯ್ಯಾ,", 
        "20736": "ಗಿಡುವಿನ ಪುಷ್ಪವ ಕೊಯ್ಯೆನು,", 
        "20737": "ಗಿಣಿಯಿಲ್ಲದ ಪಂಜರ ಹಲವು ಮಾತನಾಡಬಲ್ಲುದೆ ?", 
        "20738": "ಗುರುಲಿಂಗಜಂಗಮಕ್ಕೆ ಆಧಾರ ಬಸವಣ್ಣ,", 
        "20739": "ಗುರು-ಲಿಂಗ-ಜಂಗಮವೆಂದರಿಯದ ಗೊಡ್ಡುಗಳ", 
        "20740": "ಗುರುವಿನೊಳಡಗಿದ ಭಕ್ತ ಪರವ ಕಂಡುದಿಲ್ಲ,", 
        "20741": "ಗುರುವೆಂಬ ಭಾವ ಬ್ರಹ್ಮಮೂರ್ತಿ, ಲಿಂಗವೆಂಬ ಭಾವ ವಿಷ್ಣುಮೂರ್ತಿ,", 
        "20742": "ಗುರುವೆಂಬೆನೆ ಹಲಬರ ಮಗ,", 
        "20743": "ಘಟದ ಮಧ್ಯದಲ್ಲಿ ನಿಂದವನ, ಆತ್ಮನ ಚಿತ್ತದಲ್ಲಿ ಅರಿದವನ,", 
        "20744": "ಚಿತ್ರವ ಬರೆವ ಲೆಕ್ಕಣಿಕೆಯ ಕಟ್ಟಿಗೆಯಂತೆ", 
        "20745": "ಜಂಗಮದ ಪಾದತೀರ್ಥ ಎನ್ನಂಗದೋಷವ ಕಳೆಯಿತ್ತಯ್ಯ,", 
        "20746": "ಜಂಗಮವ ಕರತಂದು ಮನೆಯಲ್ಲಿ ಕುಳ್ಳಿರಿಸಿ,", 
        "20747": "ಜಂಗಮವೆಂದಡೆ ನಡೆನುಡಿ ಸಿದ್ಧಿಯಾಗಿರಬೇಕು.", 
        "20749": "ಅರಿವಿನ ಪಥವನರಿಯದಿರ್ದಡೆ,", 
        "8012": "ಅಂಗದ ಗುಣವನರತು ಲಿಂಗವನರಿಯಬೇಕೆಂಬರು", 
        "8013": "ಅಂಗದೊಳಗಿಪ್ಪುದು ಲಿಂಗವಲ್ಲ, ಅಂಗದ ಹೊರಗಿಪ್ಪುದು ಲಿಂಗವಲ್ಲ.", 
        "8014": "ಅಂಗವ ಅಂದ ಮಾಡಿಕೊಂಡು ತಿರುಗುವ", 
        "8015": "ಅಂತರಂಗವ ಬಿಟ್ಟು ಮಂಡೆ ಬೋಳಾದ ಮೇಲೆ", 
        "8016": "ಅಂದ ಛಂದವ ಬಿಟ್ಟು, ಮಂಡೆ ಬೋಳಾದ ಮತ್ತೆ", 
        "8017": "ಅಂದಾದಿಬಿಂದುವಿನೊಳೊಂದಿದ ಹುಟ್ಟು,", 
        "8018": "ಅಂಬಿಗ ಅಂಬಿಗ ಎಂದು ಕುಂದ ನುಡಿಯದಿರು,", 
        "8019": "ಅಂಬಿಗನು ಜಗದೊಳಗೆ ಇಂಬಿಲೋಲಾಡುವನು;", 
        "8020": "ಅಂಬಿನ ಹಿಳಿಕಿನಲ್ಲಿ ಕಟ್ಟಿದ ವಿಹಂಗನ ಗರಿಯಂತೆ,", 
        "8021": "ಅಖಂಡಪರಿಪೂರ್ಣ ನುಡಿಗೆಡೆಯಿಲ್ಲದ, ಎಡೆಗೆ ಕಡೆಯಿಲ್ಲದ,", 
        "8022": "ಅಗ್ನಿ ದಿಟವೆಂದಡೆ ತಾ ಹುಸಿ, ಕಾಷ್ಠವಿಲ್ಲದೆ.", 
        "8023": "ಅಜಾತನನೊಲಿಸದೊಡೆ ಅದೇತರ ಮಂತ್ರ, ಅದೇತರ ಆಗಮ ಹೇಳಿರೋ,", 
        "8024": "ಅಡವಿಯ ತೊಪ್ಪಲ ತರತರ ತಂದು ತಿಂದು", 
        "8025": "ಅಡವಿಯ ಹೊಗಿಸಿತ್ತು, ಹುಡುಕುನೀರಲದ್ದಿತ್ತು,", 
        "8026": "ಅಡವಿಯೊಳಗರಸುವಡೆ ಸಿಡಿಗಂಟಿ ತಾನಲ್ಲ.", 
        "8027": "ಅಡ್ಡಬಿದ್ದು ಶಿಷ್ಯನ ಮಾಡಿಕೊಂಬ ದಡ್ಡ ಪ್ರಾಣಿಗಳನೇನೆಂಬೆನಯ್ಯ.", 
        "8028": "ಅತ್ಯಾಹಾರವನುಂಡು ಹೊತ್ತುಗಳೆದು", 
        "8029": "ಅದ್ವೈತವ ನುಡಿದು", 
        "8030": "ಅನಾದಿಪರಶಿವನಿಂದ ಸಾಕಾರಲೀಲೆಯ ಧರಿಸಿ, ಮರ್ತ್ಯಕ್ಕವತರಿಸಿ,", 
        "8031": "ಅಯ್ಯ! ಅಂಗಾಚಾರವುಳ್ಳ ಶಕ್ತಿ-ಭಕ್ತ-ಜಂಗಮದ ಗೃಹದಲ್ಲಿ", 
        "8032": "ಅಯ್ಯ! ಅಚ್ಚಪ್ರಸಾದಿ, ನಿಚ್ಚಪ್ರಸಾದಿ,", 
        "8033": "ಅಯ್ಯಾ ಆಚಾರವುಳ್ಳಕಾಂಚೀಪಟ್ಟಣದಲ್ಲಿ", 
        "8034": "ಅಯ್ಯಾ, ನಾವು ಪರಮವಿರಕ್ತರು,", 
        "8035": "ಅಯ್ಯ! ಪಾಷಾಣಕ್ಕೆ ಗಿರಿ ಸವೆದವು.", 
        "8036": "ಅಯ್ಯ! ಶ್ರೀಗುರುಲಿಂಗಜಂಗಮದ ವೇಧಾಮಂತ್ರಕ್ರಿಯಾದೀಕ್ಷೆಗೆ ಹೊರಗಾದ", 
        "8037": "ಅರಳೆಯ ಮರನು ವಿಷ್ಣುಕಾಂತಿ ಬನ್ನಿ ಮುತ್ತಕ ತೊಳಚಿ", 
        "8038": "ಅರಿದೆಹೆನೆಂಬನ್ನಬರ ಅಸಗೆ ನೀರಡಿಸಿ ಸತ್ತಂತಾಯಿತ್ತು.", 
        "8039": "ಅರಿಯದ ಗುರು ಅರಿಯದ ಶಿಷ್ಯಂಗೆ", 
        "8040": "ಅರಿವನರಿದಲ್ಲಿ ತಾನೆನ್ನದೆ ಇದಿರೆನ್ನದೆ,", 
        "8041": "ಅರಿವುದೊಂದು ವಾಯು, ಮರೆವುದೊಂದು ವಾಯು.", 
        "8042": "ಅರುಹಿಯರ ದೈವ ಅಗಲ [ತೈಲವಿ]ಲ್ಲಾ ಎಂದಡೆ", 
        "8043": "ಅರ್ಚನೆಯ ಮಾಡುವಲ್ಲಿ ಆವೇಶ ಅರತಿರಬೇಕು.", 
        "8044": "ಅಲ್ಲಲ್ಲಿಗೆ ತಕ್ಕ ಹಾಗೆ ಎಲ್ಲರಿಗೂ ಬೋಧಿಸಲಾಗದು.", 
        "8045": "ಅಷ್ಟಮದಂಗಳ ಘಟ್ಟಿಯನೆ ಕರಗಿಸಿ,", 
        "8046": "ಅಸುರರ ಮಾಲೆಗಳಿಲ್ಲ, ತ್ರಿಶೂಲ ಡಮರುಗವಿಲ್ಲ,", 
        "8047": "ಅಳುಪೆಂಬ ನಾಯ ಕಳವಳದರ್ಥವ", 
        "8048": "ಆತ್ಮಂಗೆ ದಶವಾಯು ಉಂಟೆಂಬರು.", 
        "8049": "ಆದಿ ಅನಾದಿಯಿಂದತ್ತಣ", 
        "8050": "ಆದಿಶಕ್ತಿವಿಡಿದಾಡುವರೆಲ್ಲರು ಜಂಗಮವಲ್ಲ,", 
        "8051": "ಆನೆಂಬುದೇನುರಿ ಇದಿರಿಟ್ಟು ತೋರೂದಿದೇನು ?", 
        "8052": "ಆಯತಲಿಂಗದಲ್ಲಿ ಅನುಭಾವ ಸಾಹಿತ್ಯವಾಗದು,", 
        "8053": "ಆರಿಕೆ ಬಿತ್ತಿದ ಗಿಡುವಿನ ಹೂವ ಕೊಯಿದು,", 
        "8054": "ಆರು ಲಿಂಗ ಮೂರು ಲಿಂಗವೆಂಬರು,", 
        "8055": "ಆರೂ ಇಲ್ಲದಂದು ತಾನಹ ದೆವಸ,", 
        "8056": "ಆರೂಢಜ್ಞಾನಿಯಾದವಂಗೆ ಅನುಭಾವವೇಕಯ್ಯಾ ?", 
        "8057": "ಆವ ಪದಾರ್ಥವ ಮೋಹಿಸಿ ಲವಲವಿಸಬೇಡ.", 
        "8058": "ಆವಾವ ತ್ರಿಗುಣಭೇದದಲ್ಲಿವಿಶ್ವಾಸವ ಮಾಡಿದಡೂ ಭಾವಶುದ್ಧವಾಗಿರಬೇಕು.", 
        "8059": "ಆಶೆಯಲಿದ್ದವನ ತಲೆಯನರಿದು,", 
        "8060": "ಆಶೆಯುಳ್ಳಾತನೊಬ್ಬರಾಧೀನದಲ್ಲಿಪ್ಪನು.", 
        "8061": "ಆಳಾಪದ ಸೊಬಗು, ಘಂಟೆ ವಾದ್ಯದ ಕೂಗಿನ ಕೊರಚು,", 
        "8062": "ಈರೇಳು ಭುವನವನೊಳಕೊಂಡ ಮಹಾಘನಲಿಂಗವು", 
        "8063": "ಉಂಡರೆ ಭೂತನೆಂಬರು,", 
        "8064": "ಉಡುವಿನ ಕಣ್ಣು, ಪಡಿಯ ಅಡಿ, ಕೀಟಕನ ಮುಟ್ಟು,", 
        "8065": "ಉಪ್ಪಿಲ್ಲದ ಮೇಲೋಗರ ತುಪ್ಪದಲ್ಲಿ ಬೆಂದಡೆ,", 
        "8066": "ಊರ ಸುತ್ತಿ ಬಂದ[ಡೇ]ನಯ್ಯ, ಸೇರಬೇಕು ಹೆಬ್ಬಾಗಿಲಲ್ಲಿ.", 
        "8067": "ಊರೆಲ್ಲಾ ಏರಿದ ಹರಗುಲವ,", 
        "8068": "ಎತ್ತ ಸುತ್ತಿ ಬಂದಡೂ ಊರಿಗೆ ಬಪ್ಪುದು ತಪ್ಪದು.", 
        "8069": "ಎರಡು ಗ್ರಾಮದ ನಡುವೆ ಕಡದ ಸೀಮೆಯ ಕಲ್ಲು.", 
        "8070": "ಎಲ್ಲರೊಳಗೆ ಗೆಲ್ಲ ಸೋಲಕ್ಕೆ ಹೋರಬಂದೆನೆ ?", 
        "8071": "ಎಲ್ಲವ ಕಳಿದುಳಿದ ಹೂವ ತಂದು,", 
        "8072": "ಎಲ್ಲಾ ದೇವರಿಗೆ ಮಸ್ತಕದ ಪೂಜೆ,", 
        "8073": "ಎಲುವೆಂಬ ಹಂಜರ ಥಟ್ಟಾಗಿ,", 
        "8074": "ಎಲೋ ಮಾನವ ಕೇಳೆಲೊ,", 
        "8075": "ಎಸವಿನ ಗುರು ಹೋಗಿ ಶಿಶುವಧೆಯ ಮಾಡಿದ.", 
        "8076": "ಏಕಾದಶ ರುದ್ರರು ಹೊರಗಾದ,", 
        "8077": "ಐಶ್ವರ್ಯ ದುಃಖದಲ್ಲಿ ಬೇಯುವ", 
        "8078": "ಒಂದನರಿದು ಒಂದ ಮರೆದೆಹೆನೆಂಬ ಸಂದೇಹದವನಲ್ಲ.", 
        "8079": "ಒಂದ ಬಿಟ್ಟು ಒಂದನರಿದೆಹೆನೆಂಬನ್ನಕ್ಕ ಮರದ ಸಂದಿನ ಬೊಂಬೆಯೆ?", 
        "8080": "ಒಡಲಿಂಗಾರು ಬಾಯಿ, ನಡುವೆ ಮೂರು ದೇಹ,", 
        "8081": "ಒಬ್ಬ ತಂದೆಯ ಬಸಿರಿನಲ್ಲಿ ಒಂಬತ್ತು ಮಕ್ಕಳು ಹುಟ್ಟಿದಡೇನಯ್ಯ ?", 
        "8082": "ಓಂಕಾರವೆಂಬಾಕಾರದಲ್ಲಿ ನಾಲ್ಕು ವೇದ,", 
        "8083": "ಓದಿ ಬೋಧಿಸಿ ಇದಿರಿಗೆ ಹೇಳುವನ್ನಬರ ಚದುರತೆಯಲ್ಲವೆ ?", 
        "8084": "ಓದಿಹೆನೆಂಬ ಒಡಲು, ಕಂಡೆಹೆನೆಂಬ ಭ್ರಾಂತು,", 
        "8085": "ಕಂಗಳ ನಾಮ ಹರುಗುಲವಾಗಿ, ನೋಡುವ ದೃಷ್ಟಿ ಅಂಬಿಗನಾಗಿ,", 
        "8086": "ಕಂಡು ಕೊಟ್ಟೆಹೆನೆಂಬುದು ಖಂಡಿತಂಗಲ್ಲದೆ ಪರಿಪೂರ್ಣಂಗುಂಟೆ ?", 
        "8087": "ಕಂಥೆ ತೊಟ್ಟವ ಗುರುವಲ್ಲ,", 
        "8088": "ಕಟ್ಟಿ ಕಳೆ ಪಾಪವ, ಬಿಟ್ಟು ಕಳೆ ಪುಣ್ಯವ.", 
        "8089": "ಕಟ್ಟಿಗೆಯ ಹೊರೆಯ ಹೊತ್ತು", 
        "8090": "ಕಟ್ಟಿದ ಲಿಂಗವ ಕಿರಿದು ಮಾಡಿ,", 
        "8091": "ಕಟ್ಟಿಹೆ ಬಿಟ್ಟಿಹೆನೆಂಬ ದಂದುಗ", 
        "8092": "ಕತ್ತೆಯ ಮೇಲೆ ತಿತ್ತಿಯ ಮಾಡಿ ಕಳ್ಳು ಹೇರುವರು,", 
        "8093": "ಕರದಲ್ಲಿ ಲಿಂಗವ ಪಿಡಿದುಕೊಂಡು,", 
        "8094": "ಕರ್ಮೇಂದ್ರಿಯ ಕಾಯವ ಕೂಡಿಪ್ಪುದು,", 
        "8095": "ಕರ್ಮೇಂದ್ರಿಯವಯಿದು,", 
        "8096": "ಕಲ್ಲದೇವರ ಪೂಜೆಯ ಮಾಡಿ,", 
        "8097": "ಕಲಿತು ಹೇಳಿಹೆನೆಂಬ ಕರ್ಕಶ ಬೇಡ,", 
        "8098": "ಕಲ್ಲಿನಲ್ಲಿ ಕಠಿಣ, ಖುಲ್ಲರಲ್ಲಿ ದುರ್ಗುಣ,", 
        "8099": "ಕಷ್ಟಜೀವನ ಮನುಜರಿರಾ,", 
        "8100": "ಕಷ್ಟನ ಮನೆಯಲ್ಲಿ ಸೃಷ್ಟಿಗೀಶ್ವರನುಂಬಾಗ", 
        "8101": "ಕಳವು ಪಾರದ್ವಾರಕ್ಕೆ ಪರಾಕುಂಟೆರಿ ಅದು ತನ್ನ ಒಡಲಳಿವ ಇರವು.", 
        "8102": "ಜನನ ಸೂತಕ ಮರಣ ಸೂತಕಂಗಳ ಕಳೆದು", 
        "8103": "ಜಾತಿಭ್ರಮೆ, ನೀತಿಭ್ರಮೆ ಎಂಬ ಕರ್ಮಂಗಳನು", 
        "8104": "ಜಾತಿವಿಚಾರ, ನೀತಿವಿಚಾರ,", 
        "8105": "ಜೇಡಂಗೆ ಬೇಡಂಗೆ ಡೋಹಾರಂಗೆ ಹೊಲೆಯಂಗೆ", 
        "8106": "ಜ್ಞಾನಾಜ್ಞಾನವೆಂಬ ಉಭಯವ ನಾನರಿಯದೆ,", 
        "8107": "ಜ್ಞಾನಿಯಾದಲ್ಲಿ ಧ್ಯಾನ ಮೋನಂಗಳಲ್ಲಿರಲೇತಕ್ಕೆ?", 
        "8108": "ಜ್ಯೋತಿ ನಾಲ್ಕರೊಳಗೆ ಆತ್ಮನೈದಾನೆ.", 
        "8109": "ತಟಾಕ ಒಡೆದಡೆ ಕಟ್ಟುವಡೆವುದಲ್ಲದೆ.", 
        "8110": "ತಟ್ಟು ಗೋಣಿಸೊಪ್ಪು ಸಕಲಾತಿ ಅಲ್ಲ[ವು],", 
        "8111": "ತಡಿ ನೆಲೆ ಇಲ್ಲದ ಮಹಾನದಿಯಲ್ಲಿ", 
        "8112": "ತನ್ನ ತನ್ನಿಚ್ಛೆಗೆ ಬಹಲ್ಲಿ ಪಿನಾಕಿ ಬೋಸರಗಿತ್ತಿಯ ಹಾಸೆ?", 
        "8113": "ತನ್ನ ಬುದ್ಧಿ ತನ್ನ ಚಿತ್ತದಲ್ಲಿ ಅಡಗಿದ ಮತ್ತೆ", 
        "8114": "ತನ್ನುವ ಮರೆದು ದೇವರ ಕಂಡೇನೆಂಬ ಕಾರಣ,", 
        "8115": "ತನ್ನುವ ಹುಸಿ ಮಾಡಿ, ಇನ್ನೊಂದು ದಿಟಮಾಡುವ ಅಣ್ಣಂಗೆ", 
        "8116": "ತರು, ನೀರು, ಕಲ್ಲಿನ ಘಟದ ಮಧ್ಯದಲ್ಲಿ ತೋರುವ ಅಗ್ನಿ", 
        "8117": "ತಾನು ಮಾಡುವ ಭಕ್ತಿ ಲಿಂಗದ ಉಪದೇಶವನರಿಯದ ಕಾರಣ", 
        "8118": "ತಿಂಬ ಜಾತಿಗೆ ಮೇವ ಹಾಕಿ", 
        "8119": "ತಿರುಳು ಒಡೆದ ಬಿತ್ತು ಮರಳಿ ಪೈರಪ್ಪುದೆ?", 
        "8120": "ತುತ್ತಿನಾಸೆಗೆ ಲಿಂಗವ ಕೊಟ್ಟುಹೋಹ ವ್ಯರ್ಥ ಮೂಳ", 
        "8121": "ತೋಯವಿಲ್ಲದ ಕುಂಭ, ಜ್ಞಾನವಿಲ್ಲದ ಘಟ, ದೇವರಿಲ್ಲದ ಗುಡಿ", 
        "8122": "ದೃಷ್ಟವ ಕಂಡುದಕ್ಕೆ ಮತ್ತೆ ಮೂದಲೆ ಉಂಟೆ?", 
        "8123": "ದೇಹಾರವ ಮಾಡುವಣ್ಣಗಳಿರಾ, ಒಂದು ತುತ್ತು ಆಹಾರವನಿಕ್ಕಿರೆ.", 
        "8124": "ದೊಡ್ಡ ದೊಡ್ಡ ಶೆಟ್ಟಿಗಳ ಕಂಡು", 
        "8125": "ನಂಬಿಯಣ್ಣ ಮಾಡುವ ಭಕ್ತಿ ನಾಡೆಲ್ಲ ಮಾಡಬಹುದಯ್ಯಾ,", 
        "8126": "ನಮಗೊಬ್ಬರೆಂಜಲು ಸೇರದೆಂದು,", 
        "8127": "ನವನಾಳಪದ್ಮದ ಅಷ್ಟದಳದೊಳಗೆ", 
        "8128": "ನಾದದ ಬಲದಿಂದ ವೇದಂಗಳಾದವಲ್ಲದೆ, ವೇದ ಸ್ವಯಂಭುವಲ್ಲ.", 
        "8129": "ನಾದ ಬಿಂದುವಿನಲ್ಲಿ ಸಾಧಿಸಿದ ಹದಿನಾರು[ದಳ] ಕಳೆಯ ಸುಳಿಯೊಳಗೆ", 
        "8130": "ನಾಯಿ ಬಲ್ಲುದೆ ದೇವರ ಬೋನವ?", 
        "8131": "ನಾರಿವಾಳವ ತಂದು ನಾಯಮುಂದೆ ಹಾಕಿದಡೆ,", 
        "8132": "ನಾಲ್ಕು ವೇದವನೋದಿದನಂತರ ಮನೆಯ ಬೋನವ", 
        "8133": "ನಾಲ್ಕೈದು ಹದಿನೆಂಟು ಪುರಾಣ", 
        "8134": "ನಿಜಗಂಡನ ಸಂಗವನೊಲ್ಲದೆ ಬೊಜಗರ ಸಂಗ ಮಾಡುವ", 
        "8135": "ನಿಲ್ಲಿಸಬಹುದಯ್ಯ ಒಂದೇ ಮಂತ್ರದಲ್ಲಿ ಕಾಳೋರಗನ,", 
        "8136": "ನೀರೊಳಗಣ ನೆಯಿದಲು ತಾವರೆಯಂತೆ,", 
        "8138": "ನೀರೊಳಗಿಕ್ಕಿದ ಕೋಲಿನಂತೆ ಭೇದವನೊಳಗೊಂಡ ವಾದ್ಯದಂತೆ,", 
        "8139": "ನುಡಿವ ಶಬ್ದವೆ ಕಾಯದ ಕಳವಳ,", 
        "8140": "ನೆನೆವೆನೆರಿ ಮರೆದವನಲ್ಲ.", 
        "8141": "ನೇಮಸ್ಥನೆಂಬವ ಕ್ರೂರಕರ್ಮಿ, ಶೀಲವಂತನೆಂಬವ ಸಂದೇಹಧಾರಿ.", 
        "8142": "ನೇಮಸ್ಥನೇನು ಬಲ್ಲನಯ್ಯ ಲಿಂಗದ ಕುರುಹ ?", 
        "8143": "ಪನ್ನಗಂಗೆ ನನ್ನಿಯ ಗಾರುಡವಲ್ಲದೆ ಮಿಕ್ಕಾದ ದ್ವಯಜಿ[ಹ್ವಿ]ಗಳಿಗುಂಟೆ ?", 
        "8144": "ಪರಧನ-ಪರಸತಿ-ಪರನಿಂದೆಗಳಿರೆ", 
        "8145": "ಪರಪುರುಷಾರ್ಥವನರಿಯದೆ ಕೆಟ್ಟ ನರಗುರಿಗಳು ನೀವು ಕೇಳಿರೋ:", 
        "8146": "ಪಿಸಿತ ನಡುವೆ ಇದ್ದ ಕಿರಾತಂಗೆ ಹೊಸ ವಾಸನೆಯ ಬಲ್ಲನೆ?", 
        "8147": "ಪುಣ್ಯಪಾಪವಿರಹಿತ ಕಂಡಾ, ಕ್ರೀಯೇಕೆ?", 
        "8148": "ಪುಷ್ಪವ ಕಂಡುದಕ್ಕೆ ಮತ್ತೆ ಮೂದಲೆ ಉಂಟೆ?", 
        "8149": "ಪೃಥ್ವಿಯನೆತ್ತಿತ್ತು ಬಿಂದು,", 
        "8150": "ಪೃಥ್ವಿ ಶುದ್ಧವೆಂಬೆನೆ? ಪೃಥ್ವಿ ಶುದ್ಧವಲ್ಲ.", 
        "8151": "ಪೆÇಡವಿಗೀಶ್ವರ ಗೌರಿಯೊ[ಡನೆ] ಮದುವೆಯಾದಂದು,", 
        "8152": "ಪ್ರಸಾದವ ನಂಬಿದಡೆ ಭಿಲ್ಲಮರಾಯನಂತೆ ನಂಬಬೇಕಯ್ಯಾ,", 
        "8153": "ಪ್ರಾಣ ಪ್ರಣವವೆಂಬರು, ಪ್ರಾಣಕ್ಕೂ ಪ್ರಣವಕ್ಕೂ ಏನು ಸಂಬಂಧ?", 
        "8154": "ಬಡತನಕ್ಕೆ ಉಂಬುವ ಚಿಂತೆ, ಉಣಲಾದರೆ ಉಡುವ ಚಿಂತೆ,", 
        "8155": "ಬಯಲ ಉದಕವ ಹಿಡಿದು ಮಜ್ಜನಕ್ಕೆರೆವೆನಯ್ಯ.", 
        "8156": "ಬರೆದು ಓದಿಸುವ ಅಕರಿಗಳೆಲ್ಲ ನೀವು ಕೇಳಿರೋ:", 
        "8157": "ಬೀಜ ಮೊಳೆವುದಲ್ಲದೆ ಮೊಳೆ ಮೊಳೆತುದುಂಟೆ?", 
        "8158": "ಬೆಟ್ಟದ ಲಿಂಗವ ಹಿರಿದು ಮಾಡಿ[ಕೊಂ]ಡು ಪರಿವ ಕೊಟ್ಟಿ ಮೂಳರಿರಾ,", 
        "8159": "ಬೆಟ್ಟದ ಲಿಂಗವ ಹಿರಿದುಮಾಡಿ,", 
        "8160": "ಬೆಲ್ಲಕ್ಕೆ ಚದುರಸವಲ್ಲದೆ ಸಿಹಿಗೆ ಚದುರಸವುಂಟೆ?", 
        "8161": "ಬೆಲ್ಲದ ಹೊಗೆಯನಿಕ್ಕಿ,", 
        "8162": "ಬೇಗ ಬೇಗನೆ ಗತಿಪಥದ ಜ್ಞಾನವ ಮಾಡಿಕೊಂಡು", 
        "8163": "ಬ್ರಹ್ಮ ಕುಮಾರ, ವಿಷ್ಣು ಅಬಳ,", 
        "8164": "ಬ್ರಹ್ಮಕ್ಕೆ ಬಾಯಿ ತೆರೆದು ಮಾತನಾಡಿ,", 
        "8165": "ಬ್ರಹ್ಮದ ಮಾತನಾಡಿ,", 
        "8166": "ಬ್ರಹ್ಮನ ಘನವೆಂತೆಂಬಿರಯ್ಯ, ಬ್ರಹ್ಮನು ಘನವಲ್ಲ,", 
        "8167": "ಬ್ರಹ್ಮನ ನಾವು ಬಲ್ಲೆವು, ವಿಷ್ಣುವ ನಾವು ಬಲ್ಲೆವು,", 
        "8168": "ಬ್ರಹ್ಮ ನಿಮ್ಮ ಬಲ್ಲಡೆ ನಿರ್ಮಾಲ್ಯವಹನೆ?", 
        "8169": "ಬ್ರಹ್ಮ ಮೊದಲನರಿಯ,", 
        "8170": "ಭಕ್ತ ಜಂಗಮದ ಪರಿಯ ಹೇಳಿಹೆನು ಕೇಳಿರಣ್ಣಾ:", 
        "8171": "ಭಕ್ತ ನಂಬಿದರೆ ಕೊಪ್ಪದ ರಾಮಯ್ಯನಂತೆ ನಂಬಬೇಕಯ್ಯಾ,", 
        "8172": "ಭಟಂಗೆ ಭೀತಿ ಉಳ್ಳನ್ನಕ್ಕ ರಣವ ಹೊಗಬಲ್ಲನೆ?", 
        "8173": "ಭವವಿರಹಿತಂಗೆ ಕರ್ಮಂಗಳ ಕೇಳಲೇತಕ್ಕೆ?", 
        "8174": "ಭವಿತನಕ್ಕೆ ಹೇಸಿ ಭಕ್ತನಾದ ಬಳಿಕ", 
        "8175": "ಭೂತ ಭೂತ ಹೊಡಯಿತೆಂದು", 
        "8176": "ಭೇದವ ಭೇದಿಸುವ ಚಿತ್ತವ,", 
        "8177": "ಭೋಗಕ್ಕೆ ಸಾಧನದ್ರವ್ಯ ಬಂದರೆ ಬೇಗ ಬೇಗ ಸಂಭ್ರಮಿಸುವರು,", 
        "8178": "ಮಕ್ಕಳು ಮರಿಗಳು ಸತ್ತು ನಷ್ಟವಾಗಿ,", 
        "8179": "ಮಡುವಿನಲ್ಲಿ ಮೊಗೆತಹೆನೆ? ಅಗ್ಗವಣಿ ಶುದ್ಧವಲ್ಲ.", 
        "8180": "ಮದ್ದ ತಿನ್ನಬೇಕಾದರೆ ವೈದ್ಯನಿದ್ದೆಡೆಗೆ ಹೋಗಿ,", 
        "8181": "ಮನ ಮಗ್ನವಾಗಿ, ಅರಿವನು ಘನಪ್ರಾಣಲಿಂಗದಲ್ಲಿ ಸವೆದು,", 
        "8182": "ಮರ ಬೇರು ಸಾರದಿಂದ ನಾನಾ ಶಾಖೆಗಳು ಪ[ಲ್ಲವಿ]ಸುವ ತೆರನಂತೆ,", 
        "8183": "ಮರುಳ ಕಂಡ ಕನಸಿನಂತೆ, ಆಕಾಶದಲ್ಲಿ ತೋರುವ ಲಿಪಿಯಂತೆ,", 
        "8184": "ಮಸ್ತಕದಲ್ಲಿ ರುದ್ರಾಕ್ಷಿಯಂ ಧರಿಸಿ", 
        "8185": "ಮಹಾಘನಲಿಂಗದ ನಿಜಘನವೆಂಬ ಚಿದ್ಘನಾತ್ಮಕ ಶರಣನ ಲೀಲೆಯಿಂದ", 
        "8186": "ಮಳಲ ಮರೆಯ ನೀರ ಒಲವರವಿಲ್ಲದೆ ತೋಡಿ,", 
        "8187": "ಮಾಡುವ ಭಕ್ತಂಗೆ ಮನವೆ ಸಾಕ್ಷಿ, ಹೊರಹೊಮ್ಮಿ ಬಯಲ ಹರಹಲೇನು?", 
        "8188": "ಮಾತಿನ ವೇದ, ನೀತಿಯ ಶಾಸ್ತ್ರ, ಘಾತಕದ ಕಥೆ", 
        "8189": "ಮಾತುಗಂಟಿತನದಿಂದ ಎಷ್ಟು ಮಾತನಾಡಿದಡೇನು ?", 
        "8190": "ಮಾತೆ ಸೂತಕವಾಗಿ ಸಂದೇಹವ ಮಾಡುವಲ್ಲಿ", 
        "8191": "ಮಾಯೆಯ ಬಸುರಲ್ಲಿ ಬಂದಾತ ಮಹೇಶ,", 
        "8192": "ಮೂರುವ ಮುಟ್ಟಿದೆ, ನಾಲ್ಕುವನಂಟಿದೆ,", 
        "8193": "ಮೂರು ಸ್ಥಲದ ಮೂಲವನರಿಯರು,", 
        "8194": "ಮೃಡನನೊಲಿಸಿ[ಹೆ]ನೆಂದು ನುಡಿವ ನಾಲಗೆಯೆಡಹಿತೆಯಲ್ಲಿ ಕಲ್ಲು ಕೊರಡೆ?", 
        "8195": "ಮೊಟ್ಟೆ ಮೊಟ್ಟೆ ಪತ್ರೆಯ ತಂದು ಒಟ್ಟಿ,", 
        "8196": "ರತಿಯಿಂದ ರತ್ನ, ಗತಿಯಿಂದ ವಾದ್ಯ,", 
        "8197": "ರತಿಯೆಂಬುದೆ ಪ್ರಾಣ, ಘಟವೆಂಬುದೆ ಕಲ್ಲು.", 
        "8198": "ಲಿಂಗತನುವಿಗೆ ಆತ್ಮತೇಜದ ಅಹಂಕಾರವುಂಟೆ ?", 
        "8199": "ಲಿಂಗತನುವಿಂಗೆ ಶೃಂಗಾರವಪ್ಪ ತೆರನಾವುದೆಂದಡೆ:", 
        "8200": "ಲಿಂಗದೊಳಗೆ ಜಂಗಮ ಸಲೆ ಸಂದಿರಬೇಕು,", 
        "8201": "ಲಿಂಗ ಬಿತ್ತು ಎತ್ತು ಎಂಬಿರಿ,", 
        "8202": "ಲಿಂಗವನರಿದೆಹೆನೆಂದಡೆ ಗುರುವಿಗೆ ಹಂಗು,", 
        "8203": "ಲಿಂಗವೆಂಬುದು ಕಾಯದ ತೊಡಕು,", 
        "8204": "ಲೋಹ ಗುಂಡಾದಲ್ಲಿ ಇರಿಯಬಲ್ಲುದೆರಿ", 
        "8205": "ವಚನಾರ್ಥವ ಕಂಡಹರೆಂದು", 
        "8206": "ವಸ್ತುವ ಕಾಬರೆಲ್ಲರು", 
        "8207": "ವಿಹಂಗಂಗೆ ಗುರಿಯಾಸೆಯೆಂದಡೆ ಸಂಚಾರವಿಲ್ಲದೆ ಚರಿಸಬಹುದೆ?", 
        "8208": "ವೀರಂಗೆ ರಣಾಗ್ರದ ಕದನ ಭೋರೆಂದು ಕಟ್ಟಿದಲ್ಲಿ", 
        "8209": "ವೇದಂಗಳೆಲ್ಲ ಬ್ರಹ್ಮನೆಂಜಲು,", 
        "8210": "ವೇದದಲುಳ್ಳಡೆ ಪ್ರಾಣಿವಧೆಯಪ್ಪುದೆ ?", 
        "8211": "ವೇದವನೋದಿದವರು ವಿಧಿಗೊಳಗಾದರಲ್ಲದೆ", 
        "8212": "ವೇದವ ಪಠಸುವಲ್ಲಿ, ಶಾಸ್ತ್ರವನೋದುವಲ್ಲಿ,", 
        "8213": "ವೇದವೇದಾಂತರ, ಶಾಸ್ತ್ರಸಂಪದರ, ಆಗಮಕ್ಕತೀತರ,", 
        "8214": "ಶರಣ ಸತಿ, ಲಿಂಗ ಪತಿ ಎಂಬರು.", 
        "8215": "ಶಿಖಿಯನೆ ಕಟ್ಟಿ, ಮಾಹೇಶ್ವರಿಕೆಯನೆ ಕೊಡುವರೆ,", 
        "8216": "ಶಿವಭಕ್ತನಾದ ಬಳಿಕ ಅನ್ಯಭಜನೆಯ ಮಾಡದಿರಬೇಕು.", 
        "8217": "ಶಿವಭಕ್ತರ ಮನೆಗೆ ಹೋಗಿ ಒರಳಕ್ಕಿಯನಾಯ್ದು ತಂದು,", 
        "8218": "ಶಿವಭಕ್ತಿ ಶಿವಾಚಾರ ಬೇಕಾದ ಭಕ್ತನು", 
        "8219": "ಶೀಲವಂತನೆಂಬವ ಶಿವದ್ರೋಹಿ,", 
        "8220": "ಶೀಲವಂತರು ಶೀಲವಂತರು ಎಂದು ಶೀಲದಲ್ಲಿ ಆಚರಿಸುವ ಅಣ್ಣಗ[ಳೇ]", 
        "8221": "ಶುಕ್ಲಶೋಣಿತಪಿಂಡೈಕ್ಯನ ಚಿತ್ತವಾಯು ಆರು ದಳದ ಪದ್ಮದಲ್ಲಿಹುದು.", 
        "8222": "ಶ್ರೀಗುರುಲಿಂಗಜಂಗಮದ ಲೀಲೆಯ ಧರಿಸಿ,", 
        "8223": "ಸಂದೇಹ ಮಾಡುವಲ್ಲಿ ಮಾತೇ ಸೂತಕವಾಗಿ", 
        "8224": "ಸಕಲಭೋಗ ವಿಲಾಸಿತ ಲಿಂಗಕ್ಕೆಂದಲ್ಲಿ ತನ್ನಂಗಕ್ಕೆ ಶೃಂಗಾರವುಂಟೆ ?", 
        "8225": "ಸತ್ತಡೆ ಸಂಗಡ ಹೊಳಿಸಿಕೊಂಬ ಲಿಂಗವು", 
        "8226": "ಸತ್ತರೆ ಸಂಗಾತ ಹೂಳಿಸಿಕೊಂಬ ಇಷ್ಟಲಿಂಗವ ಸಟೆಮಾಡಿ,", 
        "8227": "ಸಪ್ತಸಾಗರಗಳ ನಿಲ್ಲೆಂದು ನಿಲ್ಲಿಸಿ", 
        "8228": "ಸಮಯವ ಮಾಡಿ ಹಣವ ತೆಗೆಯಲೇತಕ್ಕೆ ?", 
        "8229": "ಸರ್ವಾಂಗಲಿಂಗವಾದ ಶರಣನ ಕಾಯ", 
        "8230": "ಸಸಿಗೆ ನೀರೆರೆದಡೆ ಹಸುರಾದಂತೆ,", 
        "8231": "ಸಹಜವಯ್ಯ ಶಿವಗಣಂಗಳ ನುಡಿ ಸತ್ಯವು.", 
        "8232": "ಸೃಷ್ಟಿಯ ಕಲ್ಪಿಸುವ ಕರ್ತ ಬ್ರಹ್ಮಂಗೆ ಶತಾಯುಗನೆಂಬ ಗಣಿತವಿದೇನು?", 
        "8233": "ಸೋಮವಾರ, ಹುಣ್ಣಿಮೆ, ಅಮವಾಸ್ಯೆ ಎಂದು ಉಪವಾಸವಿರ್ದು", 
        "8234": "ಸ್ಥಲಂಗಳ ನೋಡಿ ಕಂಡೆಹೆನೆಂದಡೆ, ಅಡಗಿದ ಮಡಕೆಯಲ್ಲ", 
        "8235": "ಸ್ವಲ್ಪ ಅಮೃತಾನ್ನವನೊಯ್ದು ಹುತ್ತವೆಂದು", 
        "8236": "ಹರತೇರು ಬಿತ್ತಿದ ಗಿಡವಿನ ಹೂವ್ವ ಕೊಯ್ದು", 
        "8237": "ಹರಿಗೆ ಚಕ್ರ ಡಾಣೆ, ಬ್ರಹ್ಮಂಗೆ ವೇದ ಪಾಶ,", 
        "8238": "ಹಸಿಯ ಸೊಪ್ಪು ಮುರಿದು ತರುವಾಗ", 
        "8239": "ಹಾಡಿ ಹಾಡುವ ಹರಕೆಯ ಕೇಡು,", 
        "8240": "ಹಿಂದಣ ಜನ್ಮದಲ್ಲಿ ಹಲು ಸುಕೃತಂಗಳಂ ಮಾಡಿಕೊಂಡ ದೆಸೆಯಿಂದ", 
        "8241": "ಹಿಡಿ ಪುಣ್ಯವ, ಬಿಡು ಪಾಪವ,", 
        "8242": "ಹಿತ್ತಿಲ ಸೊಪ್ಪಿಂಗೆ ನೀರ ಹೊಯಿದು,", 
        "8243": "ಹೂವ ಕೊಯ್ವ ಕುಕ್ಕೆ ಹರಿದು, ನೀರ ಹೊಯಿವ ಕುಡಿಕೆ ಒಡೆದು,", 
        "8244": "ಹೇಳುವ ಕೇಳುವ ಮಾತ ಕೇಳಿ,", 
        "8245": "ಹೊಡವುಂಟು ದೇವರ ತಲೆಯ ತಾಟಿಸಿಕೊಂಬರು", 
        "8246": "ಹೊಡವಡಲೇಕೆ, ಹಿಡಿದು ಪೂಜಿಸಲೇಕೆ,", 
        "8247": "ಹೊಲೆಯ ಹೊಲೆಯ ಎಂದಡೆ ಹೊಲೆಯರೆಂತಪ್ಪರಯ್ಯಾ?"
    }
}