{
    "details": {
        "ಅಂಕಿತ": "ನಿವೃತ್ತಿ ಸಂಗಯ್ಯ", 
        "ಒಡಹುಟ್ಟಿದವರು": "--", 
        "ಕಾಯಕ": "--", 
        "ಕಾಲ": "0", 
        "ಕಾಲವಾದ ಸ್ಥಳ": "--", 
        "ಕೃತಿಯ ವೈಶಿಷ್ಟ್ಯ": "ಆಸೆಯನು ಧಿಕ್ಕರಿಸಿ ನಿರಾಸೆಯಲಿ ನಡೆದವರ ಸರಿಯೆಂಬ ಎಂದಿರುವನು. ಚಾತುರ್ವರ್ಣದವರು ಶಿವಭಕ್ತರಾದ ಮೇಲೆ ತಮ್ಮ ಪೂರ್ವ ಜಾತಿ ಸಂಬಂಧವನ್ನು ಬಿಡಬೇಕೆಂದಿರುವನು. ಪರಧನ, ಪರನ್ನ, ಪರಸ್ತ್ರೀಯರ ಆಸೆ ಬಿಡದವರನ್ನು ಶರಣರೆಂದು ಹೇಗೆ ಕರೆಯಲಿ? ಎಂದಿರುವನು", 
        "ಗ್ರಾಮ": "--", 
        "ಜನ್ಮ ಸ್ಥಳ": "--", 
        "ಜಿಲ್ಲೆ": "--", 
        "ತಂದೆ ಹೆಸರು": "--", 
        "ತಾಯಿ ಹೆಸರು": "--", 
        "ತಾಲ್ಲೂಕು": "--", 
        "ಪತಿ: ಪತ್ನಿಯ ಹೆಸರು": "--", 
        "ಮಕ್ಕಳು: ಅವರ ಹೆಸರು": "--", 
        "ಲಭ್ಯ ವಚನಗಳ ಸಂಖ್ಯೆ": "3", 
        "ವಚನಕಾರರ ಹೆಸರು": "ನಿವೃತ್ತಿ ಸಂಗಯ್ಯ", 
        "ವಚನಗಳಲ್ಲದೆ ಇತರ ಲಭ್ಯ ಕೃತಿಗಳು": "--", 
        "ಸಮಾಧಿ ಇರುವ ಸ್ಥಳ": "--"
    }, 
    "id": "84", 
    "name": "ನಿವೃತ್ತಿ ಸಂಗಯ್ಯ", 
    "vachana": {
        "13061": "ಪರಧನ ಪರಾನ್ನ ಪರಸ್ತ್ರೀಯರಾಸೆ ಬಿಡದು, ಶರಣನೆಂತೆಂಬೆ ಮರುಳೆ?", 
        "13063": "ಬ್ರಾಹ್ಮಣ ಶಿವಭಕ್ತನಾದ ಬಳಿಕ ಬ್ರಾಹ್ಮಣರ ಬೆರಸಲಾಗದು.", 
        "13065": "ಸಚರಾಚರವೆಲ್ಲಕ್ಕೆ ಆಸೆಯೆ ಪ್ರಾಣ."
    }
}